Workbook
Name Architecture_Practice_USA: #REF!
Name Architecture_Practice_USA: #REF!
Name Architecture_Practice_USA: #REF!
Name Architecture_Practice_USA: Picklist!#REF!
Name Cloud_Practice_India: #REF!
Name Cloud_Practice_India: #REF!
Name Cloud_Practice_India: #REF!
Name Cloud_Practice_India: Picklist!#REF!
Name Cloud_Practice_USA: #REF!
Name Cloud_Practice_USA: #REF!
Name Cloud_Practice_USA: #REF!
Name Cloud_Practice_USA: Picklist!#REF!
Name CPM_Practice_India: #REF!
Name CPM_Practice_India: #REF!
Name CPM_Practice_India: #REF!
Name CPM_Practice_India: Picklist!#REF!
Name CPM_Practice_USA: #REF!
Name CPM_Practice_USA: #REF!
Name CPM_Practice_USA: #REF!
Name CPM_Practice_USA: Picklist!#REF!
Name EPM_Practice_India: #REF!
Name EPM_Practice_India: #REF!
Name EPM_Practice_India: #REF!
Name EPM_Practice_India: Picklist!#REF!
Name EPM_Practice_USA: #REF!
Name EPM_Practice_USA: #REF!
Name EPM_Practice_USA: #REF!
Name EPM_Practice_USA: Picklist!#REF!
Name ERP_Practice_India: #REF!
Name ERP_Practice_India: #REF!
Name ERP_Practice_India: #REF!
Name ERP_Practice_India: Picklist!#REF!
Name ERP_Practice_USA: #REF!
Name ERP_Practice_USA: #REF!
Name ERP_Practice_USA: #REF!
Name ERP_Practice_USA: Picklist!#REF!
Name Functional_Practice_USA: #REF!
Name Functional_Practice_USA: #REF!
Name Functional_Practice_USA: #REF!
Name Functional_Practice_USA: Picklist!#REF!
Name PS_Practice_USA: #REF!
Name PS_Practice_USA: #REF!
Name PS_Practice_USA: #REF!
Name PS_Practice_USA: Picklist!#REF!
Name TS_Practice_India: #REF!
Name TS_Practice_India: #REF!
Name TS_Practice_India: #REF!
Name TS_Practice_India: Picklist!#REF!
Name TS_Practice_USA: #REF!
Name TS_Practice_USA: #REF!
Name TS_Practice_USA: #REF!
Name TS_Practice_USA: Picklist!#REF!

Sheet Summary
A1: General Information | F1: Blended Rate (w/Discount) | G1: Net Margin $ (w/Discount) | H1: Net Margin % (w/Discount)
A3: Client Name (Partner Name): | B3: ='Pricing Details'!B1 -> IEEE | E3: US (Goal $195) | F3: ='Pricing Details'!AT51 -> 230 | G3: ='Pricing Details'!AU51 -> 20150 | H3: ='Pricing Details'!AV51 -> 0.2826087
A4: Capability: | B4: =IF('Pricing Details'!B2=0," ",'Pricing Details'!B2) -> IT
A5: Service: | B5: =IF('Pricing Details'!B3=0," ",'Pricing Details'!B3) -> Change Management | E5: India (Goal $50) | F5: ='Pricing Details'!AT52 -> 0 | G5: ='Pricing Details'!AU52 -> 0 | H5: ='Pricing Details'!AV52 -> 0
A6: Type: | B6: ='Pricing Details'!F2 -> Expansion
A7: Pricing Date: | B7: ='Pricing Details'!D1 -> 46013 | E7: Total | F7: ='Pricing Details'!AT53 -> 230 | G7: ='Pricing Details'!AU53 -> 20150 | H7: ='Pricing Details'!AV53 -> 0.2826087
A8: Sales Rep: | B8: =IF('Pricing Details'!D2=0," ",'Pricing Details'!D2) -> Camryn Barry
A9: Presales / Delivery: | B9: =IF('Pricing Details'!D3=0," ",'Pricing Details'!D3) -> Jai Jain
A10: Engagement Lead: | B10: =IF('Pricing Details'!D4=0," ",'Pricing Details'!D4) -> Melissa O'Blenis
A12: Fees
A14: Contract Type: | B14: ='Pricing Details'!B4 -> T&M
A15: Discount Type: | B15: ='Pricing Details'!AR4 -> Hourly Rate
A16: Total Fees: | B16: ='Pricing Details'!AS44 -> 85250
A17: Total Discount: | B17: =IF('Pricing Details'!AR4="Bottom Line",'Pricing Details'!$AS$45,'Pricing Details'!$AS$44-'Pricing Details'!$AU$44) -> 13950
A18: Total Discounted Fee: | B18: =IF('Pricing Details'!$AR$4="Bottom Line",'Pricing Details'!AU45,'Pricing Details'!AU44) -> 71300

Sheet Pricing Details
A1: Client Name (Partner Name): | B1: IEEE | C1: Pricing Date: | D1: 46013 | F1: v1.7.6 | H1: Cells with purple headers can be edited
A2: Capability/Practice Area: | B2: IT | C2: Sales Rep: | D2: Camryn Barry | E2: Type: | F2: Expansion
A3: Service /Project Type: | B3: Change Management | C3: Presales/Delivery: | D3: Jai Jain | E3: Risk Profile: | F3: Low
A4: Contract Type: | B4: T&M | C4: Engagement Lead: | D4: Melissa O'Blenis | E4: Project Start Date: | F4: 46055 | G4: *If you need more than 4 months, unhide the columns between J & AP | AQ4: Discount Type | AR4: Hourly Rate | AS4: NOTE: Hourly Rate and Bottom Line discounts cannot be combined.
A5: Practice | B5: Certinia Resource Role (role required for the project if TBD; resource's actual role if staffed at the time of pricing) | C5: Project Role (description of skill/area needed, name of resource) If Subcontractor include Resource Name and Company and Certinia Resource Role. | D5: Potential Resource | E5: Resource Location | F5: Standard Hourly Rate | G5: =EOMONTH(F4,0) -> 46081 | H5: =EOMONTH(G5,1) -> 46112 | I5: =EOMONTH(H5,1) -> 46142 | J5: =EOMONTH(I5,1) -> 46173 | K5: =EOMONTH(J5,1) -> 46203 | L5: =EOMONTH(K5,1) -> 46234 | M5: =EOMONTH(L5,1) -> 46265 | N5: =EOMONTH(M5,1) -> 46295 | O5: =EOMONTH(N5,1) -> 46326 | ... AP5: =EOMONTH(AO5,1) -> 47149 | AQ5: Discount % Applied by Sales Team | AR5: Total Hours (by Role) | AS5: Total Fee (by Role) | AT5: Sales Discount Applied (by Role) | AU5: Total Fee (w/Rate Discount) | AV5: Hourly Rate after Discount (Hourly) | AW5: Hourly Rate after Discount (Bottom Line) | AX5: Net Margin % by Role | BI5: Average Cost by Role | BJ5: Total Net Cost by Role | BK5: Total Net Margin by Role | BL5: Net Margin % by Role
G6: Month 1 | H6: Month 2 | I6: Month 3 | J6: Month 4 | K6: Month 5 | L6: Month 6 | M6: Month 7 | N6: Month 8 | O6: Month 9 | P6: Month 10 | Q6: Month 11 | R6: Month 12 | S6: Month 13 | T6: Month 14 | U6: Month 15 | V6: Month 16 | W6: Month 17 | X6: Month 18 | Y6: Month 19 | Z6: Month 20 | AA6: Month 21 | AB6: Month 22 | AC6: Month 23 | AD6: Month 24 | AE6: Month 25 | AF6: Month 26 | AG6: Month 27 | AH6: Month 28 | AI6: Month 29 | AJ6: Month 30 | AK6: Month 31 | AL6: Month 32 | AM6: Month 33 | AN6: Month 34 | AO6: Month 35 | AP6: Month 36
G7: =_xlfn.XLOOKUP(G$5,Picklist!$T$2:$T$61,Picklist!$U$2:$U$61) -> 152 | H7: =_xlfn.XLOOKUP(H$5,Picklist!$T$2:$T$61,Picklist!$U$2:$U$61) -> 176 | I7: =_xlfn.XLOOKUP(I$5,Picklist!$T$2:$T$61,Picklist!$U$2:$U$61) -> 176 | J7: =_xlfn.XLOOKUP(J$5,Picklist!$T$2:$T$61,Picklist!$U$2:$U$61) -> 160 | K7: =_xlfn.XLOOKUP(K$5,Picklist!$T$2:$T$61,Picklist!$U$2:$U$61) -> 176 | L7: =_xlfn.XLOOKUP(L$5,Picklist!$T$2:$T$61,Picklist!$U$2:$U$61) -> 176 | M7: =_xlfn.XLOOKUP(M$5,Picklist!$T$2:$T$61,Picklist!$U$2:$U$61) -> 168 | N7: =_xlfn.XLOOKUP(N$5,Picklist!$T$2:$T$61,Picklist!$U$2:$U$61) -> 168 | ... AP7: =_xlfn.XLOOKUP(AP$5,Picklist!$T$2:$T$61,Picklist!$U$2:$U$61) -> 176
G8: Phase | H8: Phase | I8: Phase | J8: Phase | K8: Phase | L8: Phase | M8: Phase | N8: Phase | O8: Phase | P8: Phase | Q8: Phase | R8: Phase | S8: Phase | T8: Phase | U8: Phase | V8: Phase | W8: Phase | X8: Phase | Y8: Phase | Z8: Phase | AA8: Phase | AB8: Phase | AC8: Phase | AD8: Phase | AE8: Phase | AF8: Phase | AG8: Phase | AH8: Phase | AI8: Phase | AJ8: Phase | AK8: Phase | AL8: Phase | AM8: Phase | AN8: Phase | AO8: Phase | AP8: Phase
A9: EPM_Practice_USA | B9: Sr. Change Manager | C9: Sr. Change Manager | D9: Melissa O'Blenis | E9: {=IFERROR(INDEX(_xlfn.TEXTSPLIT(A9,"_"),3),"")} -> USA | F9: =_xlfn.XLOOKUP(_xlfn.CONCAT(A9,B9),Picklist!$O$3:$O$332,Picklist!$P$3:$P$332,"Choose Existing Role",0) -> 275 | G9: 50 | H9: 80 | I9: 90 | J9: 90 | AQ9: 0.16363 | AR9: =SUM(G9:AP9) -> 310 | AS9: =IFERROR((F9*AR9),0) -> 85250 | AT9: =ROUND((-AS9*AQ9),2) -> -13949.46 | AU9: =AR9*AV9 -> 71300 | AV9: =IFERROR(ROUND((F9*(1-AQ9)),2),0) -> 230 | AW9: =IFERROR(IF($AR$4="Hourly Rate",0,ROUND((F9*(1-$AQ$45)),2)),0) -> 0 | AX9: =BL9 -> 0.2826087 | BI9: =_xlfn.XLOOKUP((_xlfn.CONCAT(A9,B9)),Picklist!$O$3:$O$292,Picklist!$Q$3:$Q$292,"",0) -> 165 | BJ9: =IFERROR(AR9*BI9,0) -> 51150 | BK9: =(AU9*(1-$AQ$45))-BJ9 -> 20150 | BL9: =IFERROR(((AU9*(1-$AQ$45))-BJ9)/(AU9*(1-$AQ$45)),0) -> 0.2826087
E10: {=IFERROR(INDEX(_xlfn.TEXTSPLIT(A10,"_"),3),"")} | F10: =_xlfn.XLOOKUP(_xlfn.CONCAT(A10,B10),Picklist!$O$3:$O$332,Picklist!$P$3:$P$332,"Choose Existing Role",0) -> 0 | AQ10: 0 | AR10: =SUM(G10:AP10) -> 0 | AS10: =IFERROR((F10*AR10),0) -> 0 | AT10: =ROUND((-AS10*AQ10),2) -> 0 | AU10: =AR10*AV10 -> 0 | AV10: =IFERROR(ROUND((F10*(1-AQ10)),2),0) -> 0 | AW10: =IFERROR(IF($AR$4="Hourly Rate",0,ROUND((F10*(1-$AQ$45)),2)),0) -> 0 | AX10: =BL10 -> 0 | BI10: =_xlfn.XLOOKUP((_xlfn.CONCAT(A10,B10)),Picklist!$O$3:$O$292,Picklist!$Q$3:$Q$292,"",0) -> 0 | BJ10: =IFERROR(AR10*BI10,0) -> 0 | BK10: =(AU10*(1-$AQ$45))-BJ10 -> 0 | BL10: =IFERROR(((AU10*(1-$AQ$45))-BJ10)/(AU10*(1-$AQ$45)),0) -> 0
E11: {=IFERROR(INDEX(_xlfn.TEXTSPLIT(A11,"_"),3),"")} | F11: =_xlfn.XLOOKUP(_xlfn.CONCAT(A11,B11),Picklist!$O$3:$O$332,Picklist!$P$3:$P$332,"Choose Existing Role",0) -> 0 | AQ11: 0 | AR11: =SUM(G11:AP11) -> 0 | AS11: =IFERROR((F11*AR11),0) -> 0 | AT11: =ROUND((-AS11*AQ11),2) -> 0 | AU11: =AR11*AV11 -> 0 | AV11: =IFERROR(ROUND((F11*(1-AQ11)),2),0) -> 0 | AW11: =IFERROR(IF($AR$4="Hourly Rate",0,ROUND((F11*(1-$AQ$45)),2)),0) -> 0 | AX11: =BL11 -> 0 | BI11: =_xlfn.XLOOKUP((_xlfn.CONCAT(A11,B11)),Picklist!$O$3:$O$292,Picklist!$Q$3:$Q$292,"",0) -> 0 | BJ11: =IFERROR(AR11*BI11,0) -> 0 | BK11: =(AU11*(1-$AQ$45))-BJ11 -> 0 | BL11: =IFERROR(((AU11*(1-$AQ$45))-BJ11)/(AU11*(1-$AQ$45)),0) -> 0
E12: {=IFERROR(INDEX(_xlfn.TEXTSPLIT(A12,"_"),3),"")} | F12: =_xlfn.XLOOKUP(_xlfn.CONCAT(A12,B12),Picklist!$O$3:$O$332,Picklist!$P$3:$P$332,"Choose Existing Role",0) -> 0 | AQ12: 0 | AR12: =SUM(G12:AP12) -> 0 | AS12: =IFERROR((F12*AR12),0) -> 0 | AT12: =ROUND((-AS12*AQ12),2) -> 0 | AU12: =AR12*AV12 -> 0 | AV12: =IFERROR(ROUND((F12*(1-AQ12)),2),0) -> 0 | AW12: =IFERROR(IF($AR$4="Hourly Rate",0,ROUND((F12*(1-$AQ$45)),2)),0) -> 0 | AX12: =BL12 -> 0 | BI12: =_xlfn.XLOOKUP((_xlfn.CONCAT(A12,B12)),Picklist!$O$3:$O$292,Picklist!$Q$3:$Q$292,"",0) -> 0 | BJ12: =IFERROR(AR12*BI12,0) -> 0 | BK12: =(AU12*(1-$AQ$45))-BJ12 -> 0 | BL12: =IFERROR(((AU12*(1-$AQ$45))-BJ12)/(AU12*(1-$AQ$45)),0) -> 0
E13: {=IFERROR(INDEX(_xlfn.TEXTSPLIT(A13,"_"),3),"")} | F13: =_xlfn.XLOOKUP(_xlfn.CONCAT(A13,B13),Picklist!$O$3:$O$332,Picklist!$P$3:$P$332,"Choose Existing Role",0) -> 0 | AQ13: 0 | AR13: =SUM(G13:AP13) -> 0 | AS13: =IFERROR((F13*AR13),0) -> 0 | AT13: =ROUND((-AS13*AQ13),2) -> 0 | AU13: =AR13*AV13 -> 0 | AV13: =IFERROR(ROUND((F13*(1-AQ13)),2),0) -> 0 | AW13: =IFERROR(IF($AR$4="Hourly Rate",0,ROUND((F13*(1-$AQ$45)),2)),0) -> 0 | AX13: =BL13 -> 0 | BI13: =_xlfn.XLOOKUP((_xlfn.CONCAT(A13,B13)),Picklist!$O$3:$O$292,Picklist!$Q$3:$Q$292,"",0) -> 0 | BJ13: =IFERROR(AR13*BI13,0) -> 0 | BK13: =(AU13*(1-$AQ$45))-BJ13 -> 0 | BL13: =IFERROR(((AU13*(1-$AQ$45))-BJ13)/(AU13*(1-$AQ$45)),0) -> 0
E14: {=IFERROR(INDEX(_xlfn.TEXTSPLIT(A14,"_"),3),"")} | F14: =_xlfn.XLOOKUP(_xlfn.CONCAT(A14,B14),Picklist!$O$3:$O$332,Picklist!$P$3:$P$332,"Choose Existing Role",0) -> 0 | AQ14: 0 | AR14: =SUM(G14:AP14) -> 0 | AS14: =IFERROR((F14*AR14),0) -> 0 | AT14: =ROUND((-AS14*AQ14),2) -> 0 | AU14: =AR14*AV14 -> 0 | AV14: =IFERROR(ROUND((F14*(1-AQ14)),2),0) -> 0 | AW14: =IFERROR(IF($AR$4="Hourly Rate",0,ROUND((F14*(1-$AQ$45)),2)),0) -> 0 | AX14: =BL14 -> 0 | BI14: =_xlfn.XLOOKUP((_xlfn.CONCAT(A14,B14)),Picklist!$O$3:$O$292,Picklist!$Q$3:$Q$292,"",0) -> 0 | BJ14: =IFERROR(AR14*BI14,0) -> 0 | BK14: =(AU14*(1-$AQ$45))-BJ14 -> 0 | BL14: =IFERROR(((AU14*(1-$AQ$45))-BJ14)/(AU14*(1-$AQ$45)),0) -> 0
E15: {=IFERROR(INDEX(_xlfn.TEXTSPLIT(A15,"_"),3),"")} | F15: =_xlfn.XLOOKUP(_xlfn.CONCAT(A15,B15),Picklist!$O$3:$O$332,Picklist!$P$3:$P$332,"Choose Existing Role",0) -> 0 | AQ15: 0 | AR15: =SUM(G15:AP15) -> 0 | AS15: =IFERROR((F15*AR15),0) -> 0 | AT15: =ROUND((-AS15*AQ15),2) -> 0 | AU15: =AR15*AV15 -> 0 | AV15: =IFERROR(ROUND((F15*(1-AQ15)),2),0) -> 0 | AW15: =IFERROR(IF($AR$4="Hourly Rate",0,ROUND((F15*(1-$AQ$45)),2)),0) -> 0 | AX15: =BL15 -> 0 | BI15: =_xlfn.XLOOKUP((_xlfn.CONCAT(A15,B15)),Picklist!$O$3:$O$292,Picklist!$Q$3:$Q$292,"",0) -> 0 | BJ15: =IFERROR(AR15*BI15,0) -> 0 | BK15: =(AU15*(1-$AQ$45))-BJ15 -> 0 | BL15: =IFERROR(((AU15*(1-$AQ$45))-BJ15)/(AU15*(1-$AQ$45)),0) -> 0
E16: {=IFERROR(INDEX(_xlfn.TEXTSPLIT(A16,"_"),3),"")} | F16: =_xlfn.XLOOKUP(_xlfn.CONCAT(A16,B16),Picklist!$O$3:$O$332,Picklist!$P$3:$P$332,"Choose Existing Role",0) -> 0 | AQ16: 0 | AR16: =SUM(G16:AP16) -> 0 | AS16: =IFERROR((F16*AR16),0) -> 0 | AT16: =ROUND((-AS16*AQ16),2) -> 0 | AU16: =AR16*AV16 -> 0 | AV16: =IFERROR(ROUND((F16*(1-AQ16)),2),0) -> 0 | AW16: =IFERROR(IF($AR$4="Hourly Rate",0,ROUND((F16*(1-$AQ$45)),2)),0) -> 0 | AX16: =BL16 -> 0 | BI16: =_xlfn.XLOOKUP((_xlfn.CONCAT(A16,B16)),Picklist!$O$3:$O$292,Picklist!$Q$3:$Q$292,"",0) -> 0 | BJ16: =IFERROR(AR16*BI16,0) -> 0 | BK16: =(AU16*(1-$AQ$45))-BJ16 -> 0 | BL16: =IFERROR(((AU16*(1-$AQ$45))-BJ16)/(AU16*(1-$AQ$45)),0) -> 0
E17: {=IFERROR(INDEX(_xlfn.TEXTSPLIT(A17,"_"),3),"")} | F17: =_xlfn.XLOOKUP(_xlfn.CONCAT(A17,B17),Picklist!$O$3:$O$332,Picklist!$P$3:$P$332,"Choose Existing Role",0) -> 0 | AQ17: 0 | AR17: =SUM(G17:AP17) -> 0 | AS17: =IFERROR((F17*AR17),0) -> 0 | AT17: =ROUND((-AS17*AQ17),2) -> 0 | AU17: =AR17*AV17 -> 0 | AV17: =IFERROR(ROUND((F17*(1-AQ17)),2),0) -> 0 | AW17: =IFERROR(IF($AR$4="Hourly Rate",0,ROUND((F17*(1-$AQ$45)),2)),0) -> 0 | AX17: =BL17 -> 0 | BI17: =_xlfn.XLOOKUP((_xlfn.CONCAT(A17,B17)),Picklist!$O$3:$O$292,Picklist!$Q$3:$Q$292,"",0) -> 0 | BJ17: =IFERROR(AR17*BI17,0) -> 0 | BK17: =(AU17*(1-$AQ$45))-BJ17 -> 0 | BL17: =IFERROR(((AU17*(1-$AQ$45))-BJ17)/(AU17*(1-$AQ$45)),0) -> 0
E18: {=IFERROR(INDEX(_xlfn.TEXTSPLIT(A18,"_"),3),"")} | F18: =_xlfn.XLOOKUP(_xlfn.CONCAT(A18,B18),Picklist!$O$3:$O$332,Picklist!$P$3:$P$332,"Choose Existing Role",0) -> 0 | AQ18: 0 | AR18: =SUM(G18:AP18) -> 0 | AS18: =IFERROR((F18*AR18),0) -> 0 | AT18: =ROUND((-AS18*AQ18),2) -> 0 | AU18: =AR18*AV18 -> 0 | AV18: =IFERROR(ROUND((F18*(1-AQ18)),2),0) -> 0 | AW18: =IFERROR(IF($AR$4="Hourly Rate",0,ROUND((F18*(1-$AQ$45)),2)),0) -> 0 | AX18: =BL18 -> 0 | BI18: =_xlfn.XLOOKUP((_xlfn.CONCAT(A18,B18)),Picklist!$O$3:$O$292,Picklist!$Q$3:$Q$292,"",0) -> 0 | BJ18: =IFERROR(AR18*BI18,0) -> 0 | BK18: =(AU18*(1-$AQ$45))-BJ18 -> 0 | BL18: =IFERROR(((AU18*(1-$AQ$45))-BJ18)/(AU18*(1-$AQ$45)),0) -> 0
E19: {=IFERROR(INDEX(_xlfn.TEXTSPLIT(A19,"_"),3),"")} | F19: =_xlfn.XLOOKUP(_xlfn.CONCAT(A19,B19),Picklist!$O$3:$O$332,Picklist!$P$3:$P$332,"Choose Existing Role",0) -> 0 | AQ19: 0 | AR19: =SUM(G19:AP19) -> 0 | AS19: =IFERROR((F19*AR19),0) -> 0 | AT19: =ROUND((-AS19*AQ19),2) -> 0 | AU19: =AR19*AV19 -> 0 | AV19: =IFERROR(ROUND((F19*(1-AQ19)),2),0) -> 0 | AW19: =IFERROR(IF($AR$4="Hourly Rate",0,ROUND((F19*(1-$AQ$45)),2)),0) -> 0 | AX19: =BL19 -> 0 | BI19: =_xlfn.XLOOKUP((_xlfn.CONCAT(A19,B19)),Picklist!$O$3:$O$292,Picklist!$Q$3:$Q$292,"",0) -> 0 | BJ19: =IFERROR(AR19*BI19,0) -> 0 | BK19: =(AU19*(1-$AQ$45))-BJ19 -> 0 | BL19: =IFERROR(((AU19*(1-$AQ$45))-BJ19)/(AU19*(1-$AQ$45)),0) -> 0
E20: {=IFERROR(INDEX(_xlfn.TEXTSPLIT(A20,"_"),3),"")} | F20: =_xlfn.XLOOKUP(_xlfn.CONCAT(A20,B20),Picklist!$O$3:$O$332,Picklist!$P$3:$P$332,"Choose Existing Role",0) -> 0 | AQ20: 0 | AR20: =SUM(G20:AP20) -> 0 | AS20: =IFERROR((F20*AR20),0) -> 0 | AT20: =ROUND((-AS20*AQ20),2) -> 0 | AU20: =AR20*AV20 -> 0 | AV20: =IFERROR(ROUND((F20*(1-AQ20)),2),0) -> 0 | AW20: =IFERROR(IF($AR$4="Hourly Rate",0,ROUND((F20*(1-$AQ$45)),2)),0) -> 0 | AX20: =BL20 -> 0 | BI20: =_xlfn.XLOOKUP((_xlfn.CONCAT(A20,B20)),Picklist!$O$3:$O$292,Picklist!$Q$3:$Q$292,"",0) -> 0 | BJ20: =IFERROR(AR20*BI20,0) -> 0 | BK20: =(AU20*(1-$AQ$45))-BJ20 -> 0 | BL20: =IFERROR(((AU20*(1-$AQ$45))-BJ20)/(AU20*(1-$AQ$45)),0) -> 0
E21: {=IFERROR(INDEX(_xlfn.TEXTSPLIT(A21,"_"),3),"")} | F21: =_xlfn.XLOOKUP(_xlfn.CONCAT(A21,B21),Picklist!$O$3:$O$332,Picklist!$P$3:$P$332,"Choose Existing Role",0) -> 0 | AQ21: 0 | AR21: =SUM(G21:AP21) -> 0 | AS21: =IFERROR((F21*AR21),0) -> 0 | AT21: =ROUND((-AS21*AQ21),2) -> 0 | AU21: =AR21*AV21 -> 0 | AV21: =IFERROR(ROUND((F21*(1-AQ21)),2),0) -> 0 | AW21: =IFERROR(IF($AR$4="Hourly Rate",0,ROUND((F21*(1-$AQ$45)),2)),0) -> 0 | AX21: =BL21 -> 0 | BI21: =_xlfn.XLOOKUP((_xlfn.CONCAT(A21,B21)),Picklist!$O$3:$O$292,Picklist!$Q$3:$Q$292,"",0) -> 0 | BJ21: =IFERROR(AR21*BI21,0) -> 0 | BK21: =(AU21*(1-$AQ$45))-BJ21 -> 0 | BL21: =IFERROR(((AU21*(1-$AQ$45))-BJ21)/(AU21*(1-$AQ$45)),0) -> 0
... E43: {=IFERROR(INDEX(_xlfn.TEXTSPLIT(A43,"_"),3),"")} | F43: =_xlfn.XLOOKUP(_xlfn.CONCAT(A43,B43),Picklist!$O$3:$O$332,Picklist!$P$3:$P$332,"Choose Existing Role",0) -> 0 | AQ43: 0 | AR43: =SUM(G43:AP43) -> 0 | AS43: =IFERROR((F43*AR43),0) -> 0 | AT43: =ROUND((-AS43*AQ43),2) -> 0 | AU43: =AR43*AV43 -> 0 | AV43: =IFERROR(ROUND((F43*(1-AQ43)),2),0) -> 0 | AW43: =IFERROR(IF($AR$4="Hourly Rate",0,ROUND((F43*(1-$AQ$45)),2)),0) -> 0 | AX43: =BL43 -> 0 | BI43: =_xlfn.XLOOKUP((_xlfn.CONCAT(A43,B43)),Picklist!$O$3:$O$292,Picklist!$Q$3:$Q$292,"",0) -> 0 | BJ43: =IFERROR(AR43*BI43,0) -> 0 | BK43: =(AU43*(1-$AQ$45))-BJ43 -> 0 | BL43: =IFERROR(((AU43*(1-$AQ$45))-BJ43)/(AU43*(1-$AQ$45)),0) -> 0
A44: *If you need more than 10 resources, unhide the rows between 19 & 44 | F44: =IFERROR(AVERAGEIF(F9:F43,"<>0"),0) -> 275 | G44: =SUM(G9:G43) -> 50 | H44: =SUM(H9:H43) -> 80 | I44: =SUM(I9:I43) -> 90 | J44: =SUM(J9:J43) -> 90 | K44: =SUM(K9:K43) -> 0 | L44: =SUM(L9:L43) -> 0 | M44: =SUM(M9:M43) -> 0 | N44: =SUM(N9:N43) -> 0 | ... AP44: =SUM(AP9:AP43) -> 0 | AQ44: =IFERROR(AVERAGEIF(AQ9:AQ43,"<>0"),0) -> 0.16363 | AR44: =SUM(AR9:AR43) -> 310 | AS44: =SUM(AS9:AS43) -> 85250 | AT44: =SUM(AT9:AT43) -> -13949.46 | AU44: =SUM(AU9:AU43) -> 71300 | BI44: =AVERAGEIF(BI9:BI43,"<>0") -> 165 | BJ44: =SUM(BJ9:BJ43) -> 51150 | BK44: =SUM(BK9:BK43) -> 20150 | BL44: =IFERROR((AU44-BJ44)/AU44,0) -> 0.2826087
AR45: Bottom Line Disc % | AS45: =ROUND((-AS44*AQ45),2) -> 0 | AT45: Bottom Line Discount Amount | AU45: =IFERROR(IF($AR$4="Hourly Rate",0,AS44+AS45),0) -> 0 | AV45: Total Fee w/Bottom Line Discount
F46: Average Rate | G46: Monthly Total Hours | H46: Monthly Total Hours | I46: Monthly Total Hours | J46: Monthly Total Hours | K46: Monthly Total Hours | L46: Monthly Total Hours | M46: Monthly Total Hours | N46: Monthly Total Hours | O46: Monthly Total Hours | P46: Monthly Total Hours | Q46: Monthly Total Hours | R46: Monthly Total Hours | S46: Monthly Total Hours | T46: Monthly Total Hours | U46: Monthly Total Hours | V46: Monthly Total Hours | W46: Monthly Total Hours | X46: Monthly Total Hours | Y46: Monthly Total Hours | Z46: Monthly Total Hours | AA46: Monthly Total Hours | AB46: Monthly Total Hours | AC46: Monthly Total Hours | AD46: Monthly Total Hours | AE46: Monthly Total Hours | AF46: Monthly Total Hours | AG46: Monthly Total Hours | AH46: Monthly Total Hours | AI46: Monthly Total Hours | AJ46: Monthly Total Hours | AK46: Monthly Total Hours | AL46: Monthly Total Hours | AM46: Monthly Total Hours | AN46: Monthly Total Hours | AO46: Monthly Total Hours | AP46: Monthly Total Hours | AQ46: Average Discount Applied | AR46: Total Hours | AS46: TCV | AT46: Total Discount | AU46: TCV (w/Discount) | BI46: Average Cost | BJ46: Total Cost | BK46: Total Margin | BL46: Margin %
F47: TCV By Month | G47: =(SUMPRODUCT(G9:G43,$AV$9:$AV$43))-(ROUND(((SUMPRODUCT(G9:G43,$AV9:$AV43))*$AQ$45),2)) -> 11500 | H47: =(SUMPRODUCT(H9:H43,$AV$9:$AV$43))-(ROUND(((SUMPRODUCT(H9:H43,$AV9:$AV43))*$AQ$45),2)) -> 18400 | I47: =(SUMPRODUCT(I9:I43,$AV$9:$AV$43))-(ROUND(((SUMPRODUCT(I9:I43,$AV9:$AV43))*$AQ$45),2)) -> 20700 | J47: =(SUMPRODUCT(J9:J43,$AV$9:$AV$43))-(ROUND(((SUMPRODUCT(J9:J43,$AV9:$AV43))*$AQ$45),2)) -> 20700 | K47: =(SUMPRODUCT(K9:K43,$AV$9:$AV$43))-(ROUND(((SUMPRODUCT(K9:K43,$AV9:$AV43))*$AQ$45),2)) -> 0 | L47: =(SUMPRODUCT(L9:L43,$AV$9:$AV$43))-(ROUND(((SUMPRODUCT(L9:L43,$AV9:$AV43))*$AQ$45),2)) -> 0 | M47: =(SUMPRODUCT(M9:M43,$AV$9:$AV$43))-(ROUND(((SUMPRODUCT(M9:M43,$AV9:$AV43))*$AQ$45),2)) -> 0 | N47: =(SUMPRODUCT(N9:N43,$AV$9:$AV$43))-(ROUND(((SUMPRODUCT(N9:N43,$AV9:$AV43))*$AQ$45),2)) -> 0 | ... AP47: =(SUMPRODUCT(AP9:AP43,$AV$9:$AV$43))-(ROUND(((SUMPRODUCT(AP9:AP43,$AV9:$AV43))*$AQ$45),2)) -> 0
A50: Guiding Principles | D50: Target Net Margin | F50: Risk Profile | G50: Low | H50: Medium | I50: High | AQ50: Risk Profile | AT50: Blended Rate (w/Discount) | AU50: Net Margin $ (w/Discount) | AV50: Net Margin % (w/Discount) | AW50: Target Net Margin
A51: Avoid Milestone based or Fixed Fee Implementation projects - 20% contingency must be added for these projects | C51: T&M | D51: 0.35 | F51: Project Type | G51: Staff Aug / Support | H51: Implementation Managed Services | I51: Complex Implementation | AQ51: =F3 -> Low | AS51: US (Goal $195) | AT51: =IFERROR((SUMIFS($AU$9:$AU$43,$E$9:$E$43,"USA")*(1-AQ45))/(SUMIFS($AR$9:$AR$43,$E$9:$E$43,"USA")),0) -> 230 | AU51: =IFERROR((SUMIFS($BK$9:$BK$43,$E$9:$E$43,"USA")),0) -> 20150 | AV51: =IFERROR(IF($AQ$45=0,SUMIFS($BK$9:$BK$43,$E$9:$E$43,"USA")/SUMIFS($AU$9:$AU$43,$E$9:$E$43,"USA"),SUMIFS($BK$9:$BK$43,$E$9:$E$43,"USA")/(SUMIFS($AU$9:$AU$43,$E$9:$E$43,"USA")*(1-AQ45))),0) -> 0.2826087 | AW51: 0.35
A52: PM required for Implementation | C52: Managed Services (FF) | D52: 0.3 | F52: Team Size | G52: Small | H52: Medium | I52: Large | AS52: India (Goal $50) | AT52: =IFERROR((SUMIFS($AU$9:$AU$43,$E$9:$E$43,"India")*(1-AQ45))/(SUMIFS($AR$9:$AR$43,$E$9:$E$43,"India")),0) -> 0 | AU52: =IFERROR((SUMIFS($BK$9:$BK$43,$E$9:$E$43,"India")),0) -> 0 | AV52: =IFERROR(IF($AQ$45=0,SUMIFS($BK$9:$BK$43,$E$9:$E$43,"India")/SUMIFS($AU$9:$AU$43,$E$9:$E$43,"India"),SUMIFS($BK$9:$BK$43,$E$9:$E$43,"India")/(SUMIFS($AU$9:$AU$43,$E$9:$E$43,"India")*(1-AQ45))),0) -> 0
A53: Avoid partial utilization except Architects | F53: Scope Complexity | G53: Basic | H53: Medium | I53: Complex | AS53: Total | AT53: =IFERROR((AU44*(1-AQ45))/AR44,0) -> 230 | AU53: =BK44 -> 20150 | AV53: =IFERROR(IF($AQ$45=0,$AU$53/$AU$44,$AU$53/$AU$45),0) -> 0.2826087
A54: Bid for MS work on Implemention SOW | F54: Possible Scope Changes | G54: None | H54: Minor | I54: Major
A55: Engagement Lead role required for support projects at least at 10% utilization. All EPM/CPM Implementation projects require a Project Manager. Maritza must approve exceptions to this. | F55: Contract Value | G55: Small | H55: Medium | I55: Large
A56: Managed Services must include hours/month fixed fee, T&M can be used for overage.

Sheet Formulas
A1: Use to back into the discount when provided with hourly rates or total fee | T1: For SOW Timing Section
F2: T&M | K2: Discounted | M2: Fixed Fee | Q2: Discounted | R2: Discounted
T3: Resource Role / Hours | U3: Resource Location | V3: Months
A4: Goal Hourly Rate or Total Fee | B4: Donyati Standard Hourly Rate or Total Fee | C4: Discount % | F4: Resource Role | G4: Resource Location | H4: Total Estimated Hours | I4: Standard Hourly Rate | J4: Discounted Hourly Rate | K4: Estimated Fee | M4: Resource Role | N4: Resource Location | O4: Fixed Hours per Month | P4: Standard Hourly Rate | Q4: Hourly rate | R4: Monthly Fixed Fee | V4: 1 | W4: 2 | X4: 3 | Y4: 4 | Z4: 5 | AA4: 6 | AB4: 7 | AC4: 8 | AD4: 9 | AE4: 10 | AF4: 11 | AG4: 12 | AH4: 13 | AI4: 14 | AJ4: 15 | AK4: 16 | AL4: 17 | AM4: 18 | AN4: 19 | AO4: 20 | AP4: 21 | AQ4: 22 | AR4: 23 | AS4: 24 | AT4: 25 | AU4: 26 | AV4: 27 | AW4: 28 | AX4: 29 | AY4: 30 | AZ4: 31 | BA4: 32 | BB4: 33 | BC4: 34 | BD4: 35 | BE4: 36
A5: 230 | B5: 275 | C5: =(A5/B5)-1 -> -0.16363636 | F5: ='Pricing Details'!B9 -> Sr. Change Manager | G5: ='Pricing Details'!E9 -> USA | H5: ='Pricing Details'!AR9 -> 310 | I5: ='Pricing Details'!F9 -> 275 | J5: ='Pricing Details'!AV9 -> 230 | K5: ='Pricing Details'!AU9 -> 71300 | M5: ='Pricing Details'!B9 -> Sr. Change Manager | N5: ='Pricing Details'!E9 -> USA | O5: ='Pricing Details'!G9 -> 50 | P5: ='Pricing Details'!F9 -> 275 | Q5: ='Pricing Details'!AV9 -> 230 | R5: =O5*Q5 -> 11500 | T5: ='Pricing Details'!B9 -> Sr. Change Manager | U5: ='Pricing Details'!E9 -> USA | V5: ='Pricing Details'!G9 -> 50 | W5: ='Pricing Details'!H9 -> 80 | X5: ='Pricing Details'!I9 -> 90 | Y5: ='Pricing Details'!J9 -> 90 | Z5: ='Pricing Details'!K9 -> 0 | AA5: ='Pricing Details'!L9 -> 0 | AB5: ='Pricing Details'!M9 -> 0 | AC5: ='Pricing Details'!N9 -> 0 | ... BE5: ='Pricing Details'!AP9 -> 0
F6: ='Pricing Details'!B10 -> 0 | G6: ='Pricing Details'!E10 | H6: ='Pricing Details'!AR10 -> 0 | I6: ='Pricing Details'!F10 -> 0 | J6: ='Pricing Details'!AV10 -> 0 | K6: ='Pricing Details'!AU10 -> 0 | M6: ='Pricing Details'!B10 -> 0 | N6: ='Pricing Details'!E10 | O6: ='Pricing Details'!G10 -> 0 | P6: ='Pricing Details'!F10 -> 0 | Q6: ='Pricing Details'!AV10 -> 0 | R6: =O6*Q6 -> 0 | T6: ='Pricing Details'!B10 -> 0 | U6: ='Pricing Details'!E10 | V6: ='Pricing Details'!G10 -> 0 | W6: ='Pricing Details'!H10 -> 0 | X6: ='Pricing Details'!I10 -> 0 | Y6: ='Pricing Details'!J10 -> 0 | Z6: ='Pricing Details'!K10 -> 0 | AA6: ='Pricing Details'!L10 -> 0 | AB6: ='Pricing Details'!M10 -> 0 | AC6: ='Pricing Details'!N10 -> 0 | ... BE6: ='Pricing Details'!AP10 -> 0
A7: Use to calculate the End Date | F7: ='Pricing Details'!B11 -> 0 | G7: ='Pricing Details'!E11 | H7: ='Pricing Details'!AR11 -> 0 | I7: ='Pricing Details'!F11 -> 0 | J7: ='Pricing Details'!AV11 -> 0 | K7: ='Pricing Details'!AU11 -> 0 | M7: ='Pricing Details'!B11 -> 0 | N7: ='Pricing Details'!E11 | O7: ='Pricing Details'!G11 -> 0 | P7: ='Pricing Details'!F11 -> 0 | Q7: ='Pricing Details'!AV11 -> 0 | R7: =O7*Q7 -> 0 | T7: ='Pricing Details'!B11 -> 0 | U7: ='Pricing Details'!E11 | V7: ='Pricing Details'!G11 -> 0 | W7: ='Pricing Details'!H11 -> 0 | X7: ='Pricing Details'!I11 -> 0 | Y7: ='Pricing Details'!J11 -> 0 | Z7: ='Pricing Details'!K11 -> 0 | AA7: ='Pricing Details'!L11 -> 0 | AB7: ='Pricing Details'!M11 -> 0 | AC7: ='Pricing Details'!N11 -> 0 | ... BE7: ='Pricing Details'!AP11 -> 0
A8: Start Date | B8: # weeks | C8: End Date | F8: ='Pricing Details'!B12 -> 0 | G8: ='Pricing Details'!E12 | H8: ='Pricing Details'!AR12 -> 0 | I8: ='Pricing Details'!F12 -> 0 | J8: ='Pricing Details'!AV12 -> 0 | K8: ='Pricing Details'!AU12 -> 0 | M8: ='Pricing Details'!B12 -> 0 | N8: ='Pricing Details'!E12 | O8: ='Pricing Details'!G12 -> 0 | P8: ='Pricing Details'!F12 -> 0 | Q8: ='Pricing Details'!AV12 -> 0 | R8: =O8*Q8 -> 0 | T8: ='Pricing Details'!B12 -> 0 | U8: ='Pricing Details'!E12 | V8: ='Pricing Details'!G12 -> 0 | W8: ='Pricing Details'!H12 -> 0 | X8: ='Pricing Details'!I12 -> 0 | Y8: ='Pricing Details'!J12 -> 0 | Z8: ='Pricing Details'!K12 -> 0 | AA8: ='Pricing Details'!L12 -> 0 | AB8: ='Pricing Details'!M12 -> 0 | AC8: ='Pricing Details'!N12 -> 0 | ... BE8: ='Pricing Details'!AP12 -> 0
A9: 46023 | B9: 28 | C9: =A9+(B9*7)-3 -> 46216 | F9: ='Pricing Details'!B13 -> 0 | G9: ='Pricing Details'!E13 | H9: ='Pricing Details'!AR13 -> 0 | I9: ='Pricing Details'!F13 -> 0 | J9: ='Pricing Details'!AV13 -> 0 | K9: ='Pricing Details'!AU13 -> 0 | M9: ='Pricing Details'!B13 -> 0 | N9: ='Pricing Details'!E13 | O9: ='Pricing Details'!G13 -> 0 | P9: ='Pricing Details'!F13 -> 0 | Q9: ='Pricing Details'!AV13 -> 0 | R9: =O9*Q9 -> 0 | T9: ='Pricing Details'!B13 -> 0 | U9: ='Pricing Details'!E13 | V9: ='Pricing Details'!G13 -> 0 | W9: ='Pricing Details'!H13 -> 0 | X9: ='Pricing Details'!I13 -> 0 | Y9: ='Pricing Details'!J13 -> 0 | Z9: ='Pricing Details'!K13 -> 0 | AA9: ='Pricing Details'!L13 -> 0 | AB9: ='Pricing Details'!M13 -> 0 | AC9: ='Pricing Details'!N13 -> 0 | ... BE9: ='Pricing Details'!AP13 -> 0
F10: ='Pricing Details'!B14 -> 0 | G10: ='Pricing Details'!E14 | H10: ='Pricing Details'!AR14 -> 0 | I10: ='Pricing Details'!F14 -> 0 | J10: ='Pricing Details'!AV14 -> 0 | K10: ='Pricing Details'!AU14 -> 0 | M10: ='Pricing Details'!B14 -> 0 | N10: ='Pricing Details'!E14 | O10: ='Pricing Details'!G14 -> 0 | P10: ='Pricing Details'!F14 -> 0 | Q10: ='Pricing Details'!AV14 -> 0 | R10: =O10*Q10 -> 0 | T10: ='Pricing Details'!B14 -> 0 | U10: ='Pricing Details'!E14 | V10: ='Pricing Details'!G14 -> 0 | W10: ='Pricing Details'!H14 -> 0 | X10: ='Pricing Details'!I14 -> 0 | Y10: ='Pricing Details'!J14 -> 0 | Z10: ='Pricing Details'!K14 -> 0 | AA10: ='Pricing Details'!L14 -> 0 | AB10: ='Pricing Details'!M14 -> 0 | AC10: ='Pricing Details'!N14 -> 0 | ... BE10: ='Pricing Details'!AP14 -> 0
A11: Use to convert # Days to # Business Hours | F11: ='Pricing Details'!B15 -> 0 | G11: ='Pricing Details'!E15 | H11: ='Pricing Details'!AR15 -> 0 | I11: ='Pricing Details'!F15 -> 0 | J11: ='Pricing Details'!AV15 -> 0 | K11: ='Pricing Details'!AU15 -> 0 | M11: ='Pricing Details'!B15 -> 0 | N11: ='Pricing Details'!E15 | O11: ='Pricing Details'!G15 -> 0 | P11: ='Pricing Details'!F15 -> 0 | Q11: ='Pricing Details'!AV15 -> 0 | R11: =O11*Q11 -> 0 | T11: ='Pricing Details'!B15 -> 0 | U11: ='Pricing Details'!E15 | V11: ='Pricing Details'!G15 -> 0 | W11: ='Pricing Details'!H15 -> 0 | X11: ='Pricing Details'!I15 -> 0 | Y11: ='Pricing Details'!J15 -> 0 | Z11: ='Pricing Details'!K15 -> 0 | AA11: ='Pricing Details'!L15 -> 0 | AB11: ='Pricing Details'!M15 -> 0 | AC11: ='Pricing Details'!N15 -> 0 | ... BE11: ='Pricing Details'!AP15 -> 0
A12: Days | B12: Business Hours | F12: ='Pricing Details'!B16 -> 0 | G12: ='Pricing Details'!E16 | H12: ='Pricing Details'!AR16 -> 0 | I12: ='Pricing Details'!F16 -> 0 | J12: ='Pricing Details'!AV16 -> 0 | K12: ='Pricing Details'!AU16 -> 0 | M12: ='Pricing Details'!B16 -> 0 | N12: ='Pricing Details'!E16 | O12: ='Pricing Details'!G16 -> 0 | P12: ='Pricing Details'!F16 -> 0 | Q12: ='Pricing Details'!AV16 -> 0 | R12: =O12*Q12 -> 0 | T12: ='Pricing Details'!B16 -> 0 | U12: ='Pricing Details'!E16 | V12: ='Pricing Details'!G16 -> 0 | W12: ='Pricing Details'!H16 -> 0 | X12: ='Pricing Details'!I16 -> 0 | Y12: ='Pricing Details'!J16 -> 0 | Z12: ='Pricing Details'!K16 -> 0 | AA12: ='Pricing Details'!L16 -> 0 | AB12: ='Pricing Details'!M16 -> 0 | AC12: ='Pricing Details'!N16 -> 0 | ... BE12: ='Pricing Details'!AP16 -> 0
A13: 5 | B13: =A13*8 -> 40 | F13: ='Pricing Details'!B17 -> 0 | G13: ='Pricing Details'!E17 | H13: ='Pricing Details'!AR17 -> 0 | I13: ='Pricing Details'!F17 -> 0 | J13: ='Pricing Details'!AV17 -> 0 | K13: ='Pricing Details'!AU17 -> 0 | M13: ='Pricing Details'!B17 -> 0 | N13: ='Pricing Details'!E17 | O13: ='Pricing Details'!G17 -> 0 | P13: ='Pricing Details'!F17 -> 0 | Q13: ='Pricing Details'!AV17 -> 0 | R13: =O13*Q13 -> 0 | T13: ='Pricing Details'!B17 -> 0 | U13: ='Pricing Details'!E17 | V13: ='Pricing Details'!G17 -> 0 | W13: ='Pricing Details'!H17 -> 0 | X13: ='Pricing Details'!I17 -> 0 | Y13: ='Pricing Details'!J17 -> 0 | Z13: ='Pricing Details'!K17 -> 0 | AA13: ='Pricing Details'!L17 -> 0 | AB13: ='Pricing Details'!M17 -> 0 | AC13: ='Pricing Details'!N17 -> 0 | ... BE13: ='Pricing Details'!AP17 -> 0
A14: 11 | B14: =A14*8 -> 88 | F14: ='Pricing Details'!B18 -> 0 | G14: ='Pricing Details'!E18 | H14: ='Pricing Details'!AR18 -> 0 | I14: ='Pricing Details'!F18 -> 0 | J14: ='Pricing Details'!AV18 -> 0 | K14: ='Pricing Details'!AU18 -> 0 | M14: ='Pricing Details'!B18 -> 0 | N14: ='Pricing Details'!E18 | O14: ='Pricing Details'!G18 -> 0 | P14: ='Pricing Details'!F18 -> 0 | Q14: ='Pricing Details'!AV18 -> 0 | R14: =O14*Q14 -> 0 | T14: ='Pricing Details'!B18 -> 0 | U14: ='Pricing Details'!E18 | V14: ='Pricing Details'!G18 -> 0 | W14: ='Pricing Details'!H18 -> 0 | X14: ='Pricing Details'!I18 -> 0 | Y14: ='Pricing Details'!J18 -> 0 | Z14: ='Pricing Details'!K18 -> 0 | AA14: ='Pricing Details'!L18 -> 0 | AB14: ='Pricing Details'!M18 -> 0 | AC14: ='Pricing Details'!N18 -> 0 | ... BE14: ='Pricing Details'!AP18 -> 0
F15: ='Pricing Details'!B19 -> 0 | G15: ='Pricing Details'!E19 | H15: ='Pricing Details'!AR19 -> 0 | I15: ='Pricing Details'!F19 -> 0 | J15: ='Pricing Details'!AV19 -> 0 | K15: ='Pricing Details'!AU19 -> 0 | M15: ='Pricing Details'!B19 -> 0 | N15: ='Pricing Details'!E19 | O15: ='Pricing Details'!G19 -> 0 | P15: ='Pricing Details'!F19 -> 0 | Q15: ='Pricing Details'!AV19 -> 0 | R15: =O15*Q15 -> 0 | T15: ='Pricing Details'!B19 -> 0 | U15: ='Pricing Details'!E19 | V15: ='Pricing Details'!G19 -> 0 | W15: ='Pricing Details'!H19 -> 0 | X15: ='Pricing Details'!I19 -> 0 | Y15: ='Pricing Details'!J19 -> 0 | Z15: ='Pricing Details'!K19 -> 0 | AA15: ='Pricing Details'!L19 -> 0 | AB15: ='Pricing Details'!M19 -> 0 | AC15: ='Pricing Details'!N19 -> 0 | ... BE15: ='Pricing Details'!AP19 -> 0
A16: Use to input the actual Contractor Cost (what we are paying the contractor) | C16: To change you need permission from Havagi | D16: Enter the Net Margin % you want to achieve for this role | F16: ='Pricing Details'!B20 -> 0 | G16: ='Pricing Details'!E20 | H16: ='Pricing Details'!AR20 -> 0 | I16: ='Pricing Details'!F20 -> 0 | J16: ='Pricing Details'!AV20 -> 0 | K16: ='Pricing Details'!AU20 -> 0 | M16: ='Pricing Details'!B20 -> 0 | N16: ='Pricing Details'!E20 | O16: ='Pricing Details'!G20 -> 0 | P16: ='Pricing Details'!F20 -> 0 | Q16: ='Pricing Details'!AV20 -> 0 | R16: =O16*Q16 -> 0 | T16: ='Pricing Details'!B20 -> 0 | U16: ='Pricing Details'!E20 | V16: ='Pricing Details'!G20 -> 0 | W16: ='Pricing Details'!H20 -> 0 | X16: ='Pricing Details'!I20 -> 0 | Y16: ='Pricing Details'!J20 -> 0 | Z16: ='Pricing Details'!K20 -> 0 | AA16: ='Pricing Details'!L20 -> 0 | AB16: ='Pricing Details'!M20 -> 0 | AC16: ='Pricing Details'!N20 -> 0 | ... BE16: ='Pricing Details'!AP20 -> 0
A17: Contractor | B17: Hourly Cost | C17: OpX Hourly | D17: Net Margin % | F17: ='Pricing Details'!B21 -> 0 | G17: ='Pricing Details'!E21 | H17: ='Pricing Details'!AR21 -> 0 | I17: ='Pricing Details'!F21 -> 0 | J17: ='Pricing Details'!AV21 -> 0 | K17: ='Pricing Details'!AU21 -> 0 | M17: ='Pricing Details'!B21 -> 0 | N17: ='Pricing Details'!E21 | O17: ='Pricing Details'!G21 -> 0 | P17: ='Pricing Details'!F21 -> 0 | Q17: ='Pricing Details'!AV21 -> 0 | R17: =O17*Q17 -> 0 | T17: ='Pricing Details'!B21 -> 0 | U17: ='Pricing Details'!E21 | V17: ='Pricing Details'!G21 -> 0 | W17: ='Pricing Details'!H21 -> 0 | X17: ='Pricing Details'!I21 -> 0 | Y17: ='Pricing Details'!J21 -> 0 | Z17: ='Pricing Details'!K21 -> 0 | AA17: ='Pricing Details'!L21 -> 0 | AB17: ='Pricing Details'!M21 -> 0 | AC17: ='Pricing Details'!N21 -> 0 | ... BE17: ='Pricing Details'!AP21 -> 0
A18: Contractor 1 | B18: 100 | C18: 45 | D18: 0.35 | F18: ='Pricing Details'!B22 -> 0 | G18: ='Pricing Details'!E22 | H18: ='Pricing Details'!AR22 -> 0 | I18: ='Pricing Details'!F22 -> 0 | J18: ='Pricing Details'!AV22 -> 0 | K18: ='Pricing Details'!AU22 -> 0 | M18: ='Pricing Details'!B22 -> 0 | N18: ='Pricing Details'!E22 | O18: ='Pricing Details'!G22 -> 0 | P18: ='Pricing Details'!F22 -> 0 | Q18: ='Pricing Details'!AV22 -> 0 | R18: =O18*Q18 -> 0 | T18: ='Pricing Details'!B22 -> 0 | U18: ='Pricing Details'!E22 | V18: ='Pricing Details'!G22 -> 0 | W18: ='Pricing Details'!H22 -> 0 | X18: ='Pricing Details'!I22 -> 0 | Y18: ='Pricing Details'!J22 -> 0 | Z18: ='Pricing Details'!K22 -> 0 | AA18: ='Pricing Details'!L22 -> 0 | AB18: ='Pricing Details'!M22 -> 0 | AC18: ='Pricing Details'!N22 -> 0 | ... BE18: ='Pricing Details'!AP22 -> 0
A19: Contractor 2 | B19: 100 | C19: 45 | D19: 0.35 | F19: ='Pricing Details'!B23 -> 0 | G19: ='Pricing Details'!E23 | H19: ='Pricing Details'!AR23 -> 0 | I19: ='Pricing Details'!F23 -> 0 | J19: ='Pricing Details'!AV23 -> 0 | K19: ='Pricing Details'!AU23 -> 0 | M19: ='Pricing Details'!B23 -> 0 | N19: ='Pricing Details'!E23 | O19: ='Pricing Details'!G23 -> 0 | P19: ='Pricing Details'!F23 -> 0 | Q19: ='Pricing Details'!AV23 -> 0 | R19: =O19*Q19 -> 0 | T19: ='Pricing Details'!B23 -> 0 | U19: ='Pricing Details'!E23 | V19: ='Pricing Details'!G23 -> 0 | W19: ='Pricing Details'!H23 -> 0 | X19: ='Pricing Details'!I23 -> 0 | Y19: ='Pricing Details'!J23 -> 0 | Z19: ='Pricing Details'!K23 -> 0 | AA19: ='Pricing Details'!L23 -> 0 | AB19: ='Pricing Details'!M23 -> 0 | AC19: ='Pricing Details'!N23 -> 0 | ... BE19: ='Pricing Details'!AP23 -> 0
A20: Contractor 3 | B20: 100 | C20: 45 | D20: 0.35 | F20: ='Pricing Details'!B24 -> 0 | G20: ='Pricing Details'!E24 | H20: ='Pricing Details'!AR24 -> 0 | I20: ='Pricing Details'!F24 -> 0 | J20: ='Pricing Details'!AV24 -> 0 | K20: ='Pricing Details'!AU24 -> 0 | M20: ='Pricing Details'!B24 -> 0 | N20: ='Pricing Details'!E24 | O20: ='Pricing Details'!G24 -> 0 | P20: ='Pricing Details'!F24 -> 0 | Q20: ='Pricing Details'!AV24 -> 0 | R20: =O20*Q20 -> 0 | T20: ='Pricing Details'!B24 -> 0 | U20: ='Pricing Details'!E24 | V20: ='Pricing Details'!G24 -> 0 | W20: ='Pricing Details'!H24 -> 0 | X20: ='Pricing Details'!I24 -> 0 | Y20: ='Pricing Details'!J24 -> 0 | Z20: ='Pricing Details'!K24 -> 0 | AA20: ='Pricing Details'!L24 -> 0 | AB20: ='Pricing Details'!M24 -> 0 | AC20: ='Pricing Details'!N24 -> 0 | ... BE20: ='Pricing Details'!AP24 -> 0
A21: Contractor 4 | B21: 100 | C21: 45 | D21: 0.35 | F21: ='Pricing Details'!B25 -> 0 | G21: ='Pricing Details'!E25 | H21: ='Pricing Details'!AR25 -> 0 | I21: ='Pricing Details'!F25 -> 0 | J21: ='Pricing Details'!AV25 -> 0 | K21: ='Pricing Details'!AU25 -> 0 | M21: ='Pricing Details'!B25 -> 0 | N21: ='Pricing Details'!E25 | O21: ='Pricing Details'!G25 -> 0 | P21: ='Pricing Details'!F25 -> 0 | Q21: ='Pricing Details'!AV25 -> 0 | R21: =O21*Q21 -> 0 | T21: ='Pricing Details'!B25 -> 0 | U21: ='Pricing Details'!E25 | V21: ='Pricing Details'!G25 -> 0 | W21: ='Pricing Details'!H25 -> 0 | X21: ='Pricing Details'!I25 -> 0 | Y21: ='Pricing Details'!J25 -> 0 | Z21: ='Pricing Details'!K25 -> 0 | AA21: ='Pricing Details'!L25 -> 0 | AB21: ='Pricing Details'!M25 -> 0 | AC21: ='Pricing Details'!N25 -> 0 | ... BE21: ='Pricing Details'!AP25 -> 0
A22: Contractor 5 | B22: 100 | C22: 45 | D22: 0.35 | F22: ='Pricing Details'!B26 -> 0 | G22: ='Pricing Details'!E26 | H22: ='Pricing Details'!AR26 -> 0 | I22: ='Pricing Details'!F26 -> 0 | J22: ='Pricing Details'!AV26 -> 0 | K22: ='Pricing Details'!AU26 -> 0 | M22: ='Pricing Details'!B26 -> 0 | N22: ='Pricing Details'!E26 | O22: ='Pricing Details'!G26 -> 0 | P22: ='Pricing Details'!F26 -> 0 | Q22: ='Pricing Details'!AV26 -> 0 | R22: =O22*Q22 -> 0 | T22: ='Pricing Details'!B26 -> 0 | U22: ='Pricing Details'!E26 | V22: ='Pricing Details'!G26 -> 0 | W22: ='Pricing Details'!H26 -> 0 | X22: ='Pricing Details'!I26 -> 0 | Y22: ='Pricing Details'!J26 -> 0 | Z22: ='Pricing Details'!K26 -> 0 | AA22: ='Pricing Details'!L26 -> 0 | AB22: ='Pricing Details'!M26 -> 0 | AC22: ='Pricing Details'!N26 -> 0 | ... BE22: ='Pricing Details'!AP26 -> 0
F23: ='Pricing Details'!B27 -> 0 | G23: ='Pricing Details'!E27 | H23: ='Pricing Details'!AR27 -> 0 | I23: ='Pricing Details'!F27 -> 0 | J23: ='Pricing Details'!AV27 -> 0 | K23: ='Pricing Details'!AU27 -> 0 | M23: ='Pricing Details'!B27 -> 0 | N23: ='Pricing Details'!E27 | O23: ='Pricing Details'!G27 -> 0 | P23: ='Pricing Details'!F27 -> 0 | Q23: ='Pricing Details'!AV27 -> 0 | R23: =O23*Q23 -> 0 | T23: ='Pricing Details'!B27 -> 0 | U23: ='Pricing Details'!E27 | V23: ='Pricing Details'!G27 -> 0 | W23: ='Pricing Details'!H27 -> 0 | X23: ='Pricing Details'!I27 -> 0 | Y23: ='Pricing Details'!J27 -> 0 | Z23: ='Pricing Details'!K27 -> 0 | AA23: ='Pricing Details'!L27 -> 0 | AB23: ='Pricing Details'!M27 -> 0 | AC23: ='Pricing Details'!N27 -> 0 | ... BE23: ='Pricing Details'!AP27 -> 0
A24: Use to back into the Net Margin % when you have the hourly bill rate | F24: ='Pricing Details'!B28 -> 0 | G24: ='Pricing Details'!E28 | H24: ='Pricing Details'!AR28 -> 0 | I24: ='Pricing Details'!F28 -> 0 | J24: ='Pricing Details'!AV28 -> 0 | K24: ='Pricing Details'!AU28 -> 0 | M24: ='Pricing Details'!B28 -> 0 | N24: ='Pricing Details'!E28 | O24: ='Pricing Details'!G28 -> 0 | P24: ='Pricing Details'!F28 -> 0 | Q24: ='Pricing Details'!AV28 -> 0 | R24: =O24*Q24 -> 0 | T24: ='Pricing Details'!B28 -> 0 | U24: ='Pricing Details'!E28 | V24: ='Pricing Details'!G28 -> 0 | W24: ='Pricing Details'!H28 -> 0 | X24: ='Pricing Details'!I28 -> 0 | Y24: ='Pricing Details'!J28 -> 0 | Z24: ='Pricing Details'!K28 -> 0 | AA24: ='Pricing Details'!L28 -> 0 | AB24: ='Pricing Details'!M28 -> 0 | AC24: ='Pricing Details'!N28 -> 0 | ... BE24: ='Pricing Details'!AP28 -> 0
A25: Goal Hourly Rate | B25: Contractor Hourly Cost + OpX Cost | C25: Net Margin % | F25: ='Pricing Details'!B29 -> 0 | G25: ='Pricing Details'!E29 | H25: ='Pricing Details'!AR29 -> 0 | I25: ='Pricing Details'!F29 -> 0 | J25: ='Pricing Details'!AV29 -> 0 | K25: ='Pricing Details'!AU29 -> 0 | M25: ='Pricing Details'!B29 -> 0 | N25: ='Pricing Details'!E29 | O25: ='Pricing Details'!G29 -> 0 | P25: ='Pricing Details'!F29 -> 0 | Q25: ='Pricing Details'!AV29 -> 0 | R25: =O25*Q25 -> 0 | T25: ='Pricing Details'!B29 -> 0 | U25: ='Pricing Details'!E29 | V25: ='Pricing Details'!G29 -> 0 | W25: ='Pricing Details'!H29 -> 0 | X25: ='Pricing Details'!I29 -> 0 | Y25: ='Pricing Details'!J29 -> 0 | Z25: ='Pricing Details'!K29 -> 0 | AA25: ='Pricing Details'!L29 -> 0 | AB25: ='Pricing Details'!M29 -> 0 | AC25: ='Pricing Details'!N29 -> 0 | ... BE25: ='Pricing Details'!AP29 -> 0
A26: 185 | B26: 120 | C26: =(A26-B26)/A26 -> 0.35135135 | F26: ='Pricing Details'!B30 -> 0 | G26: ='Pricing Details'!E30 | H26: ='Pricing Details'!AR30 -> 0 | I26: ='Pricing Details'!F30 -> 0 | J26: ='Pricing Details'!AV30 -> 0 | K26: ='Pricing Details'!AU30 -> 0 | M26: ='Pricing Details'!B30 -> 0 | N26: ='Pricing Details'!E30 | O26: ='Pricing Details'!G30 -> 0 | P26: ='Pricing Details'!F30 -> 0 | Q26: ='Pricing Details'!AV30 -> 0 | R26: =O26*Q26 -> 0 | T26: ='Pricing Details'!B30 -> 0 | U26: ='Pricing Details'!E30 | V26: ='Pricing Details'!G30 -> 0 | W26: ='Pricing Details'!H30 -> 0 | X26: ='Pricing Details'!I30 -> 0 | Y26: ='Pricing Details'!J30 -> 0 | Z26: ='Pricing Details'!K30 -> 0 | AA26: ='Pricing Details'!L30 -> 0 | AB26: ='Pricing Details'!M30 -> 0 | AC26: ='Pricing Details'!N30 -> 0 | ... BE26: ='Pricing Details'!AP30 -> 0
F27: ='Pricing Details'!B31 -> 0 | G27: ='Pricing Details'!E31 | H27: ='Pricing Details'!AR31 -> 0 | I27: ='Pricing Details'!F31 -> 0 | J27: ='Pricing Details'!AV31 -> 0 | K27: ='Pricing Details'!AU31 -> 0 | M27: ='Pricing Details'!B31 -> 0 | N27: ='Pricing Details'!E31 | O27: ='Pricing Details'!G31 -> 0 | P27: ='Pricing Details'!F31 -> 0 | Q27: ='Pricing Details'!AV31 -> 0 | R27: =O27*Q27 -> 0 | T27: ='Pricing Details'!B31 -> 0 | U27: ='Pricing Details'!E31 | V27: ='Pricing Details'!G31 -> 0 | W27: ='Pricing Details'!H31 -> 0 | X27: ='Pricing Details'!I31 -> 0 | Y27: ='Pricing Details'!J31 -> 0 | Z27: ='Pricing Details'!K31 -> 0 | AA27: ='Pricing Details'!L31 -> 0 | AB27: ='Pricing Details'!M31 -> 0 | AC27: ='Pricing Details'!N31 -> 0 | ... BE27: ='Pricing Details'!AP31 -> 0
A28: Below is the standard price. If you are billing each month, then put 1 hour in each month. The price can be discounted using the Hourly Rate or Bottom Line Discount. | F28: ='Pricing Details'!B32 -> 0 | G28: ='Pricing Details'!E32 | H28: ='Pricing Details'!AR32 -> 0 | I28: ='Pricing Details'!F32 -> 0 | J28: ='Pricing Details'!AV32 -> 0 | K28: ='Pricing Details'!AU32 -> 0 | M28: ='Pricing Details'!B32 -> 0 | N28: ='Pricing Details'!E32 | O28: ='Pricing Details'!G32 -> 0 | P28: ='Pricing Details'!F32 -> 0 | Q28: ='Pricing Details'!AV32 -> 0 | R28: =O28*Q28 -> 0 | T28: ='Pricing Details'!B32 -> 0 | U28: ='Pricing Details'!E32 | V28: ='Pricing Details'!G32 -> 0 | W28: ='Pricing Details'!H32 -> 0 | X28: ='Pricing Details'!I32 -> 0 | Y28: ='Pricing Details'!J32 -> 0 | Z28: ='Pricing Details'!K32 -> 0 | AA28: ='Pricing Details'!L32 -> 0 | AB28: ='Pricing Details'!M32 -> 0 | AC28: ='Pricing Details'!N32 -> 0 | ... BE28: ='Pricing Details'!AP32 -> 0
F29: ='Pricing Details'!B33 -> 0 | G29: ='Pricing Details'!E33 | H29: ='Pricing Details'!AR33 -> 0 | I29: ='Pricing Details'!F33 -> 0 | J29: ='Pricing Details'!AV33 -> 0 | K29: ='Pricing Details'!AU33 -> 0 | M29: ='Pricing Details'!B33 -> 0 | N29: ='Pricing Details'!E33 | O29: ='Pricing Details'!G33 -> 0 | P29: ='Pricing Details'!F33 -> 0 | Q29: ='Pricing Details'!AV33 -> 0 | R29: =O29*Q29 -> 0 | T29: ='Pricing Details'!B33 -> 0 | U29: ='Pricing Details'!E33 | V29: ='Pricing Details'!G33 -> 0 | W29: ='Pricing Details'!H33 -> 0 | X29: ='Pricing Details'!I33 -> 0 | Y29: ='Pricing Details'!J33 -> 0 | Z29: ='Pricing Details'!K33 -> 0 | AA29: ='Pricing Details'!L33 -> 0 | AB29: ='Pricing Details'!M33 -> 0 | AC29: ='Pricing Details'!N33 -> 0 | ... BE29: ='Pricing Details'!AP33 -> 0
A30: Donyati Product | B30: Hourly Price | F30: ='Pricing Details'!B34 -> 0 | G30: ='Pricing Details'!E34 | H30: ='Pricing Details'!AR34 -> 0 | I30: ='Pricing Details'!F34 -> 0 | J30: ='Pricing Details'!AV34 -> 0 | K30: ='Pricing Details'!AU34 -> 0 | M30: ='Pricing Details'!B34 -> 0 | N30: ='Pricing Details'!E34 | O30: ='Pricing Details'!G34 -> 0 | P30: ='Pricing Details'!F34 -> 0 | Q30: ='Pricing Details'!AV34 -> 0 | R30: =O30*Q30 -> 0 | T30: ='Pricing Details'!B34 -> 0 | U30: ='Pricing Details'!E34 | V30: ='Pricing Details'!G34 -> 0 | W30: ='Pricing Details'!H34 -> 0 | X30: ='Pricing Details'!I34 -> 0 | Y30: ='Pricing Details'!J34 -> 0 | Z30: ='Pricing Details'!K34 -> 0 | AA30: ='Pricing Details'!L34 -> 0 | AB30: ='Pricing Details'!M34 -> 0 | AC30: ='Pricing Details'!N34 -> 0 | ... BE30: ='Pricing Details'!AP34 -> 0
A31: DART | B31: 4000 | F31: ='Pricing Details'!B35 -> 0 | G31: ='Pricing Details'!E35 | H31: ='Pricing Details'!AR35 -> 0 | I31: ='Pricing Details'!F35 -> 0 | J31: ='Pricing Details'!AV35 -> 0 | K31: ='Pricing Details'!AU35 -> 0 | M31: ='Pricing Details'!B35 -> 0 | N31: ='Pricing Details'!E35 | O31: ='Pricing Details'!G35 -> 0 | P31: ='Pricing Details'!F35 -> 0 | Q31: ='Pricing Details'!AV35 -> 0 | R31: =O31*Q31 -> 0 | T31: ='Pricing Details'!B35 -> 0 | U31: ='Pricing Details'!E35 | V31: ='Pricing Details'!G35 -> 0 | W31: ='Pricing Details'!H35 -> 0 | X31: ='Pricing Details'!I35 -> 0 | Y31: ='Pricing Details'!J35 -> 0 | Z31: ='Pricing Details'!K35 -> 0 | AA31: ='Pricing Details'!L35 -> 0 | AB31: ='Pricing Details'!M35 -> 0 | AC31: ='Pricing Details'!N35 -> 0 | ... BE31: ='Pricing Details'!AP35 -> 0
A32: EPM Cloud Assurance | B32: 4000 | F32: ='Pricing Details'!B36 -> 0 | G32: ='Pricing Details'!E36 | H32: ='Pricing Details'!AR36 -> 0 | I32: ='Pricing Details'!F36 -> 0 | J32: ='Pricing Details'!AV36 -> 0 | K32: ='Pricing Details'!AU36 -> 0 | M32: ='Pricing Details'!B36 -> 0 | N32: ='Pricing Details'!E36 | O32: ='Pricing Details'!G36 -> 0 | P32: ='Pricing Details'!F36 -> 0 | Q32: ='Pricing Details'!AV36 -> 0 | R32: =O32*Q32 -> 0 | T32: ='Pricing Details'!B36 -> 0 | U32: ='Pricing Details'!E36 | V32: ='Pricing Details'!G36 -> 0 | W32: ='Pricing Details'!H36 -> 0 | X32: ='Pricing Details'!I36 -> 0 | Y32: ='Pricing Details'!J36 -> 0 | Z32: ='Pricing Details'!K36 -> 0 | AA32: ='Pricing Details'!L36 -> 0 | AB32: ='Pricing Details'!M36 -> 0 | AC32: ='Pricing Details'!N36 -> 0 | ... BE32: ='Pricing Details'!AP36 -> 0
F33: ='Pricing Details'!B37 -> 0 | G33: ='Pricing Details'!E37 | H33: ='Pricing Details'!AR37 -> 0 | I33: ='Pricing Details'!F37 -> 0 | J33: ='Pricing Details'!AV37 -> 0 | K33: ='Pricing Details'!AU37 -> 0 | M33: ='Pricing Details'!B37 -> 0 | N33: ='Pricing Details'!E37 | O33: ='Pricing Details'!G37 -> 0 | P33: ='Pricing Details'!F37 -> 0 | Q33: ='Pricing Details'!AV37 -> 0 | R33: =O33*Q33 -> 0 | T33: ='Pricing Details'!B37 -> 0 | U33: ='Pricing Details'!E37 | V33: ='Pricing Details'!G37 -> 0 | W33: ='Pricing Details'!H37 -> 0 | X33: ='Pricing Details'!I37 -> 0 | Y33: ='Pricing Details'!J37 -> 0 | Z33: ='Pricing Details'!K37 -> 0 | AA33: ='Pricing Details'!L37 -> 0 | AB33: ='Pricing Details'!M37 -> 0 | AC33: ='Pricing Details'!N37 -> 0 | ... BE33: ='Pricing Details'!AP37 -> 0
F34: ='Pricing Details'!B38 -> 0 | G34: ='Pricing Details'!E38 | H34: ='Pricing Details'!AR38 -> 0 | I34: ='Pricing Details'!F38 -> 0 | J34: ='Pricing Details'!AV38 -> 0 | K34: ='Pricing Details'!AU38 -> 0 | M34: ='Pricing Details'!B38 -> 0 | N34: ='Pricing Details'!E38 | O34: ='Pricing Details'!G38 -> 0 | P34: ='Pricing Details'!F38 -> 0 | Q34: ='Pricing Details'!AV38 -> 0 | R34: =O34*Q34 -> 0 | T34: ='Pricing Details'!B38 -> 0 | U34: ='Pricing Details'!E38 | V34: ='Pricing Details'!G38 -> 0 | W34: ='Pricing Details'!H38 -> 0 | X34: ='Pricing Details'!I38 -> 0 | Y34: ='Pricing Details'!J38 -> 0 | Z34: ='Pricing Details'!K38 -> 0 | AA34: ='Pricing Details'!L38 -> 0 | AB34: ='Pricing Details'!M38 -> 0 | AC34: ='Pricing Details'!N38 -> 0 | ... BE34: ='Pricing Details'!AP38 -> 0
F35: ='Pricing Details'!B39 -> 0 | G35: ='Pricing Details'!E39 | H35: ='Pricing Details'!AR39 -> 0 | I35: ='Pricing Details'!F39 -> 0 | J35: ='Pricing Details'!AV39 -> 0 | K35: ='Pricing Details'!AU39 -> 0 | M35: ='Pricing Details'!B39 -> 0 | N35: ='Pricing Details'!E39 | O35: ='Pricing Details'!G39 -> 0 | P35: ='Pricing Details'!F39 -> 0 | Q35: ='Pricing Details'!AV39 -> 0 | R35: =O35*Q35 -> 0 | T35: ='Pricing Details'!B39 -> 0 | U35: ='Pricing Details'!E39 | V35: ='Pricing Details'!G39 -> 0 | W35: ='Pricing Details'!H39 -> 0 | X35: ='Pricing Details'!I39 -> 0 | Y35: ='Pricing Details'!J39 -> 0 | Z35: ='Pricing Details'!K39 -> 0 | AA35: ='Pricing Details'!L39 -> 0 | AB35: ='Pricing Details'!M39 -> 0 | AC35: ='Pricing Details'!N39 -> 0 | ... BE35: ='Pricing Details'!AP39 -> 0
F36: ='Pricing Details'!B40 -> 0 | G36: ='Pricing Details'!E40 | H36: ='Pricing Details'!AR40 -> 0 | I36: ='Pricing Details'!F40 -> 0 | J36: ='Pricing Details'!AV40 -> 0 | K36: ='Pricing Details'!AU40 -> 0 | M36: ='Pricing Details'!B40 -> 0 | N36: ='Pricing Details'!E40 | O36: ='Pricing Details'!G40 -> 0 | P36: ='Pricing Details'!F40 -> 0 | Q36: ='Pricing Details'!AV40 -> 0 | R36: =O36*Q36 -> 0 | T36: ='Pricing Details'!B40 -> 0 | U36: ='Pricing Details'!E40 | V36: ='Pricing Details'!G40 -> 0 | W36: ='Pricing Details'!H40 -> 0 | X36: ='Pricing Details'!I40 -> 0 | Y36: ='Pricing Details'!J40 -> 0 | Z36: ='Pricing Details'!K40 -> 0 | AA36: ='Pricing Details'!L40 -> 0 | AB36: ='Pricing Details'!M40 -> 0 | AC36: ='Pricing Details'!N40 -> 0 | ... BE36: ='Pricing Details'!AP40 -> 0
F37: ='Pricing Details'!B41 -> 0 | G37: ='Pricing Details'!E41 | H37: ='Pricing Details'!AR41 -> 0 | I37: ='Pricing Details'!F41 -> 0 | J37: ='Pricing Details'!AV41 -> 0 | K37: ='Pricing Details'!AU41 -> 0 | M37: ='Pricing Details'!B41 -> 0 | N37: ='Pricing Details'!E41 | O37: ='Pricing Details'!G41 -> 0 | P37: ='Pricing Details'!F41 -> 0 | Q37: ='Pricing Details'!AV41 -> 0 | R37: =O37*Q37 -> 0 | T37: ='Pricing Details'!B41 -> 0 | U37: ='Pricing Details'!E41 | V37: ='Pricing Details'!G41 -> 0 | W37: ='Pricing Details'!H41 -> 0 | X37: ='Pricing Details'!I41 -> 0 | Y37: ='Pricing Details'!J41 -> 0 | Z37: ='Pricing Details'!K41 -> 0 | AA37: ='Pricing Details'!L41 -> 0 | AB37: ='Pricing Details'!M41 -> 0 | AC37: ='Pricing Details'!N41 -> 0 | ... BE37: ='Pricing Details'!AP41 -> 0
F38: ='Pricing Details'!B42 -> 0 | G38: ='Pricing Details'!E42 | H38: ='Pricing Details'!AR42 -> 0 | I38: ='Pricing Details'!F42 -> 0 | J38: ='Pricing Details'!AV42 -> 0 | K38: ='Pricing Details'!AU42 -> 0 | M38: ='Pricing Details'!B42 -> 0 | N38: ='Pricing Details'!E42 | O38: ='Pricing Details'!G42 -> 0 | P38: ='Pricing Details'!F42 -> 0 | Q38: ='Pricing Details'!AV42 -> 0 | R38: =O38*Q38 -> 0 | T38: ='Pricing Details'!B42 -> 0 | U38: ='Pricing Details'!E42 | V38: ='Pricing Details'!G42 -> 0 | W38: ='Pricing Details'!H42 -> 0 | X38: ='Pricing Details'!I42 -> 0 | Y38: ='Pricing Details'!J42 -> 0 | Z38: ='Pricing Details'!K42 -> 0 | AA38: ='Pricing Details'!L42 -> 0 | AB38: ='Pricing Details'!M42 -> 0 | AC38: ='Pricing Details'!N42 -> 0 | ... BE38: ='Pricing Details'!AP42 -> 0
F39: ='Pricing Details'!B43 -> 0 | G39: ='Pricing Details'!E43 | H39: ='Pricing Details'!AR43 -> 0 | I39: ='Pricing Details'!F43 -> 0 | J39: ='Pricing Details'!AV43 -> 0 | K39: ='Pricing Details'!AU43 -> 0 | M39: ='Pricing Details'!B43 -> 0 | N39: ='Pricing Details'!E43 | O39: ='Pricing Details'!G43 -> 0 | P39: ='Pricing Details'!F43 -> 0 | Q39: ='Pricing Details'!AV43 -> 0 | R39: =O39*Q39 -> 0 | T39: ='Pricing Details'!B43 -> 0 | U39: ='Pricing Details'!E43 | V39: ='Pricing Details'!G43 -> 0 | W39: ='Pricing Details'!H43 -> 0 | X39: ='Pricing Details'!I43 -> 0 | Y39: ='Pricing Details'!J43 -> 0 | Z39: ='Pricing Details'!K43 -> 0 | AA39: ='Pricing Details'!L43 -> 0 | AB39: ='Pricing Details'!M43 -> 0 | AC39: ='Pricing Details'!N43 -> 0 | ... BE39: ='Pricing Details'!AP43 -> 0
H40: =SUM(H5:H39) -> 310 | K40: =SUM(K5:K39) -> 71300 | O40: =SUM(O5:O39) -> 50 | Q40: Monthly | R40: =SUM(R5:R39) -> 11500
F42: T&M
F43: Resource Role | G43: Resource Location | H43: Total Estimated Hours | I43: Hourly Rate | J43: Estimated Fee
F44: ='Pricing Details'!B9 -> Sr. Change Manager | G44: ='Pricing Details'!E9 -> USA | H44: ='Pricing Details'!AR9 -> 310 | I44: ='Pricing Details'!F9 -> 275 | J44: ='Pricing Details'!AU9 -> 71300
F45: ='Pricing Details'!B10 -> 0 | G45: ='Pricing Details'!E10 | H45: ='Pricing Details'!AR10 -> 0 | I45: ='Pricing Details'!F10 -> 0 | J45: ='Pricing Details'!AU10 -> 0
F46: ='Pricing Details'!B11 -> 0 | G46: ='Pricing Details'!E11 | H46: ='Pricing Details'!AR11 -> 0 | I46: ='Pricing Details'!F11 -> 0 | J46: ='Pricing Details'!AU11 -> 0
F47: ='Pricing Details'!B12 -> 0 | G47: ='Pricing Details'!E12 | H47: ='Pricing Details'!AR12 -> 0 | I47: ='Pricing Details'!F12 -> 0 | J47: ='Pricing Details'!AU12 -> 0
F48: ='Pricing Details'!B13 -> 0 | G48: ='Pricing Details'!E13 | H48: ='Pricing Details'!AR13 -> 0 | I48: ='Pricing Details'!F13 -> 0 | J48: ='Pricing Details'!AU13 -> 0
F49: ='Pricing Details'!B14 -> 0 | G49: ='Pricing Details'!E14 | H49: ='Pricing Details'!AR14 -> 0 | I49: ='Pricing Details'!F14 -> 0 | J49: ='Pricing Details'!AU14 -> 0
F50: ='Pricing Details'!B15 -> 0 | G50: ='Pricing Details'!E15 | H50: ='Pricing Details'!AR15 -> 0 | I50: ='Pricing Details'!F15 -> 0 | J50: ='Pricing Details'!AU15 -> 0
F51: ='Pricing Details'!B16 -> 0 | G51: ='Pricing Details'!E16 | H51: ='Pricing Details'!AR16 -> 0 | I51: ='Pricing Details'!F16 -> 0 | J51: ='Pricing Details'!AU16 -> 0
F52: ='Pricing Details'!B17 -> 0 | G52: ='Pricing Details'!E17 | H52: ='Pricing Details'!AR17 -> 0 | I52: ='Pricing Details'!F17 -> 0 | J52: ='Pricing Details'!AU17 -> 0
F53: ='Pricing Details'!B18 -> 0 | G53: ='Pricing Details'!E18 | H53: ='Pricing Details'!AR18 -> 0 | I53: ='Pricing Details'!F18 -> 0 | J53: ='Pricing Details'!AU18 -> 0
F54: ='Pricing Details'!B19 -> 0 | G54: ='Pricing Details'!E19 | H54: ='Pricing Details'!AR19 -> 0 | I54: ='Pricing Details'!F19 -> 0 | J54: ='Pricing Details'!AU19 -> 0
F55: ='Pricing Details'!B20 -> 0 | G55: ='Pricing Details'!E20 | H55: ='Pricing Details'!AR20 -> 0 | I55: ='Pricing Details'!F20 -> 0 | J55: ='Pricing Details'!AU20 -> 0
... F78: ='Pricing Details'!B43 -> 0 | G78: ='Pricing Details'!E43 | H78: ='Pricing Details'!AR43 -> 0 | I78: ='Pricing Details'!F43 -> 0 | J78: ='Pricing Details'!AU43 -> 0
H79: =SUM(H44:H78) -> 310 | J79: =SUM(J44:J78) -> 71300

Sheet Resource List
A1: Practice | B1: Role | C1: Name | D1: Updated 11/11/2025
A2: Cloud_Practice_USA | B2: Program Manager | C2: Rodrigo Farinazo
A3: Cloud_Practice_USA | B3: Program Manager | C3: Michael Stevens
A4: Cloud_Practice_USA | B4: Sr. Program Lead | C4: Michael J Meier
A5: Cloud_Practice_USA | B5: Project Manager | C5: Kerri Dittmar
A6: Cloud_Practice_USA | B6: Engineer | C6: Harrison Koons
A7: Cloud_Practice_USA | B7: Program Lead | C7: Evan C List
A8: Cloud_Practice_USA | B8: Architect | C8: Christina Allan
A9: Cloud_Practice_USA | B9: Architect | C9: Brandon C Wagoner
A10: Cloud_Practice_USA | B10: Architect | C10: Eric Paul
A11: Cloud_Practice_USA | B11: Architect | C11: Sean Clark
A12: Cloud_Practice_USA | B12: Engineer | C12: Asha Angalla
A13: Cloud_Practice_USA | B13: Engineer | C13: Gowtham Nelavelli
... A277: TS_Practice_USA | B277: Business/Data Analyst | C277: Jinali Kamdar

Sheet Timeline 36 Weeks
G1: Week 1 Date is the Monday of the week of the Project Start Date on the Pricing Sheet tab
G2: Timeline in Weeks
B4: Week # | C4: 1 | D4: =C4+1 -> 2 | E4: =D4+1 -> 3 | F4: 4 | G4: 5 | H4: 6 | I4: 7 | J4: 8 | K4: 9 | L4: 10 | M4: 11 | N4: 12 | O4: 13 | P4: 14 | Q4: 15 | R4: 16 | S4: =R4+1 -> 17 | T4: =S4+1 -> 18 | U4: =T4+1 -> 19 | V4: =U4+1 -> 20 | W4: =V4+1 -> 21 | X4: =W4+1 -> 22 | Y4: =X4+1 -> 23 | Z4: =Y4+1 -> 24 | ... AP4: =AO4+1 -> 40
B5: Project Phases | C5: =('Pricing Details'!F4)-WEEKDAY('Pricing Details'!F4,3) -> 46055 | D5: =C5+7 -> 46062 | E5: =D5+7 -> 46069 | F5: =E5+7 -> 46076 | G5: =F5+7 -> 46083 | H5: =G5+7 -> 46090 | I5: =H5+7 -> 46097 | J5: =I5+7 -> 46104 | K5: =J5+7 -> 46111 | ... AP5: =AO5+7 -> 46328
B6: Mobilize | C6: 1
B7: Requirements | D7: 3
B8: Design | G8: 5
B9: Application Build / Unit Testing | L9: 12
B10: Data Integrations | J10: 14
B11: Report Build | R11: 6
B12: Performance Testing Prep & Execution | W12: 2
B13: SIT Prep | Y13: 1
B14: SIT Execute & Remediate | Z14: 2
B15: UAT Prep | AB15: 1
B16: UAT Execute & Remediate | AC16: 2
B17: Training Prep | AE17: 2
B18: Training Delivery | AG18: 1
B19: Data Validation | Q19: Reconciliation / Client sign-off
B20: Parallel #1 | AH20: 2
B21: Parallel #2 | AJ21: 2
B22: Go Live | AL22: 1
B23: Post Production Support / Hypercare | AM23: 2
B24: Holidays
B27: Project Manager (FTE combine US / India) | C27: 40 | D27: 40 | E27: 40 | F27: 40 | G27: 40 | H27: 40 | I27: 40 | J27: 40 | K27: 40 | L27: 40 | M27: 40 | N27: 40 | O27: 40 | P27: 40 | Q27: 40 | R27: 40 | S27: 40 | T27: 40 | U27: 40 | V27: 40 | W27: 40 | X27: 40 | Y27: 40 | Z27: 40 | AA27: 40 | AB27: 40 | AC27: 40 | AD27: 40 | AE27: 40 | AF27: 40 | AG27: 40 | AH27: 40 | AI27: 40 | AJ27: 40 | AK27: 40 | AL27: 40
B28: Architect | C28: 24 | D28: 36 | E28: 36 | F28: 36 | G28: 36 | H28: 36 | I28: 36 | J28: 36 | K28: 36 | L28: 24 | M28: 24 | N28: 16 | O28: 8 | P28: 8 | Q28: 8 | R28: 8 | S28: 8 | T28: 8 | U28: 8 | V28: 8 | W28: 8 | X28: 16 | Y28: 16 | Z28: 16 | AA28: 16 | AB28: 16 | AC28: 16 | AD28: 16
B29: FCC / Planning Lead Developer (US) | C29: 40 | D29: 40 | E29: 40 | F29: 40 | G29: 40 | H29: 40 | I29: 40 | J29: 40 | K29: 40 | L29: 40 | M29: 40 | N29: 40 | O29: 40 | P29: 40 | Q29: 40 | R29: 40 | S29: 40 | T29: 40 | U29: 40 | V29: 40 | W29: 40 | X29: 40 | Y29: 40 | Z29: 40 | AA29: 40 | AB29: 40 | AC29: 40 | AD29: 40 | AE29: 40 | AF29: 40 | AG29: 40 | AH29: 40 | AI29: 40 | AJ29: 40 | AK29: 40 | AL29: 40 | AM29: 40 | AN29: 40
B30: FCC / Planning Developer (India) | K30: 40 | L30: 40 | M30: 40 | N30: 40 | O30: 40 | P30: 40 | Q30: 40 | R30: 40 | S30: 40 | T30: 40 | U30: 40 | V30: 40 | W30: 40 | X30: 40 | Y30: 40 | Z30: 40 | AA30: 40 | AB30: 40 | AC30: 40 | AD30: 40 | AE30: 40 | AF30: 40 | AG30: 40 | AH30: 40 | AI30: 40 | AJ30: 40 | AK30: 40 | AL30: 40 | AM30: 40 | AN30: 40
B31: Data Integration Lead Developer (US) | I31: 40 | J31: 40 | K31: 40 | L31: 40 | M31: 40 | N31: 40 | O31: 40 | P31: 16 | Q31: 16 | R31: 16 | S31: 16 | T31: 16 | U31: 16 | V31: 16 | W31: 16 | X31: 16 | Y31: 36 | Z31: 36 | AA31: 36 | AB31: 16 | AC31: 24 | AD31: 24 | AE31: 8 | AF31: 8 | AG31: 8 | AH31: 8 | AI31: 8 | AJ31: 8 | AK31: 8 | AL31: 8
B32: Data Integration Developer (India) | K32: 40 | L32: 40 | M32: 40 | N32: 40 | O32: 40 | P32: 40 | Q32: 40 | R32: 40 | S32: 40 | T32: 40 | U32: 40 | V32: 40 | W32: 40 | X32: 40 | Y32: 40 | Z32: 40 | AA32: 40 | AB32: 40 | AC32: 40 | AD32: 40 | AE32: 40 | AF32: 40 | AG32: 40 | AH32: 40 | AI32: 40 | AJ32: 40 | AK32: 40 | AL32: 40 | AM32: 40 | AN32: 40
B33: Narrative Reporting Lead | R33: 40 | S33: 40 | T33: 40 | U33: 40 | V33: 40 | W33: 40

Sheet Deliverables 
A1: Mobilize | B1: Requirements | C1: Design | D1: Build | E1: Testing | F1: Training | G1: Parallel Testing | H1: HyperCare
A3: 1. Program Objective | B3: 1. Scope Alignment & Requirements Preparation | C3: 1. Design Sessions for Requirements | D3: 1. Application Development & Unit Testing | E3: 1. Performance Testing | F3: 1. Train-the-Trainer | G3: 1. Parallel Test support (required for FCC | optional for Planning) | H3: 1. Production Support
A4: Vision & Goals | B4: Conduct a scoping session to determine immediate needs and long-term goals. | C4: Current state process review | D4: Dimensions, members, primary hiearhies and alternate hierarchies | E4: Performance expections / benchmarks | F4: Training Guides | G4: Client led non-quarter end close | Donyati support
A5: Challenges & Priorities | B5: Gather Requirements for desired end state processes | C5: Conduct design workshops to flesh-out requirements | D5: Data Integrations sources and targets | E5: Performance Test Plan | F5: Training Exercises | G5: Client led quarter end close | Donyati Support
B6: Workshops to review and finalize RTM | C6: Table Read of Design Document | D6: Calculations / Rules | F6: Frequently Asked Questions (FAQ)
A7: 2. Governance & Team Structure | D7: Workflows | E7: 2. System Integration Testing (SIT) | F7: Deliver Instructor Led (ILT) | G7: 2. Deliverables
A8: Establish Steering Committee | B8: 2. Deliverables | C8: 2. Deliverables | D8: Reports | E8: SIT Test Plan | G8: none
A9: Establish Core Team | B9: Schedule Requirements Workshops | C9: Design Workshops | D9: Data Conversion & Mapping | E9: SIT Tracking tool (Jira, DevOps, Excel)
A10: Establish SMEs for functional processes and IT | B10: Requirements Traceablity Matrix (RTM) | C10: Detailed Design Document | D10: Deployment and Cut-over Plan | F10: 2. Deliverables | G10: TOLL GATE - Go Live approval
A11: Establish Governance Board | B11: Sign off on RTM | C11: Updated timeline incorporating design requirments | E11: 2. User Acceptace Testing (UAT) | F11: Training Materials
A12: Establish Project Management structure and RACI | C12: Sign-off on Design Document | D12: 2. Security | E12: Client approved UAT Scripts | F12: Training Delivery
B13: TOLL GATE - approval of Requirements Traceability Matrix (RTM) | C13: Updated budget and staffing model based on Design | D13: User security & groups | E13: UAT tracking tool (Jira, DevOps, Excel) | F13: FAQ Sheets
A14: 3. Project Planning & Budgeting | C14: Change Order for scope change from initial SOW | E14: UAT Tester training
A15: Draft High Level implementation timeline (weeks / task) | C15: Roadmap - Phased Implementation plan | D15: 3. Deliverables | E15: Security set up
A16: Develop budget vs. actual tracking template for financial transparency | D16: Instance Strategy | E16: SmartView client install
A17: Risk, Action, Issue, Decision (RAID) Logs | C17: TOLL GATE - approval of design document, timeline and budget | D17: Architecture Diagram
D18: Data Conversion & Validation Strategy | E18: 3. Deliverables
A19: 4. Communications | D19: Testing Strategy | E19: Approved Performance
A20: Establish Status Meeting cadence | D20: Training Strategy | E20: SIT Exit Criteria sign off
A21: Establish Steering Committee cadence | D21: Change Management Strategy | E21: UAT Exit Criteria sign off
A22: Schedule Requirements Sessions | D22: Performance Testing Plan
D23: System Integration Test (SIT) Plan | E23: TOLL GATE - Training Entrance Criteria sign off
A24: 5. Deliverables | D24: User Acceptance Test (UAT) Plan
A25: Project Charter | D25: User Acceptance Test Scripts
A26: Microsoft / Smartsheet Project Schedule | D26: Parallel Test Plan
A27: Budget Tracker | D27: Training Documents
A28: Project Status Report | D28: Admin Guides
A29: Project RACI | D29: UAT Entrance & Exit Criteria
A30: RAID Logs | D30: Training Entrance & Exit Criteria
A31: Communication Plan | D31: Parallel Entrance & Exit Criteria
A32: Scope Management Plan | D32: Go Live Checklist
D33: Security
D34: Client - Validated Historical Data
D36: TOLL GATE - UAT sign off, historical data validation sign off

Sheet Complexity Considerations
A1: Change to dimensions or hierarchies
A2: COA Redesign - completed before project kick off
A3: Currency translations - number of currencies
A4: Overrides
A5: Compliance & Audit Checks & Balances
A6: Rolling Forecast
A7: Data Integrations
B8: number of direct connect integrations
B9: number of flat file integrations
B10: complexity of mapping tables / conversion logic
A11: Reports
B12: number of reports
B13: complexity of reports
A14: Dashboards
B15: number of dashboards
B16: complexity of dashboards
A17: Allocations
B18: number of allocations
B19: complexity of allocations
A20: Business Rules
B21: number of business rules
B22: complexity of business rules
A23: Calculations
B24: number of calculations
B25: complexity of calculations
A26: Member Formulas
B27: number of member formulas
B28: complexity of member formulas

Sheet INSTRUCTIONS
A1: INSTRUCTIONS | AA1: 45923

Sheet Picklist
A1: Client | B1: Capability | C1: Services/Project Type | D1: Contract Types | E1: Practice | F1: Roles | G1: Practice | H1: Role | I1: Combo for Lookup | J1: People | K1: Person Location | M1: Practice | N1: Resource Roles | O1: Combo for Lookup | P1: Bill Rate | Q1: Cost | R1: Rate Location | T1: Month | U1: Business Hours | W1: Practice and Role (UNIQUE) | Y1: From Pricing Sheet Practice Role Combo (Rows 9-43) | Z1: Resources (FILTER) - Row 9 | AA1: Resources (FILTER) - Row 10 | AB1: Resources (FILTER) - Row 11 | AC1: Resources (FILTER) - Row 12 | AD1: Resources (FILTER) - Row 13 | AE1: Resources (FILTER) - Row 14 | AF1: Resources (FILTER) - Row 15 | AG1: Resources (FILTER) - Row 16 | AH1: Resources (FILTER) - Row 17 | AI1: Resources (FILTER) - Row 18 | AJ1: Resources (FILTER) - Row 19 | AK1: Resources (FILTER) - Row 20 | AL1: Resources (FILTER) - Row 21 | AM1: Resources (FILTER) - Row 22 | AN1: Resources (FILTER) - Row 23 | AO1: Resources (FILTER) - Row 24 | AP1: Resources (FILTER) - Row 25 | AQ1: Resources (FILTER) - Row 26 | AR1: Resources (FILTER) - Row 27 | AS1: Resources (FILTER) - Row 28 | AT1: Resources (FILTER) - Row 29 | AU1: Resources (FILTER) - Row 30 | AV1: Resources (FILTER) - Row 31 | AW1: Resources (FILTER) - Row 32 | AX1: Resources (FILTER) - Row 33 | AY1: Resources (FILTER) - Row 34 | AZ1: Resources (FILTER) - Row 35 | BA1: Resources (FILTER) - Row 36 | BB1: Resources (FILTER) - Row 37 | BC1: Resources (FILTER) - Row 38 | BD1: Resources (FILTER) - Row 39 | BE1: Resources (FILTER) - Row 40 | BF1: Resources (FILTER) - Row 41 | BG1: Resources (FILTER) - Row 42 | BH1: Resources (FILTER) - Row 43 | BJ1: Risk Profile | BK1: Type
A2: **New Client** | B2: ARCS | C2: Advisory | D2: T&M | E2: Cloud_Practice_USA | F2: Application Developer | G2: EPM_Practice_USA | H2: Application Developer | I2: =_xlfn.CONCAT(G2,H2) -> EPM_Practice_USAApplication Developer | J2: TBD | K2: USA | T2: 45688 | U2: 176 | W2: {=_xlfn.UNIQUE(I2:I521)} -> EPM_Practice_USAApplication Developer | Y2: =_xlfn.CONCAT('Pricing Details'!$A9,'Pricing Details'!$B9) -> EPM_Practice_USASr. Change Manager | Z2: {=_xlfn._xlws.SORT(_xlfn._xlws.FILTER($J$2:$J$542,$I$2:$I$542=$Y2),1)} -> Melissa O'Blenis | AA2: {=_xlfn._xlws.SORT(_xlfn._xlws.FILTER($J$2:$J$542,$I$2:$I$542=$Y3),1)} -> 0 | AB2: {=_xlfn._xlws.SORT(_xlfn._xlws.FILTER($J$2:$J$542,$I$2:$I$542=$Y4),1)} -> 0 | AC2: {=_xlfn._xlws.SORT(_xlfn._xlws.FILTER($J$2:$J$542,$I$2:$I$542=$Y5),1)} -> 0 | AD2: {=_xlfn._xlws.SORT(_xlfn._xlws.FILTER($J$2:$J$542,$I$2:$I$542=$Y6),1)} -> 0 | AE2: {=_xlfn._xlws.SORT(_xlfn._xlws.FILTER($J$2:$J$542,$I$2:$I$542=$Y7),1)} -> 0 | AF2: {=_xlfn._xlws.SORT(_xlfn._xlws.FILTER($J$2:$J$542,$I$2:$I$542=$Y8),1)} -> 0 | AG2: {=_xlfn._xlws.SORT(_xlfn._xlws.FILTER($J$2:$J$542,$I$2:$I$542=$Y9),1)} -> 0 | AH2: {=_xlfn._xlws.SORT(_xlfn._xlws.FILTER($J$2:$J$542,$I$2:$I$542=$Y10),1)} -> 0 | AI2: {=_xlfn._xlws.SORT(_xlfn._xlws.FILTER($J$2:$J$542,$I$2:$I$542=$Y11),1)} -> 0 | AJ2: {=_xlfn._xlws.SORT(_xlfn._xlws.FILTER($J$2:$J$542,$I$2:$I$542=$Y12),1)} -> 0 | AK2: {=_xlfn._xlws.SORT(_xlfn._xlws.FILTER($J$2:$J$542,$I$2:$I$542=$Y13),1)} -> 0 | AL2: {=_xlfn._xlws.SORT(_xlfn._xlws.FILTER($J$2:$J$542,$I$2:$I$542=$Y14),1)} -> 0 | AM2: {=_xlfn._xlws.SORT(_xlfn._xlws.FILTER($J$2:$J$542,$I$2:$I$542=$Y15),1)} -> 0 | AN2: {=_xlfn._xlws.SORT(_xlfn._xlws.FILTER($J$2:$J$542,$I$2:$I$542=$Y16),1)} -> 0 | AO2: {=_xlfn._xlws.SORT(_xlfn._xlws.FILTER($J$2:$J$542,$I$2:$I$542=$Y17),1)} -> 0 | AP2: {=_xlfn._xlws.SORT(_xlfn._xlws.FILTER($J$2:$J$542,$I$2:$I$542=$Y18),1)} -> 0 | AQ2: {=_xlfn._xlws.SORT(_xlfn._xlws.FILTER($J$2:$J$542,$I$2:$I$542=$Y19),1)} -> 0 | AR2: {=_xlfn._xlws.SORT(_xlfn._xlws.FILTER($J$2:$J$542,$I$2:$I$542=$Y20),1)} -> 0 | AS2: {=_xlfn._xlws.SORT(_xlfn._xlws.FILTER($J$2:$J$542,$I$2:$I$542=$Y21),1)} -> 0 | AT2: {=_xlfn._xlws.SORT(_xlfn._xlws.FILTER($J$2:$J$542,$I$2:$I$542=$Y22),1)} -> 0 | AU2: {=_xlfn._xlws.SORT(_xlfn._xlws.FILTER($J$2:$J$542,$I$2:$I$542=$Y23),1)} -> 0 | AV2: {=_xlfn._xlws.SORT(_xlfn._xlws.FILTER($J$2:$J$542,$I$2:$I$542=$Y24),1)} -> 0 | AW2: {=_xlfn._xlws.SORT(_xlfn._xlws.FILTER($J$2:$J$542,$I$2:$I$542=$Y25),1)} -> 0 | AX2: {=_xlfn._xlws.SORT(_xlfn._xlws.FILTER($J$2:$J$542,$I$2:$I$542=$Y26),1)} -> 0 | AY2: {=_xlfn._xlws.SORT(_xlfn._xlws.FILTER($J$2:$J$542,$I$2:$I$542=$Y27),1)} -> 0 | AZ2: {=_xlfn._xlws.SORT(_xlfn._xlws.FILTER($J$2:$J$542,$I$2:$I$542=$Y28),1)} -> 0 | BA2: {=_xlfn._xlws.SORT(_xlfn._xlws.FILTER($J$2:$J$542,$I$2:$I$542=$Y29),1)} -> 0 | BB2: {=_xlfn._xlws.SORT(_xlfn._xlws.FILTER($J$2:$J$542,$I$2:$I$542=$Y30),1)} -> 0 | BC2: {=_xlfn._xlws.SORT(_xlfn._xlws.FILTER($J$2:$J$542,$I$2:$I$542=$Y31),1)} -> 0 | BD2: {=_xlfn._xlws.SORT(_xlfn._xlws.FILTER($J$2:$J$542,$I$2:$I$542=$Y32),1)} -> 0 | BE2: {=_xlfn._xlws.SORT(_xlfn._xlws.FILTER($J$2:$J$542,$I$2:$I$542=$Y33),1)} -> 0 | BF2: {=_xlfn._xlws.SORT(_xlfn._xlws.FILTER($J$2:$J$542,$I$2:$I$542=$Y34),1)} -> 0 | BG2: {=_xlfn._xlws.SORT(_xlfn._xlws.FILTER($J$2:$J$542,$I$2:$I$542=$Y35),1)} -> 0 | BH2: {=_xlfn._xlws.SORT(_xlfn._xlws.FILTER($J$2:$J$542,$I$2:$I$542=$Y36),1)} -> 0 | BJ2: Low | BK2: New
A3: 1800HANSONS | B3: AWS | C3: Application Rationalization | D3: T&M - On Demand | E3: EPM_Practice_Canada_-_Consolidation | F3: Application Developer - DI | G3: EPM_Practice_USA | H3: Project Manager | I3: =_xlfn.CONCAT(G3,H3) -> EPM_Practice_USAProject Manager | J3: TBD | K3: USA | M3: EPM_Practice_USA | N3: Application Developer | O3: =_xlfn.CONCAT(M3,N3) -> EPM_Practice_USAApplication Developer | P3: 215 | Q3: 125 | R3: USA | T3: 45716 | U3: 152 | W3: EPM_Practice_USAProject Manager | Y3: =_xlfn.CONCAT('Pricing Details'!$A10,'Pricing Details'!$B10) | Z3: TBD | AA3: 0 | AB3: 0 | AC3: 0 | AD3: 0 | AE3: 0 | AF3: 0 | AG3: 0 | AH3: 0 | AI3: 0 | AJ3: 0 | AK3: 0 | AL3: 0 | AM3: 0 | AN3: 0 | AO3: 0 | AP3: 0 | AQ3: 0 | AR3: 0 | AS3: 0 | AT3: 0 | AU3: 0 | AV3: 0 | AW3: 0 | AX3: 0 | AY3: 0 | AZ3: 0 | BA3: 0 | BB3: 0 | BC3: 0 | BD3: 0 | BE3: 0 | BF3: 0 | BG3: 0 | BH3: 0 | BJ3: Medium | BK3: Expansion
A4: Acadia Healthcare | B4: Azure | C4: Application Support | D4: Fixed Fee | E4: EPM_Practice_India | F4: Application Developer - FCC | G4: EPM_Practice_USA | H4: Sr. Application Developer | I4: =_xlfn.CONCAT(G4,H4) -> EPM_Practice_USASr. Application Developer | J4: TBD | K4: USA | M4: EPM_Practice_USA | N4: Project Manager | O4: =_xlfn.CONCAT(M4,N4) -> EPM_Practice_USAProject Manager | P4: 230 | Q4: 130 | R4: USA | T4: 45747 | U4: 168 | W4: EPM_Practice_USASr. Application Developer | Y4: =_xlfn.CONCAT('Pricing Details'!$A11,'Pricing Details'!$B11) | AA4: 0 | AB4: 0 | AC4: 0 | AD4: 0 | AE4: 0 | AF4: 0 | AG4: 0 | AH4: 0 | AI4: 0 | AJ4: 0 | AK4: 0 | AL4: 0 | AM4: 0 | AN4: 0 | AO4: 0 | AP4: 0 | AQ4: 0 | AR4: 0 | AS4: 0 | AT4: 0 | AU4: 0 | AV4: 0 | AW4: 0 | AX4: 0 | AY4: 0 | AZ4: 0 | BA4: 0 | BB4: 0 | BC4: 0 | BD4: 0 | BE4: 0 | BF4: 0 | BG4: 0 | BH4: 0 | BJ4: High | BK4: Renewal
A5: Adecco | B5: Backend Technologies | C5: Assessment | D5: Milestone | E5: EPM_Practice_India_-_Consolidation | F5: Application Developer - PLN | G5: EPM_Practice_USA | H5: Sr. Project Manager | I5: =_xlfn.CONCAT(G5,H5) -> EPM_Practice_USASr. Project Manager | J5: TBD | K5: USA | M5: EPM_Practice_USA | N5: Sr. Application Developer | O5: =_xlfn.CONCAT(M5,N5) -> EPM_Practice_USASr. Application Developer | P5: 240 | Q5: 135 | R5: USA | T5: 45777 | U5: 176 | W5: EPM_Practice_USASr. Project Manager | Y5: =_xlfn.CONCAT('Pricing Details'!$A12,'Pricing Details'!$B12) | AA5: 0 | AB5: 0 | AC5: 0 | AD5: 0 | AE5: 0 | AF5: 0 | AG5: 0 | AH5: 0 | AI5: 0 | AJ5: 0 | AK5: 0 | AL5: 0 | AM5: 0 | AN5: 0 | AO5: 0 | AP5: 0 | AQ5: 0 | AR5: 0 | AS5: 0 | AT5: 0 | AU5: 0 | AV5: 0 | AW5: 0 | AX5: 0 | AY5: 0 | AZ5: 0 | BA5: 0 | BB5: 0 | BC5: 0 | BD5: 0 | BE5: 0 | BF5: 0 | BG5: 0 | BH5: 0
A6: Adecco(Oracle) | B6: BCP/DR | C6: Business Analyst Support | E6: EPM_Practice_India_-_Integration | F6: Application Lead | G6: EPM_Practice_USA | H6: Change Manager | I6: =_xlfn.CONCAT(G6,H6) -> EPM_Practice_USAChange Manager | J6: TBD | K6: USA | M6: EPM_Practice_USA | N6: Sr. Project Manager | O6: =_xlfn.CONCAT(M6,N6) -> EPM_Practice_USASr. Project Manager | P6: 250 | Q6: 140 | R6: USA | T6: 45808 | U6: 168 | W6: EPM_Practice_USAChange Manager | Y6: =_xlfn.CONCAT('Pricing Details'!$A13,'Pricing Details'!$B13) | AA6: 0 | AB6: 0 | AC6: 0 | AD6: 0 | AE6: 0 | AF6: 0 | AG6: 0 | AH6: 0 | AI6: 0 | AJ6: 0 | AK6: 0 | AL6: 0 | AM6: 0 | AN6: 0 | AO6: 0 | AP6: 0 | AQ6: 0 | AR6: 0 | AS6: 0 | AT6: 0 | AU6: 0 | AV6: 0 | AW6: 0 | AX6: 0 | AY6: 0 | AZ6: 0 | BA6: 0 | BB6: 0 | BC6: 0 | BD6: 0 | BE6: 0 | BF6: 0 | BG6: 0 | BH6: 0
A7: ADVICS | B7: BI | C7: Change Management | E7: EPM_Practice_India_-_Planning | F7: Application Lead - FCC | G7: EPM_Practice_USA | H7: Sr. Change Manager | I7: =_xlfn.CONCAT(G7,H7) -> EPM_Practice_USASr. Change Manager | J7: TBD | K7: USA | M7: EPM_Practice_USA | N7: Change Manager | O7: =_xlfn.CONCAT(M7,N7) -> EPM_Practice_USAChange Manager | P7: 265 | Q7: 145 | R7: USA | T7: 45838 | U7: 168 | W7: EPM_Practice_USASr. Change Manager | Y7: =_xlfn.CONCAT('Pricing Details'!$A14,'Pricing Details'!$B14) | AA7: 0 | AB7: 0 | AC7: 0 | AD7: 0 | AE7: 0 | AF7: 0 | AG7: 0 | AH7: 0 | AI7: 0 | AJ7: 0 | AK7: 0 | AL7: 0 | AM7: 0 | AN7: 0 | AO7: 0 | AP7: 0 | AQ7: 0 | AR7: 0 | AS7: 0 | AT7: 0 | AU7: 0 | AV7: 0 | AW7: 0 | AX7: 0 | AY7: 0 | AZ7: 0 | BA7: 0 | BB7: 0 | BC7: 0 | BD7: 0 | BE7: 0 | BF7: 0 | BG7: 0 | BH7: 0
A8: Aisin World Corp of America | B8: Cloud Engineering | C8: Deployment Support | E8: EPM_Practice_USA | F8: Application Lead - PLN | G8: EPM_Practice_USA | H8: Application Lead | I8: =_xlfn.CONCAT(G8,H8) -> EPM_Practice_USAApplication Lead | J8: TBD | K8: USA | M8: EPM_Practice_USA | N8: Sr. Change Manager | O8: =_xlfn.CONCAT(M8,N8) -> EPM_Practice_USASr. Change Manager | P8: 275 | Q8: 165 | R8: USA | T8: 45869 | U8: 176 | W8: EPM_Practice_USAApplication Lead | Y8: =_xlfn.CONCAT('Pricing Details'!$A15,'Pricing Details'!$B15) | AA8: 0 | AB8: 0 | AC8: 0 | AD8: 0 | AE8: 0 | AF8: 0 | AG8: 0 | AH8: 0 | AI8: 0 | AJ8: 0 | AK8: 0 | AL8: 0 | AM8: 0 | AN8: 0 | AO8: 0 | AP8: 0 | AQ8: 0 | AR8: 0 | AS8: 0 | AT8: 0 | AU8: 0 | AV8: 0 | AW8: 0 | AX8: 0 | AY8: 0 | AZ8: 0 | BA8: 0 | BB8: 0 | BC8: 0 | BD8: 0 | BE8: 0 | BF8: 0 | BG8: 0 | BH8: 0
A9: AIT Worldwide Logistics | B9: Cloud IP | C9: Development | E9: EPM_Practice_USA_-_Consolidation | F9: Application Support Lead | G9: EPM_Practice_USA | H9: Functional Lead | I9: =_xlfn.CONCAT(G9,H9) -> EPM_Practice_USAFunctional Lead | J9: TBD | K9: USA | M9: EPM_Practice_USA | N9: Application Lead | O9: =_xlfn.CONCAT(M9,N9) -> EPM_Practice_USAApplication Lead | P9: 265 | Q9: 145 | R9: USA | T9: 45900 | U9: 168 | W9: EPM_Practice_USAFunctional Lead | Y9: =_xlfn.CONCAT('Pricing Details'!$A16,'Pricing Details'!$B16) | AA9: 0 | AB9: 0 | AC9: 0 | AD9: 0 | AE9: 0 | AF9: 0 | AG9: 0 | AH9: 0 | AI9: 0 | AJ9: 0 | AK9: 0 | AL9: 0 | AM9: 0 | AN9: 0 | AO9: 0 | AP9: 0 | AQ9: 0 | AR9: 0 | AS9: 0 | AT9: 0 | AU9: 0 | AV9: 0 | AW9: 0 | AX9: 0 | AY9: 0 | AZ9: 0 | BA9: 0 | BB9: 0 | BC9: 0 | BD9: 0 | BE9: 0 | BF9: 0 | BG9: 0 | BH9: 0
A10: Amentum(SC&H) | B10: Cloud PM | C10: Divestiture/Spinoff Support | E10: EPM_Practice_USA_-_Integration | F10: Application Support Lead - EPB | G10: EPM_Practice_USA | H10: Sr. Application Lead | I10: =_xlfn.CONCAT(G10,H10) -> EPM_Practice_USASr. Application Lead | J10: TBD | K10: USA | M10: EPM_Practice_USA | N10: Functional Lead | O10: =_xlfn.CONCAT(M10,N10) -> EPM_Practice_USAFunctional Lead | P10: 315 | Q10: 170 | R10: USA | T10: 45930 | U10: 168 | W10: EPM_Practice_USASr. Application Lead | Y10: =_xlfn.CONCAT('Pricing Details'!$A17,'Pricing Details'!$B17)
A11: AmTrust Financial Services | B11: Consolidation Cloud | C11: Enhancements | E11: EPM_Practice_USA_-_Managed_Services | F11: Application Support Lead - FCC | G11: EPM_Practice_USA | H11: Solution Architect | I11: =_xlfn.CONCAT(G11,H11) -> EPM_Practice_USASolution Architect | J11: TBD | K11: USA | M11: EPM_Practice_USA | N11: Sr. Application Lead | O11: =_xlfn.CONCAT(M11,N11) -> EPM_Practice_USASr. Application Lead | P11: 290 | Q11: 160 | R11: USA | T11: 45961 | U11: 184 | W11: EPM_Practice_USASolution Architect | Y11: =_xlfn.CONCAT('Pricing Details'!$A18,'Pricing Details'!$B18)
A12: AmTrust Financial(Oracle) | B12: CPM IP | C12: Finance Transformation | E12: EPM_Practice_USA_-_Planning | F12: Architect | G12: EPM_Practice_USA | H12: Solution Architect - FCC | I12: =_xlfn.CONCAT(G12,H12) -> EPM_Practice_USASolution Architect - FCC | J12: TBD | K12: USA | M12: EPM_Practice_USA | N12: Solution Architect | O12: =_xlfn.CONCAT(M12,N12) -> EPM_Practice_USASolution Architect | P12: 365 | Q12: 185 | R12: USA | T12: 45991 | U12: 144 | W12: EPM_Practice_USASolution Architect - FCC | Y12: =_xlfn.CONCAT('Pricing Details'!$A19,'Pricing Details'!$B19)
A13: Anthem(TNP Systems) | B13: Cybersecurity | C13: Functional Support | E13: ERP_Practice_Argentina | F13: Business/Data Analyst | G13: EPM_Practice_USA | H13: Sr. Solution Architect | I13: =_xlfn.CONCAT(G13,H13) -> EPM_Practice_USASr. Solution Architect | J13: TBD | K13: USA | M13: EPM_Practice_USA | N13: Solution Architect - FCC | O13: =_xlfn.CONCAT(M13,N13) -> EPM_Practice_USASolution Architect - FCC | P13: 365 | Q13: 185 | R13: USA | T13: 46022 | U13: 176 | W13: EPM_Practice_USASr. Solution Architect | Y13: =_xlfn.CONCAT('Pricing Details'!$A20,'Pricing Details'!$B20)
A14: Apex Tool Group | B14: DART | C14: Implementation | E14: ERP_Practice_Brazil | F14: Developer | G14: EPM_Practice_USA | H14: Principal | I14: =_xlfn.CONCAT(G14,H14) -> EPM_Practice_USAPrincipal | J14: TBD | K14: USA | M14: EPM_Practice_USA | N14: Sr. Solution Architect | O14: =_xlfn.CONCAT(M14,N14) -> EPM_Practice_USASr. Solution Architect | P14: 390 | Q14: 195 | R14: USA | T14: 46053 | U14: 168 | W14: EPM_Practice_USAPrincipal | Y14: =_xlfn.CONCAT('Pricing Details'!$A21,'Pricing Details'!$B21)
A15: Aptiv | B15: Data Engineering | C15: Infrastructure Support | E15: ERP_Practice_CzechRepublic | F15: DevOps Engineer | G15: EPM_Practice_USA | H15: Principal Architect | I15: =_xlfn.CONCAT(G15,H15) -> EPM_Practice_USAPrincipal Architect | J15: TBD | K15: USA | M15: EPM_Practice_USA | N15: Principal | O15: =_xlfn.CONCAT(M15,N15) -> EPM_Practice_USAPrincipal | P15: 415 | Q15: 205 | R15: USA | T15: 46081 | U15: 152 | W15: EPM_Practice_USAPrincipal Architect | Y15: =_xlfn.CONCAT('Pricing Details'!$A22,'Pricing Details'!$B22)
A16: Argo | B16: Data Governance | C16: Licenses | E16: ERP_Practice_Germany | F16: Engineer | G16: EPM_Practice_USA_-_Consolidation | H16: Application Developer - FCC | I16: =_xlfn.CONCAT(G16,H16) -> EPM_Practice_USA_-_ConsolidationApplication Developer - FCC | J16: TBD | K16: USA | M16: EPM_Practice_USA | N16: Principal Architect | O16: =_xlfn.CONCAT(M16,N16) -> EPM_Practice_USAPrincipal Architect | P16: 450 | Q16: 235 | R16: USA | T16: 46112 | U16: 176 | W16: EPM_Practice_USA_-_ConsolidationApplication Developer - FCC | Y16: =_xlfn.CONCAT('Pricing Details'!$A23,'Pricing Details'!$B23)
A17: Argo(Secure24) | B17: Data Transformation | C17: Mergers/Acquisitions Support | E17: ERP_Practice_India | F17: Functional Lead | G17: EPM_Practice_USA_-_Consolidation | H17: Sr. Application Developer - FCC | I17: =_xlfn.CONCAT(G17,H17) -> EPM_Practice_USA_-_ConsolidationSr. Application Developer - FCC | J17: TBD | K17: USA | T17: 46142 | U17: 176 | W17: EPM_Practice_USA_-_ConsolidationSr. Application Developer - FCC | Y17: =_xlfn.CONCAT('Pricing Details'!$A24,'Pricing Details'!$B24)
A18: Argon Medical Devices | B18: Databricks | C18: Migration | E18: ERP_Practice_Mexico | F18: Integration Lead | G18: EPM_Practice_USA_-_Consolidation | H18: Sr. Application Developer - ARC | I18: =_xlfn.CONCAT(G18,H18) -> EPM_Practice_USA_-_ConsolidationSr. Application Developer - ARC | J18: TBD | K18: USA | M18: EPM_Practice_USA_-_Consolidation | N18: Application Developer - FCC | O18: =_xlfn.CONCAT(M18,N18) -> EPM_Practice_USA_-_ConsolidationApplication Developer - FCC | P18: 215 | Q18: 125 | R18: USA | T18: 46173 | U18: 160 | W18: EPM_Practice_USA_-_ConsolidationSr. Application Developer - ARC | Y18: =_xlfn.CONCAT('Pricing Details'!$A25,'Pricing Details'!$B25)
A19: Aspen Dental(Xoogify) | B19: DBA | C19: Optimization | E19: ERP_Practice_Spain | F19: Principal | G19: EPM_Practice_USA_-_Consolidation | H19: Application Lead - FCC | I19: =_xlfn.CONCAT(G19,H19) -> EPM_Practice_USA_-_ConsolidationApplication Lead - FCC | J19: TBD | K19: USA | M19: EPM_Practice_USA_-_Consolidation | N19: Sr. Application Developer - FCC | O19: =_xlfn.CONCAT(M19,N19) -> EPM_Practice_USA_-_ConsolidationSr. Application Developer - FCC | P19: 240 | Q19: 135 | R19: USA | T19: 46203 | U19: 176 | W19: EPM_Practice_USA_-_ConsolidationApplication Lead - FCC | Y19: =_xlfn.CONCAT('Pricing Details'!$A26,'Pricing Details'!$B26)
A20: AT&T(Badal) | B20: DevOps Technologies | C20: POC | E20: ERP_Practice_USA | F20: Principal Architect | G20: EPM_Practice_USA_-_Consolidation | H20: Sr. Application Lead - FCC | I20: =_xlfn.CONCAT(G20,H20) -> EPM_Practice_USA_-_ConsolidationSr. Application Lead - FCC | J20: TBD | K20: USA | M20: EPM_Practice_USA_-_Consolidation | N20: Sr. Application Developer - ARC | O20: =_xlfn.CONCAT(M20,N20) -> EPM_Practice_USA_-_ConsolidationSr. Application Developer - ARC | P20: 240 | Q20: 135 | R20: USA | T20: 46234 | U20: 176 | W20: EPM_Practice_USA_-_ConsolidationSr. Application Lead - FCC | Y20: =_xlfn.CONCAT('Pricing Details'!$A27,'Pricing Details'!$B27)
A21: AT&T(Bravens) | B21: DRM | C21: Portfolio Management | E21: PS_Practice_USA | F21: Program Lead | G21: EPM_Practice_USA_-_Consolidation | H21: Solution Architect | I21: =_xlfn.CONCAT(G21,H21) -> EPM_Practice_USA_-_ConsolidationSolution Architect | J21: TBD | K21: USA | M21: EPM_Practice_USA_-_Consolidation | N21: Application Lead - FCC | O21: =_xlfn.CONCAT(M21,N21) -> EPM_Practice_USA_-_ConsolidationApplication Lead - FCC | P21: 265 | Q21: 145 | R21: USA | T21: 46265 | U21: 168 | W21: EPM_Practice_USA_-_ConsolidationSolution Architect | Y21: =_xlfn.CONCAT('Pricing Details'!$A28,'Pricing Details'!$B28)
A22: AT&T(Data Piper) | B22: Duck Creek Suite | C22: Process Transformation | E22: TS_Practice_India | F22: Program Manager | G22: EPM_Practice_USA_-_Consolidation | H22: Solution Architect - FCC | I22: =_xlfn.CONCAT(G22,H22) -> EPM_Practice_USA_-_ConsolidationSolution Architect - FCC | J22: TBD | K22: USA | M22: EPM_Practice_USA_-_Consolidation | N22: Sr. Application Lead - FCC | O22: =_xlfn.CONCAT(M22,N22) -> EPM_Practice_USA_-_ConsolidationSr. Application Lead - FCC | P22: 290 | Q22: 160 | R22: USA | T22: 46295 | U22: 168 | W22: EPM_Practice_USA_-_ConsolidationSolution Architect - FCC | Y22: =_xlfn.CONCAT('Pricing Details'!$A29,'Pricing Details'!$B29)
A23: AT&T(ZeroChaos) | B23: EPM Cloud Suite | C23: Program Management | E23: TS_Practice_USA | F23: Project Coordinator | G23: EPM_Practice_USA_-_Consolidation | H23: Sr. Solution Architect - FCC | I23: =_xlfn.CONCAT(G23,H23) -> EPM_Practice_USA_-_ConsolidationSr. Solution Architect - FCC | J23: TBD | K23: USA | M23: EPM_Practice_USA_-_Consolidation | N23: Solution Architect | O23: =_xlfn.CONCAT(M23,N23) -> EPM_Practice_USA_-_ConsolidationSolution Architect | P23: 365 | Q23: 185 | R23: USA | T23: 46326 | U23: 176 | W23: EPM_Practice_USA_-_ConsolidationSr. Solution Architect - FCC | Y23: =_xlfn.CONCAT('Pricing Details'!$A30,'Pricing Details'!$B30)
A24: AvMed(Secure24) | B24: EPM IP | C24: Project Management | E24: Donyati_Products_USA | F24: Project Manager | G24: EPM_Practice_USA_-_Integration | H24: Application Lead | I24: =_xlfn.CONCAT(G24,H24) -> EPM_Practice_USA_-_IntegrationApplication Lead | J24: TBD | K24: USA | M24: EPM_Practice_USA_-_Consolidation | N24: Solution Architect - FCC | O24: =_xlfn.CONCAT(M24,N24) -> EPM_Practice_USA_-_ConsolidationSolution Architect - FCC | P24: 365 | Q24: 185 | R24: USA | T24: 46356 | U24: 152 | W24: EPM_Practice_USA_-_IntegrationApplication Lead | Y24: =_xlfn.CONCAT('Pricing Details'!$A31,'Pricing Details'!$B31)
A25: Avnet | B25: EPM PM | C25: Referral | E25: ICSub_Contractor_USA | F25: QA Tester - Automation | G25: EPM_Practice_USA_-_Integration | H25: Sr. Application Support Lead | I25: =_xlfn.CONCAT(G25,H25) -> EPM_Practice_USA_-_IntegrationSr. Application Support Lead | J25: TBD | K25: USA | M25: EPM_Practice_USA_-_Consolidation | N25: Sr. Solution Architect - FCC | O25: =_xlfn.CONCAT(M25,N25) -> EPM_Practice_USA_-_ConsolidationSr. Solution Architect - FCC | P25: 390 | Q25: 195 | R25: USA | T25: 46387 | U25: 176 | W25: EPM_Practice_USA_-_IntegrationSr. Application Support Lead | Y25: =_xlfn.CONCAT('Pricing Details'!$A32,'Pricing Details'!$B32)
A26: Avnet(OneStream) | B26: ERP PM | C26: Solution Architecture | E26: ICSub_Contractor_India | F26: QA Tester - Manual | G26: EPM_Practice_USA_-_Integration | H26: Application Developer - DI | I26: =_xlfn.CONCAT(G26,H26) -> EPM_Practice_USA_-_IntegrationApplication Developer - DI | J26: TBD | K26: USA | T26: 46418 | U26: 160 | W26: EPM_Practice_USA_-_IntegrationApplication Developer - DI | Y26: =_xlfn.CONCAT('Pricing Details'!$A33,'Pricing Details'!$B33)
A27: BCBS Michigan | B27: Essbase | C27: Strategy | F27: Security Engineer | G27: EPM_Practice_USA_-_Integration | H27: Sr. Application Developer - DI | I27: =_xlfn.CONCAT(G27,H27) -> EPM_Practice_USA_-_IntegrationSr. Application Developer - DI | J27: TBD | K27: USA | M27: EPM_Practice_USA_-_Integration | N27: Application Lead | O27: =_xlfn.CONCAT(M27,N27) -> EPM_Practice_USA_-_IntegrationApplication Lead | P27: 265 | Q27: 145 | R27: USA | T27: 46446 | U27: 152 | W27: EPM_Practice_USA_-_IntegrationSr. Application Developer - DI | Y27: =_xlfn.CONCAT('Pricing Details'!$A34,'Pricing Details'!$B34)
A28: Bell Canada(Badal) | B28: FDMEE | C28: Support | F28: Service Delivery Manager | G28: EPM_Practice_USA_-_Integration | H28: Application Lead - DI | I28: =_xlfn.CONCAT(G28,H28) -> EPM_Practice_USA_-_IntegrationApplication Lead - DI | J28: TBD | K28: USA | M28: EPM_Practice_USA_-_Integration | N28: Sr. Application Support Lead | O28: =_xlfn.CONCAT(M28,N28) -> EPM_Practice_USA_-_IntegrationSr. Application Support Lead | P28: 210 | Q28: 140 | R28: USA | T28: 46477 | U28: 184 | W28: EPM_Practice_USA_-_IntegrationApplication Lead - DI | Y28: =_xlfn.CONCAT('Pricing Details'!$A35,'Pricing Details'!$B35)
A29: Bell Canada(Data Piper) | B29: Frontend Technologies | C29: Testing | F29: Software Engineer | G29: EPM_Practice_USA_-_Integration | H29: Sr. Application Lead - DI | I29: =_xlfn.CONCAT(G29,H29) -> EPM_Practice_USA_-_IntegrationSr. Application Lead - DI | J29: TBD | K29: USA | M29: EPM_Practice_USA_-_Integration | N29: Application Developer - DI | O29: =_xlfn.CONCAT(M29,N29) -> EPM_Practice_USA_-_IntegrationApplication Developer - DI | P29: 215 | Q29: 125 | R29: USA | T29: 46507 | U29: 176 | W29: EPM_Practice_USA_-_IntegrationSr. Application Lead - DI | Y29: =_xlfn.CONCAT('Pricing Details'!$A36,'Pricing Details'!$B36)
A30: Blue Ribbon(Trace3) | B30: Google Cloud | C30: Upgrade | F30: Solution Architect | G30: EPM_Practice_USA_-_Integration | H30: Solution Architect - DI | I30: =_xlfn.CONCAT(G30,H30) -> EPM_Practice_USA_-_IntegrationSolution Architect - DI | J30: TBD | K30: USA | M30: EPM_Practice_USA_-_Integration | N30: Sr. Application Developer - DI | O30: =_xlfn.CONCAT(M30,N30) -> EPM_Practice_USA_-_IntegrationSr. Application Developer - DI | P30: 240 | Q30: 135 | R30: USA | T30: 46538 | U30: 160 | W30: EPM_Practice_USA_-_IntegrationSolution Architect - DI | Y30: =_xlfn.CONCAT('Pricing Details'!$A37,'Pricing Details'!$B37)
A31: Body Control Systems | B31: HFM | F31: Solution Architect - DI | G31: EPM_Practice_USA_-_Integration | H31: Sr. Solution Architect | I31: =_xlfn.CONCAT(G31,H31) -> EPM_Practice_USA_-_IntegrationSr. Solution Architect | J31: TBD | K31: USA | M31: EPM_Practice_USA_-_Integration | N31: Application Lead - DI | O31: =_xlfn.CONCAT(M31,N31) -> EPM_Practice_USA_-_IntegrationApplication Lead - DI | P31: 265 | Q31: 145 | R31: USA | T31: 46568 | U31: 176 | W31: EPM_Practice_USA_-_IntegrationSr. Solution Architect | Y31: =_xlfn.CONCAT('Pricing Details'!$A38,'Pricing Details'!$B38)
A32: BorgWarner | B32: Hyperion Suite | F32: Solution Architect - FCC | G32: EPM_Practice_USA_-_Integration | H32: Sr. Solution Architect - DI | I32: =_xlfn.CONCAT(G32,H32) -> EPM_Practice_USA_-_IntegrationSr. Solution Architect - DI | J32: TBD | K32: USA | M32: EPM_Practice_USA_-_Integration | N32: Sr. Application Lead - DI | O32: =_xlfn.CONCAT(M32,N32) -> EPM_Practice_USA_-_IntegrationSr. Application Lead - DI | P32: 290 | Q32: 160 | R32: USA | T32: 46599 | U32: 168 | W32: EPM_Practice_USA_-_IntegrationSr. Solution Architect - DI | Y32: =_xlfn.CONCAT('Pricing Details'!$A39,'Pricing Details'!$B39)
A33: BRAVVOX | B33: IT | F33: Solution Architect - PLN | G33: EPM_Practice_USA_-_Managed_Services | H33: Application Support Lead - FCC | I33: =_xlfn.CONCAT(G33,H33) -> EPM_Practice_USA_-_Managed_ServicesApplication Support Lead - FCC | J33: TBD | K33: USA | M33: EPM_Practice_USA_-_Integration | N33: Solution Architect - DI | O33: =_xlfn.CONCAT(M33,N33) -> EPM_Practice_USA_-_IntegrationSolution Architect - DI | P33: 365 | Q33: 185 | R33: USA | T33: 46630 | U33: 176 | W33: EPM_Practice_USA_-_Managed_ServicesApplication Support Lead - FCC | Y33: =_xlfn.CONCAT('Pricing Details'!$A40,'Pricing Details'!$B40)
A34: Builders FirstSource | B34: Middleware | F34: Sr. Application Developer | G34: EPM_Practice_USA_-_Managed_Services | H34: Sr. Application Lead - PLN | I34: =_xlfn.CONCAT(G34,H34) -> EPM_Practice_USA_-_Managed_ServicesSr. Application Lead - PLN | J34: TBD | K34: USA | M34: EPM_Practice_USA_-_Integration | N34: Sr. Solution Architect | O34: =_xlfn.CONCAT(M34,N34) -> EPM_Practice_USA_-_IntegrationSr. Solution Architect | P34: 390 | Q34: 195 | R34: USA | T34: 46660 | U34: 168 | W34: EPM_Practice_USA_-_Managed_ServicesSr. Application Lead - PLN | Y34: =_xlfn.CONCAT('Pricing Details'!$A41,'Pricing Details'!$B41)
A35: Bunge(Microland) | B35: MuleSoft | F35: Sr. Application Developer - DI | G35: EPM_Practice_USA_-_Managed_Services | H35: Sr. Application Support Lead - FCC | I35: =_xlfn.CONCAT(G35,H35) -> EPM_Practice_USA_-_Managed_ServicesSr. Application Support Lead - FCC | J35: TBD | K35: USA | M35: EPM_Practice_USA_-_Integration | N35: Sr. Solution Architect - DI | O35: =_xlfn.CONCAT(M35,N35) -> EPM_Practice_USA_-_IntegrationSr. Solution Architect - DI | P35: 390 | Q35: 195 | R35: USA | T35: 46691 | U35: 176 | W35: EPM_Practice_USA_-_Managed_ServicesSr. Application Support Lead - FCC | Y35: =_xlfn.CONCAT('Pricing Details'!$A42,'Pricing Details'!$B42)
A36: CarTech(SC&H) | B36: OCI | F36: Sr. Application Developer - PLN | G36: EPM_Practice_USA_-_Managed_Services | H36: Sr. Application Lead - FCC | I36: =_xlfn.CONCAT(G36,H36) -> EPM_Practice_USA_-_Managed_ServicesSr. Application Lead - FCC | J36: TBD | K36: USA | T36: 46721 | U36: 160 | W36: EPM_Practice_USA_-_Managed_ServicesSr. Application Lead - FCC | Y36: =_xlfn.CONCAT('Pricing Details'!$A43,'Pricing Details'!$B43)
A37: Catholic Relief Services | B37: OneStream | F37: Sr. Application Lead | G37: EPM_Practice_USA_-_Managed_Services | H37: Application Support Lead - PLN | I37: =_xlfn.CONCAT(G37,H37) -> EPM_Practice_USA_-_Managed_ServicesApplication Support Lead - PLN | J37: TBD | K37: USA | M37: EPM_Practice_USA_-_Managed_Services | N37: Application Support Lead - FCC | O37: =_xlfn.CONCAT(M37,N37) -> EPM_Practice_USA_-_Managed_ServicesApplication Support Lead - FCC | P37: 200 | Q37: 130 | R37: USA | T37: 46752 | U37: 176 | W37: EPM_Practice_USA_-_Managed_ServicesApplication Support Lead - PLN
A38: CDM Smith | B38: Oracle Data Integrator | F38: Sr. Application Lead - FCC | G38: EPM_Practice_USA_-_Managed_Services | H38: Sr. Application Support Lead | I38: =_xlfn.CONCAT(G38,H38) -> EPM_Practice_USA_-_Managed_ServicesSr. Application Support Lead | J38: TBD | K38: USA | M38: EPM_Practice_USA_-_Managed_Services | N38: Sr. Application Lead - PLN | O38: =_xlfn.CONCAT(M38,N38) -> EPM_Practice_USA_-_Managed_ServicesSr. Application Lead - PLN | P38: 290 | Q38: 160 | R38: USA | T38: 46783 | U38: 168 | W38: EPM_Practice_USA_-_Managed_ServicesSr. Application Support Lead
A39: Central Insurance | B39: Oracle EBS | F39: Sr. Application Lead - PLN | G39: EPM_Practice_USA_-_Managed_Services | H39: Sr. Integration Lead | I39: =_xlfn.CONCAT(G39,H39) -> EPM_Practice_USA_-_Managed_ServicesSr. Integration Lead | J39: TBD | K39: USA | M39: EPM_Practice_USA_-_Managed_Services | N39: Sr. Application Support Lead - FCC | O39: =_xlfn.CONCAT(M39,N39) -> EPM_Practice_USA_-_Managed_ServicesSr. Application Support Lead - FCC | P39: 210 | Q39: 140 | R39: USA | T39: 46812 | U39: 160 | W39: EPM_Practice_USA_-_Managed_ServicesSr. Integration Lead
A40: Centric3 | B40: Oracle ERP Cloud | F40: Sr. Application Support Lead | G40: EPM_Practice_USA_-_Managed_Services | H40: Sr. Reporting Lead | I40: =_xlfn.CONCAT(G40,H40) -> EPM_Practice_USA_-_Managed_ServicesSr. Reporting Lead | J40: TBD | K40: USA | M40: EPM_Practice_USA_-_Managed_Services | N40: Sr. Application Lead - FCC | O40: =_xlfn.CONCAT(M40,N40) -> EPM_Practice_USA_-_Managed_ServicesSr. Application Lead - FCC | P40: 290 | Q40: 160 | R40: USA | T40: 46843 | U40: 184 | W40: EPM_Practice_USA_-_Managed_ServicesSr. Reporting Lead
A41: Century Aluminum | B41: Oracle HCM | F41: Sr. Application Support Lead - FCC | G41: EPM_Practice_USA_-_Managed_Services | H41: Sr. Application Developer | I41: =_xlfn.CONCAT(G41,H41) -> EPM_Practice_USA_-_Managed_ServicesSr. Application Developer | J41: TBD | K41: USA | M41: EPM_Practice_USA_-_Managed_Services | N41: Application Support Lead - PLN | O41: =_xlfn.CONCAT(M41,N41) -> EPM_Practice_USA_-_Managed_ServicesApplication Support Lead - PLN | P41: 200 | Q41: 130 | R41: USA | T41: 46873 | U41: 160 | W41: EPM_Practice_USA_-_Managed_ServicesSr. Application Developer
A42: Charter Communications(Trace3) | B42: Oracle JD Edwards | F42: Sr. Architect | G42: EPM_Practice_USA_-_Managed_Services | H42: Application Lead | I42: =_xlfn.CONCAT(G42,H42) -> EPM_Practice_USA_-_Managed_ServicesApplication Lead | J42: TBD | K42: USA | M42: EPM_Practice_USA_-_Managed_Services | N42: Sr. Application Support Lead | O42: =_xlfn.CONCAT(M42,N42) -> EPM_Practice_USA_-_Managed_ServicesSr. Application Support Lead | P42: 210 | Q42: 140 | R42: USA | T42: 46904 | U42: 176 | W42: EPM_Practice_USA_-_Managed_ServicesApplication Lead
A43: Cintas(Trace3) | B43: Oracle NetSuite ERP | F43: Sr. Change Manager | G43: EPM_Practice_USA_-_Managed_Services | H43: Integration Lead | I43: =_xlfn.CONCAT(G43,H43) -> EPM_Practice_USA_-_Managed_ServicesIntegration Lead | J43: TBD | K43: USA | M43: EPM_Practice_USA_-_Managed_Services | N43: Sr. Integration Lead | O43: =_xlfn.CONCAT(M43,N43) -> EPM_Practice_USA_-_Managed_ServicesSr. Integration Lead | P43: 290 | Q43: 160 | R43: USA | T43: 46934 | U43: 176 | W43: EPM_Practice_USA_-_Managed_ServicesIntegration Lead
A44: Clark County NV(Trace3) | B44: Org Effectiveness | F44: Sr. Data Engineer | G44: EPM_Practice_USA_-_Managed_Services | H44: Reporting Lead | I44: =_xlfn.CONCAT(G44,H44) -> EPM_Practice_USA_-_Managed_ServicesReporting Lead | J44: TBD | K44: USA | M44: EPM_Practice_USA_-_Managed_Services | N44: Sr. Reporting Lead | O44: =_xlfn.CONCAT(M44,N44) -> EPM_Practice_USA_-_Managed_ServicesSr. Reporting Lead | P44: 290 | Q44: 160 | R44: USA | T44: 46965 | U44: 160 | W44: EPM_Practice_USA_-_Managed_ServicesReporting Lead
A45: CoBank(Oracle) | B45: Partner | F45: Sr. DBA | G45: EPM_Practice_USA_-_Managed_Services | H45: Solution Architect | I45: =_xlfn.CONCAT(G45,H45) -> EPM_Practice_USA_-_Managed_ServicesSolution Architect | J45: TBD | K45: USA | M45: EPM_Practice_USA_-_Managed_Services | N45: Sr. Application Developer | O45: =_xlfn.CONCAT(M45,N45) -> EPM_Practice_USA_-_Managed_ServicesSr. Application Developer | P45: 240 | Q45: 135 | R45: USA | T45: 46996 | U45: 184 | W45: EPM_Practice_USA_-_Managed_ServicesSolution Architect
A46: Comcast(Fincons) | B46: PCMCS | F46: Sr. Developer | G46: EPM_Practice_USA_-_Managed_Services | H46: Sr. Solution Architect | I46: =_xlfn.CONCAT(G46,H46) -> EPM_Practice_USA_-_Managed_ServicesSr. Solution Architect | J46: TBD | K46: USA | M46: EPM_Practice_USA_-_Managed_Services | N46: Application Lead | O46: =_xlfn.CONCAT(M46,N46) -> EPM_Practice_USA_-_Managed_ServicesApplication Lead | P46: 265 | Q46: 145 | R46: USA | T46: 47026 | U46: 160 | W46: EPM_Practice_USA_-_Managed_ServicesSr. Solution Architect
A47: Cooper Standard | B47: PeopleSoft | F47: Sr. Functional Lead | G47: EPM_Practice_USA_-_Managed_Services | H47: Principal Architect | I47: =_xlfn.CONCAT(G47,H47) -> EPM_Practice_USA_-_Managed_ServicesPrincipal Architect | J47: TBD | K47: USA | M47: EPM_Practice_USA_-_Managed_Services | N47: Integration Lead | O47: =_xlfn.CONCAT(M47,N47) -> EPM_Practice_USA_-_Managed_ServicesIntegration Lead | P47: 265 | Q47: 145 | R47: USA | T47: 47057 | U47: 176 | W47: EPM_Practice_USA_-_Managed_ServicesPrincipal Architect
A48: CooperVision | B48: Planning | F48: Sr. Integration Developer | G48: EPM_Practice_USA_-_Planning | H48: Sr. Solution Architect | I48: =_xlfn.CONCAT(G48,H48) -> EPM_Practice_USA_-_PlanningSr. Solution Architect | J48: TBD | K48: USA | M48: EPM_Practice_USA_-_Managed_Services | N48: Reporting Lead | O48: =_xlfn.CONCAT(M48,N48) -> EPM_Practice_USA_-_Managed_ServicesReporting Lead | P48: 265 | Q48: 145 | R48: USA | T48: 47087 | U48: 160 | W48: EPM_Practice_USA_-_PlanningSr. Solution Architect
... A51: Cretex Companies | B51: Power BI | F51: Sr. Program Manager | G51: EPM_Practice_USA_-_Planning | H51: Integration Lead | I51: =_xlfn.CONCAT(G51,H51) -> EPM_Practice_USA_-_PlanningIntegration Lead | J51: TBD | K51: USA | M51: EPM_Practice_USA_-_Managed_Services | N51: Principal Architect | O51: =_xlfn.CONCAT(M51,N51) -> EPM_Practice_USA_-_Managed_ServicesPrincipal Architect | P51: 450 | Q51: 235 | R51: USA | T51: 47177 | U51: 152 | W51: EPM_Practice_USA_-_PlanningIntegration Lead
A52: Cummins | B52: PS EPM Cloud Suite | F52: Sr. Project Manager | G52: EPM_Practice_USA_-_Planning | H52: Application Support Lead - EPB | I52: =_xlfn.CONCAT(G52,H52) -> EPM_Practice_USA_-_PlanningApplication Support Lead - EPB | J52: TBD | K52: USA | O52: =_xlfn.CONCAT(M52,N52) | T52: 47208 | U52: 176 | W52: EPM_Practice_USA_-_PlanningApplication Support Lead - EPB
A53: Dana | B53: PS IT | F53: Sr. QA Tester - Automation | G53: EPM_Practice_USA_-_Planning | H53: Sr. Application Support Lead - PLN | I53: =_xlfn.CONCAT(G53,H53) -> EPM_Practice_USA_-_PlanningSr. Application Support Lead - PLN | J53: TBD | K53: USA | M53: EPM_Practice_USA_-_Planning | N53: Sr. Solution Architect | O53: =_xlfn.CONCAT(M53,N53) -> EPM_Practice_USA_-_PlanningSr. Solution Architect | P53: 390 | Q53: 195 | R53: USA | T53: 47238 | U53: 168 | W53: EPM_Practice_USA_-_PlanningSr. Application Support Lead - PLN
A54: Databricks(Transatlantix) | B54: PS Oracle ERP Cloud | F54: Sr. QA Tester - Manual | G54: EPM_Practice_USA_-_Planning | H54: Sr. Application Developer | I54: =_xlfn.CONCAT(G54,H54) -> EPM_Practice_USA_-_PlanningSr. Application Developer | J54: TBD | K54: USA | M54: EPM_Practice_USA_-_Planning | N54: Application Developer | O54: =_xlfn.CONCAT(M54,N54) -> EPM_Practice_USA_-_PlanningApplication Developer | P54: 215 | Q54: 125 | R54: USA | T54: 47269 | U54: 176 | W54: EPM_Practice_USA_-_PlanningSr. Application Developer
A55: Daymon Worldwide | B55: QA | F55: Sr. Software Engineer | G55: EPM_Practice_USA_-_Planning | H55: Application Developer - PLN | I55: =_xlfn.CONCAT(G55,H55) -> EPM_Practice_USA_-_PlanningApplication Developer - PLN | J55: TBD | K55: USA | M55: EPM_Practice_USA_-_Planning | N55: Principal Architect | O55: =_xlfn.CONCAT(M55,N55) -> EPM_Practice_USA_-_PlanningPrincipal Architect | P55: 450 | Q55: 235 | R55: USA | T55: 47299 | U55: 168 | W55: EPM_Practice_USA_-_PlanningApplication Developer - PLN
A56: Delphi Automotive | B56: RPA | F56: Sr. Solution Architect | G56: EPM_Practice_USA_-_Planning | H56: Sr. Application Developer - PLN | I56: =_xlfn.CONCAT(G56,H56) -> EPM_Practice_USA_-_PlanningSr. Application Developer - PLN | J56: TBD | K56: USA | M56: EPM_Practice_USA_-_Planning | N56: Integration Lead | O56: =_xlfn.CONCAT(M56,N56) -> EPM_Practice_USA_-_PlanningIntegration Lead | P56: 265 | Q56: 145 | R56: USA | T56: 47330 | U56: 168 | W56: EPM_Practice_USA_-_PlanningSr. Application Developer - PLN
A57: Delphi Automotive(American Partners) | B57: Salesforce | F57: Sr. Solution Architect - FCC | G57: EPM_Practice_USA_-_Planning | H57: Application Lead - PLN | I57: =_xlfn.CONCAT(G57,H57) -> EPM_Practice_USA_-_PlanningApplication Lead - PLN | J57: TBD | K57: USA | M57: EPM_Practice_USA_-_Planning | N57: Application Support Lead - EPB | O57: =_xlfn.CONCAT(M57,N57) -> EPM_Practice_USA_-_PlanningApplication Support Lead - EPB | P57: 200 | Q57: 130 | R57: USA | T57: 47361 | U57: 184 | W57: EPM_Practice_USA_-_PlanningApplication Lead - PLN
A58: Delphi Technologies | B58: SAP BPC | F58: Sr. Solution Architect - PLN | G58: EPM_Practice_USA_-_Planning | H58: Sr. Application Lead | I58: =_xlfn.CONCAT(G58,H58) -> EPM_Practice_USA_-_PlanningSr. Application Lead | J58: TBD | K58: USA | M58: EPM_Practice_USA_-_Planning | N58: Sr. Application Support Lead - PLN | O58: =_xlfn.CONCAT(M58,N58) -> EPM_Practice_USA_-_PlanningSr. Application Support Lead - PLN | P58: 210 | Q58: 140 | R58: USA | T58: 47391 | U58: 152 | W58: EPM_Practice_USA_-_PlanningSr. Application Lead
A59: Delphi Technologies(Secure24) | B59: SAP ERP | F59: Sr. Technical Lead | G59: EPM_Practice_USA_-_Planning | H59: Solution Architect | I59: =_xlfn.CONCAT(G59,H59) -> EPM_Practice_USA_-_PlanningSolution Architect | J59: TBD | K59: USA | M59: EPM_Practice_USA_-_Planning | N59: Sr. Application Developer | O59: =_xlfn.CONCAT(M59,N59) -> EPM_Practice_USA_-_PlanningSr. Application Developer | P59: 240 | Q59: 135 | R59: USA | T59: 47422 | U59: 184 | W59: EPM_Practice_USA_-_PlanningSolution Architect
A60: Delta Air Lines | B60: SAP S4 HANA | F60: Support Engineer | G60: EPM_Practice_USA_-_Planning | H60: Solution Architect - PLN | I60: =_xlfn.CONCAT(G60,H60) -> EPM_Practice_USA_-_PlanningSolution Architect - PLN | J60: TBD | K60: USA | M60: EPM_Practice_USA_-_Planning | N60: Application Developer - PLN | O60: =_xlfn.CONCAT(M60,N60) -> EPM_Practice_USA_-_PlanningApplication Developer - PLN | P60: 215 | Q60: 125 | R60: USA | T60: 47452 | U60: 160 | W60: EPM_Practice_USA_-_PlanningSolution Architect - PLN
A61: Duck Creek Technologies | B61: System Administration | F61: Technical Lead | G61: EPM_Practice_Australia | H61: Sr. Application Lead | I61: =_xlfn.CONCAT(G61,H61) -> EPM_Practice_AustraliaSr. Application Lead | J61: TBD | K61: Australia | M61: EPM_Practice_USA_-_Planning | N61: Sr. Application Developer - PLN | O61: =_xlfn.CONCAT(M61,N61) -> EPM_Practice_USA_-_PlanningSr. Application Developer - PLN | P61: 240 | Q61: 135 | R61: USA | T61: 47483 | U61: 160 | W61: EPM_Practice_AustraliaSr. Application Lead
A62: Dun&Bradstreet(IVA Technos) | B62: TS Business Analyst | F62: Techno-Functional Finance Lead | G62: EPM_Practice_Canada_Consolidation | H62: Application Developer | I62: =_xlfn.CONCAT(G62,H62) -> EPM_Practice_Canada_ConsolidationApplication Developer | J62: TBD | K62: Canada | M62: EPM_Practice_USA_-_Planning | N62: Application Lead - PLN | O62: =_xlfn.CONCAT(M62,N62) -> EPM_Practice_USA_-_PlanningApplication Lead - PLN | P62: 265 | Q62: 145 | R62: USA | W62: EPM_Practice_Canada_ConsolidationApplication Developer
A63: EchoStar(Data Piper) | B63: TS IP | F63: Contractor 1 | G63: EPM_Practice_India | H63: Project Manager | I63: =_xlfn.CONCAT(G63,H63) -> EPM_Practice_IndiaProject Manager | J63: TBD | K63: India | M63: EPM_Practice_USA_-_Planning | N63: Sr. Application Lead | O63: =_xlfn.CONCAT(M63,N63) -> EPM_Practice_USA_-_PlanningSr. Application Lead | P63: 290 | Q63: 160 | R63: USA | W63: EPM_Practice_IndiaProject Manager
A64: Edwards Lifesciences | B64: Workday | F64: Contractor 2 | G64: EPM_Practice_India | H64: Sr. Project Manager | I64: =_xlfn.CONCAT(G64,H64) -> EPM_Practice_IndiaSr. Project Manager | J64: TBD | K64: India | M64: EPM_Practice_USA_-_Planning | N64: Solution Architect | O64: =_xlfn.CONCAT(M64,N64) -> EPM_Practice_USA_-_PlanningSolution Architect | P64: 365 | Q64: 185 | R64: USA | W64: EPM_Practice_IndiaSr. Project Manager
A65: Equinox Gold | F65: Contractor 3 | G65: EPM_Practice_India_-_Consolidation | H65: Software Engineer | I65: =_xlfn.CONCAT(G65,H65) -> EPM_Practice_India_-_ConsolidationSoftware Engineer | J65: TBD | K65: India | M65: EPM_Practice_USA_-_Planning | N65: Solution Architect - PLN | O65: =_xlfn.CONCAT(M65,N65) -> EPM_Practice_USA_-_PlanningSolution Architect - PLN | P65: 365 | Q65: 185 | R65: USA | W65: EPM_Practice_India_-_ConsolidationSoftware Engineer
A66: Experian(Xoogify) | F66: Contractor 4 | G66: EPM_Practice_India_-_Consolidation | H66: Sr. Application Lead | I66: =_xlfn.CONCAT(G66,H66) -> EPM_Practice_India_-_ConsolidationSr. Application Lead | J66: TBD | K66: India | O66: =_xlfn.CONCAT(M66,N66) | W66: EPM_Practice_India_-_ConsolidationSr. Application Lead
A67: Express Flooring | F67: Contractor 5 | G67: EPM_Practice_India_-_Consolidation | H67: Sr. Software Engineer | I67: =_xlfn.CONCAT(G67,H67) -> EPM_Practice_India_-_ConsolidationSr. Software Engineer | J67: TBD | K67: India | M67: EPM_Practice_Australia | N67: Sr. Application Lead | O67: =_xlfn.CONCAT(M67,N67) -> EPM_Practice_AustraliaSr. Application Lead | P67: 290 | Q67: 100 | R67: Australia | W67: EPM_Practice_India_-_ConsolidationSr. Software Engineer
A68: FDC | F68: DART | G68: EPM_Practice_India_-_Consolidation | H68: Application Support Lead - FCC | I68: =_xlfn.CONCAT(G68,H68) -> EPM_Practice_India_-_ConsolidationApplication Support Lead - FCC | J68: TBD | K68: India | W68: EPM_Practice_India_-_ConsolidationApplication Support Lead - FCC
A69: Fiserv | F69: EPM Cloud Assurance | G69: EPM_Practice_India_-_Consolidation | H69: Sr. Application Support Lead - FCC | I69: =_xlfn.CONCAT(G69,H69) -> EPM_Practice_India_-_ConsolidationSr. Application Support Lead - FCC | J69: TBD | K69: India | M69: EPM_Practice_Canada_Consolidation | N69: Application Developer | O69: =_xlfn.CONCAT(M69,N69) -> EPM_Practice_Canada_ConsolidationApplication Developer | P69: 215 | Q69: 125 | R69: Canada | W69: EPM_Practice_India_-_ConsolidationSr. Application Support Lead - FCC
A70: Fiserv India | G70: EPM_Practice_India_-_Consolidation | H70: Application Developer - FCC | I70: =_xlfn.CONCAT(G70,H70) -> EPM_Practice_India_-_ConsolidationApplication Developer - FCC | J70: TBD | K70: India | W70: EPM_Practice_India_-_ConsolidationApplication Developer - FCC
A71: Ford | G71: EPM_Practice_India_-_Consolidation | H71: Sr. Application Developer - FCC | I71: =_xlfn.CONCAT(G71,H71) -> EPM_Practice_India_-_ConsolidationSr. Application Developer - FCC | J71: TBD | K71: India | M71: EPM_Practice_India | N71: Project Manager | O71: =_xlfn.CONCAT(M71,N71) -> EPM_Practice_IndiaProject Manager | P71: 45 | Q71: 22 | R71: India | W71: EPM_Practice_India_-_ConsolidationSr. Application Developer - FCC
A72: Ford(Insight) | G72: EPM_Practice_India_-_Consolidation | H72: Application Lead - FCC | I72: =_xlfn.CONCAT(G72,H72) -> EPM_Practice_India_-_ConsolidationApplication Lead - FCC | J72: TBD | K72: India | M72: EPM_Practice_India | N72: Sr. Project Manager | O72: =_xlfn.CONCAT(M72,N72) -> EPM_Practice_IndiaSr. Project Manager | P72: 70 | Q72: 35 | R72: India | W72: EPM_Practice_India_-_ConsolidationApplication Lead - FCC
A73: Gardner Denver(PARC) | G73: EPM_Practice_India_-_Consolidation | H73: Sr. Application Lead - FCC | I73: =_xlfn.CONCAT(G73,H73) -> EPM_Practice_India_-_ConsolidationSr. Application Lead - FCC | J73: TBD | K73: India | W73: EPM_Practice_India_-_ConsolidationSr. Application Lead - FCC
A74: Gentex | G74: EPM_Practice_India_-_Consolidation | H74: Solution Architect - FCC | I74: =_xlfn.CONCAT(G74,H74) -> EPM_Practice_India_-_ConsolidationSolution Architect - FCC | J74: TBD | K74: India | M74: EPM_Practice_India_-_Consolidation | N74: Software Engineer | O74: =_xlfn.CONCAT(M74,N74) -> EPM_Practice_India_-_ConsolidationSoftware Engineer | P74: 35 | Q74: 11 | R74: India | W74: EPM_Practice_India_-_ConsolidationSolution Architect - FCC
A75: Gilead Sciences(ZS Associates) | G75: EPM_Practice_India_-_Consolidation | H75: Sr. Solution Architect - FCC | I75: =_xlfn.CONCAT(G75,H75) -> EPM_Practice_India_-_ConsolidationSr. Solution Architect - FCC | J75: TBD | K75: India | M75: EPM_Practice_India_-_Consolidation | N75: Sr. Application Lead | O75: =_xlfn.CONCAT(M75,N75) -> EPM_Practice_India_-_ConsolidationSr. Application Lead | P75: 85 | Q75: 27 | R75: India | W75: EPM_Practice_India_-_ConsolidationSr. Solution Architect - FCC
A76: Global Partners | G76: EPM_Practice_India_-_Integration | H76: Sr. Software Engineer | I76: =_xlfn.CONCAT(G76,H76) -> EPM_Practice_India_-_IntegrationSr. Software Engineer | J76: TBD | K76: India | M76: EPM_Practice_India_-_Consolidation | N76: Sr. Software Engineer | O76: =_xlfn.CONCAT(M76,N76) -> EPM_Practice_India_-_ConsolidationSr. Software Engineer | P76: 45 | Q76: 13 | R76: India | W76: EPM_Practice_India_-_IntegrationSr. Software Engineer
A77: Global Partners(Oracle) | G77: EPM_Practice_India_-_Integration | H77: Software Engineer | I77: =_xlfn.CONCAT(G77,H77) -> EPM_Practice_India_-_IntegrationSoftware Engineer | J77: TBD | K77: India | M77: EPM_Practice_India_-_Consolidation | N77: Application Support Lead - FCC | O77: =_xlfn.CONCAT(M77,N77) -> EPM_Practice_India_-_ConsolidationApplication Support Lead - FCC | P77: 40 | Q77: 17 | R77: India | W77: EPM_Practice_India_-_IntegrationSoftware Engineer
A78: GM Financial | G78: EPM_Practice_India_-_Integration | H78: Integration Lead | I78: =_xlfn.CONCAT(G78,H78) -> EPM_Practice_India_-_IntegrationIntegration Lead | J78: TBD | K78: India | M78: EPM_Practice_India_-_Consolidation | N78: Sr. Application Support Lead - FCC | O78: =_xlfn.CONCAT(M78,N78) -> EPM_Practice_India_-_ConsolidationSr. Application Support Lead - FCC | P78: 50 | Q78: 22 | R78: India | W78: EPM_Practice_India_-_IntegrationIntegration Lead
A79: GM Financial(Oracle India) | G79: EPM_Practice_India_-_Integration | H79: Sr. Integration Developer | I79: =_xlfn.CONCAT(G79,H79) -> EPM_Practice_India_-_IntegrationSr. Integration Developer | J79: TBD | K79: India | M79: EPM_Practice_India_-_Consolidation | N79: Application Developer - FCC | O79: =_xlfn.CONCAT(M79,N79) -> EPM_Practice_India_-_ConsolidationApplication Developer - FCC | P79: 55 | Q79: 15 | R79: India | W79: EPM_Practice_India_-_IntegrationSr. Integration Developer
A80: GM Financial(Oracle) | G80: EPM_Practice_India_-_Integration | H80: Sr. Integration Lead | I80: =_xlfn.CONCAT(G80,H80) -> EPM_Practice_India_-_IntegrationSr. Integration Lead | J80: TBD | K80: India | M80: EPM_Practice_India_-_Consolidation | N80: Sr. Application Developer - FCC | O80: =_xlfn.CONCAT(M80,N80) -> EPM_Practice_India_-_ConsolidationSr. Application Developer - FCC | P80: 65 | Q80: 17 | R80: India | W80: EPM_Practice_India_-_IntegrationSr. Integration Lead
A81: GM(Technosoft) | G81: EPM_Practice_India_-_Integration | H81: Application Developer - DI | I81: =_xlfn.CONCAT(G81,H81) -> EPM_Practice_India_-_IntegrationApplication Developer - DI | J81: TBD | K81: India | M81: EPM_Practice_India_-_Consolidation | N81: Application Lead - FCC | O81: =_xlfn.CONCAT(M81,N81) -> EPM_Practice_India_-_ConsolidationApplication Lead - FCC | P81: 75 | Q81: 22 | R81: India | W81: EPM_Practice_India_-_IntegrationApplication Developer - DI
A82: Google(Xoogify) | G82: EPM_Practice_India_-_Integration | H82: Application Lead - DI | I82: =_xlfn.CONCAT(G82,H82) -> EPM_Practice_India_-_IntegrationApplication Lead - DI | J82: TBD | K82: India | M82: EPM_Practice_India_-_Consolidation | N82: Sr. Application Lead - FCC | O82: =_xlfn.CONCAT(M82,N82) -> EPM_Practice_India_-_ConsolidationSr. Application Lead - FCC | P82: 85 | Q82: 27 | R82: India | W82: EPM_Practice_India_-_IntegrationApplication Lead - DI
A83: Graham Packaging(SC&H) | G83: EPM_Practice_India_-_Integration | H83: Sr. Application Developer - DI | I83: =_xlfn.CONCAT(G83,H83) -> EPM_Practice_India_-_IntegrationSr. Application Developer - DI | J83: TBD | K83: India | M83: EPM_Practice_India_-_Consolidation | N83: Solution Architect - FCC | O83: =_xlfn.CONCAT(M83,N83) -> EPM_Practice_India_-_ConsolidationSolution Architect - FCC | P83: 95 | Q83: 32 | R83: India | W83: EPM_Practice_India_-_IntegrationSr. Application Developer - DI
A84: Grange Insurance | G84: EPM_Practice_India_-_Integration | H84: Solution Architect - DI | I84: =_xlfn.CONCAT(G84,H84) -> EPM_Practice_India_-_IntegrationSolution Architect - DI | J84: TBD | K84: India | M84: EPM_Practice_India_-_Consolidation | N84: Sr. Solution Architect - FCC | O84: =_xlfn.CONCAT(M84,N84) -> EPM_Practice_India_-_ConsolidationSr. Solution Architect - FCC | P84: 150 | Q84: 45 | R84: India | W84: EPM_Practice_India_-_IntegrationSolution Architect - DI
A85: Grede Holdings | G85: EPM_Practice_India_-_Planning | H85: Sr. Solution Architect | I85: =_xlfn.CONCAT(G85,H85) -> EPM_Practice_India_-_PlanningSr. Solution Architect | J85: TBD | K85: India | W85: EPM_Practice_India_-_PlanningSr. Solution Architect
A86: GREIF(Secure24) | G86: EPM_Practice_India_-_Planning | H86: Software Engineer | I86: =_xlfn.CONCAT(G86,H86) -> EPM_Practice_India_-_PlanningSoftware Engineer | J86: TBD | K86: India | M86: EPM_Practice_India_-_Integration | N86: Sr. Software Engineer | O86: =_xlfn.CONCAT(M86,N86) -> EPM_Practice_India_-_IntegrationSr. Software Engineer | P86: 45 | Q86: 13 | R86: India | W86: EPM_Practice_India_-_PlanningSoftware Engineer
A87: GTS Direct | G87: EPM_Practice_India_-_Planning | H87: Sr. Software Engineer | I87: =_xlfn.CONCAT(G87,H87) -> EPM_Practice_India_-_PlanningSr. Software Engineer | J87: TBD | K87: India | M87: EPM_Practice_India_-_Integration | N87: Software Engineer | O87: =_xlfn.CONCAT(M87,N87) -> EPM_Practice_India_-_IntegrationSoftware Engineer | P87: 35 | Q87: 11 | R87: India | W87: EPM_Practice_India_-_PlanningSr. Software Engineer
A88: Guthrie(Oracle) | G88: EPM_Practice_India_-_Planning | H88: Sr. Application Developer | I88: =_xlfn.CONCAT(G88,H88) -> EPM_Practice_India_-_PlanningSr. Application Developer | J88: TBD | K88: India | M88: EPM_Practice_India_-_Integration | N88: Integration Lead | O88: =_xlfn.CONCAT(M88,N88) -> EPM_Practice_India_-_IntegrationIntegration Lead | P88: 75 | Q88: 22 | R88: India | W88: EPM_Practice_India_-_PlanningSr. Application Developer
A89: Harris Corporation | G89: EPM_Practice_India_-_Planning | H89: Application Support Lead - PLN | I89: =_xlfn.CONCAT(G89,H89) -> EPM_Practice_India_-_PlanningApplication Support Lead - PLN | J89: TBD | K89: India | M89: EPM_Practice_India_-_Integration | N89: Sr. Integration Developer | O89: =_xlfn.CONCAT(M89,N89) -> EPM_Practice_India_-_IntegrationSr. Integration Developer | P89: 65 | Q89: 17 | R89: India | W89: EPM_Practice_India_-_PlanningApplication Support Lead - PLN
A90: HealthEdge | G90: EPM_Practice_India_-_Planning | H90: Sr. Application Support Lead - PLN | I90: =_xlfn.CONCAT(G90,H90) -> EPM_Practice_India_-_PlanningSr. Application Support Lead - PLN | J90: TBD | K90: India | M90: EPM_Practice_India_-_Integration | N90: Sr. Integration Lead | O90: =_xlfn.CONCAT(M90,N90) -> EPM_Practice_India_-_IntegrationSr. Integration Lead | P90: 95 | Q90: 30 | R90: India | W90: EPM_Practice_India_-_PlanningSr. Application Support Lead - PLN
A91: ICF(SC&H) | G91: EPM_Practice_India_-_Planning | H91: Application Developer - PLN | I91: =_xlfn.CONCAT(G91,H91) -> EPM_Practice_India_-_PlanningApplication Developer - PLN | J91: TBD | K91: India | M91: EPM_Practice_India_-_Integration | N91: Application Developer - DI | O91: =_xlfn.CONCAT(M91,N91) -> EPM_Practice_India_-_IntegrationApplication Developer - DI | P91: 55 | Q91: 15 | R91: India | W91: EPM_Practice_India_-_PlanningApplication Developer - PLN
A92: IEEE | G92: EPM_Practice_India_-_Planning | H92: Sr. Application Developer - PLN | I92: =_xlfn.CONCAT(G92,H92) -> EPM_Practice_India_-_PlanningSr. Application Developer - PLN | J92: TBD | K92: India | M92: EPM_Practice_India_-_Integration | N92: Application Lead - DI | O92: =_xlfn.CONCAT(M92,N92) -> EPM_Practice_India_-_IntegrationApplication Lead - DI | P92: 75 | Q92: 22 | R92: India | W92: EPM_Practice_India_-_PlanningSr. Application Developer - PLN
A93: Illinois Tool Works | G93: EPM_Practice_India_-_Planning | H93: Application Lead - PLN | I93: =_xlfn.CONCAT(G93,H93) -> EPM_Practice_India_-_PlanningApplication Lead - PLN | J93: TBD | K93: India | M93: EPM_Practice_India_-_Integration | N93: Sr. Application Developer - DI | O93: =_xlfn.CONCAT(M93,N93) -> EPM_Practice_India_-_IntegrationSr. Application Developer - DI | P93: 65 | Q93: 17 | R93: India | W93: EPM_Practice_India_-_PlanningApplication Lead - PLN
A94: Ingersoll Rand(PARC) | G94: EPM_Practice_India_-_Planning | H94: Sr. Application Lead - PLN | I94: =_xlfn.CONCAT(G94,H94) -> EPM_Practice_India_-_PlanningSr. Application Lead - PLN | J94: TBD | K94: India | M94: EPM_Practice_India_-_Integration | N94: Solution Architect - DI | O94: =_xlfn.CONCAT(M94,N94) -> EPM_Practice_India_-_IntegrationSolution Architect - DI | P94: 95 | Q94: 32 | R94: India | W94: EPM_Practice_India_-_PlanningSr. Application Lead - PLN
A95: Ingram Micro | G95: EPM_Practice_India_-_Planning | H95: Solution Architect - PLN | I95: =_xlfn.CONCAT(G95,H95) -> EPM_Practice_India_-_PlanningSolution Architect - PLN | J95: TBD | K95: India | W95: EPM_Practice_India_-_PlanningSolution Architect - PLN
A96: IVA Technos | G96: EPM_Practice_India_-_Planning | H96: Sr. Solution Architect - PLN | I96: =_xlfn.CONCAT(G96,H96) -> EPM_Practice_India_-_PlanningSr. Solution Architect - PLN | J96: TBD | K96: India | M96: EPM_Practice_India_-_Planning | N96: Sr. Solution Architect | O96: =_xlfn.CONCAT(M96,N96) -> EPM_Practice_India_-_PlanningSr. Solution Architect | P96: 150 | Q96: 45 | R96: India | W96: EPM_Practice_India_-_PlanningSr. Solution Architect - PLN
A97: JM Huber | G97: ERP_Practice_USA | H97: Project Coordinator | I97: =_xlfn.CONCAT(G97,H97) -> ERP_Practice_USAProject Coordinator | J97: TBD | K97: USA | M97: EPM_Practice_India_-_Planning | N97: Software Engineer | O97: =_xlfn.CONCAT(M97,N97) -> EPM_Practice_India_-_PlanningSoftware Engineer | P97: 35 | Q97: 11 | R97: India | W97: ERP_Practice_USAProject Coordinator
A98: Joyson Safety Systems | G98: ERP_Practice_USA | H98: Project Manager | I98: =_xlfn.CONCAT(G98,H98) -> ERP_Practice_USAProject Manager | J98: TBD | K98: USA | M98: EPM_Practice_India_-_Planning | N98: Sr. Software Engineer | O98: =_xlfn.CONCAT(M98,N98) -> EPM_Practice_India_-_PlanningSr. Software Engineer | P98: 45 | Q98: 13 | R98: India | W98: ERP_Practice_USAProject Manager
A99: JTEKT | G99: ERP_Practice_USA | H99: Sr. Project Manager | I99: =_xlfn.CONCAT(G99,H99) -> ERP_Practice_USASr. Project Manager | J99: TBD | K99: USA | M99: EPM_Practice_India_-_Planning | N99: Sr. Application Developer | O99: =_xlfn.CONCAT(M99,N99) -> EPM_Practice_India_-_PlanningSr. Application Developer | P99: 65 | Q99: 17 | R99: India | W99: ERP_Practice_USASr. Project Manager
A100: Kemper Insurance(Lorven Technologies) | G100: ERP_Practice_USA | H100: Application Support Lead | I100: =_xlfn.CONCAT(G100,H100) -> ERP_Practice_USAApplication Support Lead | J100: TBD | K100: USA | M100: EPM_Practice_India_-_Planning | N100: Application Support Lead - PLN | O100: =_xlfn.CONCAT(M100,N100) -> EPM_Practice_India_-_PlanningApplication Support Lead - PLN | P100: 40 | Q100: 17 | R100: India | W100: ERP_Practice_USAApplication Support Lead
A101: Kohler | G101: ERP_Practice_USA | H101: Sr. Application Support Lead | I101: =_xlfn.CONCAT(G101,H101) -> ERP_Practice_USASr. Application Support Lead | J101: TBD | K101: USA | M101: EPM_Practice_India_-_Planning | N101: Sr. Application Support Lead - PLN | O101: =_xlfn.CONCAT(M101,N101) -> EPM_Practice_India_-_PlanningSr. Application Support Lead - PLN | P101: 50 | Q101: 22 | R101: India | W101: ERP_Practice_USASr. Application Support Lead
A102: KORE Wireless(Trace3) | G102: ERP_Practice_USA | H102: Application Developer | I102: =_xlfn.CONCAT(G102,H102) -> ERP_Practice_USAApplication Developer | J102: TBD | K102: USA | M102: EPM_Practice_India_-_Planning | N102: Application Developer - PLN | O102: =_xlfn.CONCAT(M102,N102) -> EPM_Practice_India_-_PlanningApplication Developer - PLN | P102: 55 | Q102: 15 | R102: India | W102: ERP_Practice_USAApplication Developer
...

Sheet Update Resource Instructions
B1: Instructions to update the Picklist Tab with current data from Certina
A2: 1 | B2: Run the Resource Contact List report in Certinia (link is at the top of the Certinia Resource List tab)
A3: 2 | B3: Export to Excel (details only format)
A4: 3 | B4: Open the exported file, and remove any resources not assigned to a practice (Paul Coalescence)
A5: 4 | B5: If any resources are not assigned a Resource Role, validate with Amy; may need to be corrected
A6: 5 | B6: Copy/paste the list into the Certina Resource List tab columns A-F
A7: 6 | B7: Scroll to the bottom so you can either delete rows that were not copied over, or drag down the formulas in columns H-P if new list is longer
A8: 7 | B8: Adjust the formulas to include the correct number of rows for Columns S-W
A9: 8 | B9: If changed, copy/paste the Unique Practice List (Column U) to the Picklist tab Practice (Column E). Do not overwrite the Donyati Products or the IC/Subcontractor) | C9: Check to be sure that the Organizational Effectiveness Practice has practice in the name - Amy was to correct back in May.
A10: 9 | B10: If changed, copy/paste the Unique Roles List (Column W) to the Picklist tab Roles (Column F). Do not overwrite the Donyati Producst or the IC/Subcontractors.
A11: 10 | B11: To copy the updated list of resources, notice that the TBD data (do not copy over) on the Picklist tab is shaded grey. There is also a formula in the section below that is greyed out. To copy the resource info, first copy columns M and N to Picklist G and H, starting where the column is not shaded. Scroll to the bottom after copying as you may need to delete extra rows or drag formulas further down the list in column I if the new list is longer
A12: 11 | B12: Next, copy columns O and P to Picklist J and K, starting where the column is not shaded (below the TBD list). Scroll to the bottom after copying as you may need to delete extra rows.
A13: 12 | B13: Update the Updated Date to today's date (Cell F1).
B15: Instructions to update the Resource List Tab with current data from Certinia
A16: 1 | B16: Copy columns M-O on the Certinia Resource List Tab.
A17: 2 | B17: Paste to columns A-C on the Resource List Tab.
A18: 3 | B18: Be sure to remove any additional rows that were from the prior list.
A19: 4 | B19: Update the Updated Date to today's date (Cell D1).

Sheet Certinia Resource List
A1: Salesforce Report | B1: https://donyati.lightning.force.com/lightning/r/Report/00OQO000000NQeX2AW/view?queryScope=userFolders | F1: Updated 11/11/2025 | S1: UPDATE THE LAST # in formula with last Row # | U1: UPDATE THE LAST # in formula with last Row # | W1: UPDATE THE LAST # in formula with last Row #
A2: Account Name | B2: Practice | C2: First Name | D2: Last Name | E2: Resource Role | F2: Employment Type | H2: Change to EPM (CPM/EPM/Architecture/Functional) | J2: Add Hyphen to Practice Names | K2: Combo for Lookup | M2: Practice | N2: Role | O2: Name | P2: Location | S2: Practice and Role (UNIQUE) | U2: Practice (UNIQUE) | W2: Roles (UNIQUE)
A3: Donyati | B3: Cloud Practice USA | C3: Rodrigo | D3: Farinazo | E3: Program Manager | F3: Full Time USA - Billable | H3: =SUBSTITUTE(SUBSTITUTE(B3,"Organizational Effectiveness","EPM"),"CPM","EPM") -> Cloud Practice USA | J3: =SUBSTITUTE(TRIM(H3)," ","_") -> Cloud_Practice_USA | K3: =_xlfn.CONCAT(J3,E3) -> Cloud_Practice_USAProgram Manager | M3: =J3 -> Cloud_Practice_USA | N3: =E3 -> Program Manager | O3: =_xlfn.CONCAT(C3," ",D3) -> Rodrigo Farinazo | P3: {=INDEX(_xlfn.TEXTSPLIT(B3," "),3)} -> USA | S3: {=_xlfn.UNIQUE(K3:K279)} -> Cloud_Practice_USAProgram Manager | U3: {=_xlfn._xlws.SORT(_xlfn.UNIQUE(J3:J279))} | W3: {=_xlfn._xlws.SORT(_xlfn.UNIQUE(E3:E279))} -> Application Developer
A4: Donyati | B4: Cloud Practice USA | C4: Michael | D4: Stevens | E4: Program Manager | F4: Full Time USA - Billable | H4: =SUBSTITUTE(SUBSTITUTE(B4,"Organizational Effectiveness","EPM"),"CPM","EPM") -> Cloud Practice USA | J4: =SUBSTITUTE(TRIM(H4)," ","_") -> Cloud_Practice_USA | K4: =_xlfn.CONCAT(J4,E4) -> Cloud_Practice_USAProgram Manager | M4: =J4 -> Cloud_Practice_USA | N4: =E4 -> Program Manager | O4: =_xlfn.CONCAT(C4," ",D4) -> Michael Stevens | P4: {=INDEX(_xlfn.TEXTSPLIT(B4," "),3)} -> USA | S4: Cloud_Practice_USASr. Program Lead | U4: Cloud_Practice_USA | W4: Application Developer - DI
A5: Donyati | B5: Cloud Practice USA | C5: Michael | D5: J Meier | E5: Sr. Program Lead | F5: Full Time USA - Billable | H5: =SUBSTITUTE(SUBSTITUTE(B5,"Organizational Effectiveness","EPM"),"CPM","EPM") -> Cloud Practice USA | J5: =SUBSTITUTE(TRIM(H5)," ","_") -> Cloud_Practice_USA | K5: =_xlfn.CONCAT(J5,E5) -> Cloud_Practice_USASr. Program Lead | M5: =J5 -> Cloud_Practice_USA | N5: =E5 -> Sr. Program Lead | O5: =_xlfn.CONCAT(C5," ",D5) -> Michael J Meier | P5: {=INDEX(_xlfn.TEXTSPLIT(B5," "),3)} -> USA | S5: Cloud_Practice_USAProject Manager | U5: EPM_Practice_Canada_-_Consolidation | W5: Application Developer - FCC
A6: Donyati | B6: Cloud Practice USA | C6: Kerri | D6: Dittmar | E6: Project Manager | F6: Full Time USA - Billable | H6: =SUBSTITUTE(SUBSTITUTE(B6,"Organizational Effectiveness","EPM"),"CPM","EPM") -> Cloud Practice USA | J6: =SUBSTITUTE(TRIM(H6)," ","_") -> Cloud_Practice_USA | K6: =_xlfn.CONCAT(J6,E6) -> Cloud_Practice_USAProject Manager | M6: =J6 -> Cloud_Practice_USA | N6: =E6 -> Project Manager | O6: =_xlfn.CONCAT(C6," ",D6) -> Kerri Dittmar | P6: {=INDEX(_xlfn.TEXTSPLIT(B6," "),3)} -> USA | S6: Cloud_Practice_USAEngineer | U6: EPM_Practice_India | W6: Application Developer - PLN
A7: Donyati | B7: Cloud Practice USA | C7: Harrison | D7: Koons | E7: Engineer | F7: Full Time USA - Billable | H7: =SUBSTITUTE(SUBSTITUTE(B7,"Organizational Effectiveness","EPM"),"CPM","EPM") -> Cloud Practice USA | J7: =SUBSTITUTE(TRIM(H7)," ","_") -> Cloud_Practice_USA | K7: =_xlfn.CONCAT(J7,E7) -> Cloud_Practice_USAEngineer | M7: =J7 -> Cloud_Practice_USA | N7: =E7 -> Engineer | O7: =_xlfn.CONCAT(C7," ",D7) -> Harrison Koons | P7: {=INDEX(_xlfn.TEXTSPLIT(B7," "),3)} -> USA | S7: Cloud_Practice_USAProgram Lead | U7: EPM_Practice_India_-_Consolidation | W7: Application Lead
A8: Donyati | B8: Cloud Practice USA | C8: Evan | D8: C List | E8: Program Lead | F8: Full Time USA - Billable | H8: =SUBSTITUTE(SUBSTITUTE(B8,"Organizational Effectiveness","EPM"),"CPM","EPM") -> Cloud Practice USA | J8: =SUBSTITUTE(TRIM(H8)," ","_") -> Cloud_Practice_USA | K8: =_xlfn.CONCAT(J8,E8) -> Cloud_Practice_USAProgram Lead | M8: =J8 -> Cloud_Practice_USA | N8: =E8 -> Program Lead | O8: =_xlfn.CONCAT(C8," ",D8) -> Evan C List | P8: {=INDEX(_xlfn.TEXTSPLIT(B8," "),3)} -> USA | S8: Cloud_Practice_USAArchitect | U8: EPM_Practice_India_-_Integration | W8: Application Lead - FCC
A9: Donyati | B9: Cloud Practice USA | C9: Christina | D9: Allan | E9: Architect | F9: Full Time USA - Billable | H9: =SUBSTITUTE(SUBSTITUTE(B9,"Organizational Effectiveness","EPM"),"CPM","EPM") -> Cloud Practice USA | J9: =SUBSTITUTE(TRIM(H9)," ","_") -> Cloud_Practice_USA | K9: =_xlfn.CONCAT(J9,E9) -> Cloud_Practice_USAArchitect | M9: =J9 -> Cloud_Practice_USA | N9: =E9 -> Architect | O9: =_xlfn.CONCAT(C9," ",D9) -> Christina Allan | P9: {=INDEX(_xlfn.TEXTSPLIT(B9," "),3)} -> USA | S9: EPM_Practice_Canada_-_ConsolidationApplication Developer | U9: EPM_Practice_India_-_Planning | W9: Application Lead - PLN
A10: Donyati | B10: Cloud Practice USA | C10: Brandon | D10: C Wagoner | E10: Architect | F10: Full Time USA - Billable | H10: =SUBSTITUTE(SUBSTITUTE(B10,"Organizational Effectiveness","EPM"),"CPM","EPM") -> Cloud Practice USA | J10: =SUBSTITUTE(TRIM(H10)," ","_") -> Cloud_Practice_USA | K10: =_xlfn.CONCAT(J10,E10) -> Cloud_Practice_USAArchitect | M10: =J10 -> Cloud_Practice_USA | N10: =E10 -> Architect | O10: =_xlfn.CONCAT(C10," ",D10) -> Brandon C Wagoner | P10: {=INDEX(_xlfn.TEXTSPLIT(B10," "),3)} -> USA | S10: EPM_Practice_India_-_ConsolidationSr. Application Lead | U10: EPM_Practice_USA | W10: Application Support Lead
A11: Cyber Sphere LLC | B11: Cloud Practice USA | C11: Eric | D11: Paul | E11: Architect | F11: Contractor USA - Billable | H11: =SUBSTITUTE(SUBSTITUTE(B11,"Organizational Effectiveness","EPM"),"CPM","EPM") -> Cloud Practice USA | J11: =SUBSTITUTE(TRIM(H11)," ","_") -> Cloud_Practice_USA | K11: =_xlfn.CONCAT(J11,E11) -> Cloud_Practice_USAArchitect | M11: =J11 -> Cloud_Practice_USA | N11: =E11 -> Architect | O11: =_xlfn.CONCAT(C11," ",D11) -> Eric Paul | P11: {=INDEX(_xlfn.TEXTSPLIT(B11," "),3)} -> USA | S11: EPM_Practice_India_-_ConsolidationSr. Application Lead - FCC | U11: EPM_Practice_USA_-_Consolidation | W11: Application Support Lead - EPB
A12: IC | B12: Cloud Practice USA | C12: Sean | D12: Clark | E12: Architect | F12: Contractor USA - Billable | H12: =SUBSTITUTE(SUBSTITUTE(B12,"Organizational Effectiveness","EPM"),"CPM","EPM") -> Cloud Practice USA | J12: =SUBSTITUTE(TRIM(H12)," ","_") -> Cloud_Practice_USA | K12: =_xlfn.CONCAT(J12,E12) -> Cloud_Practice_USAArchitect | M12: =J12 -> Cloud_Practice_USA | N12: =E12 -> Architect | O12: =_xlfn.CONCAT(C12," ",D12) -> Sean Clark | P12: {=INDEX(_xlfn.TEXTSPLIT(B12," "),3)} -> USA | S12: EPM_Practice_India_-_ConsolidationApplication Lead - FCC | U12: EPM_Practice_USA_-_Integration | W12: Application Support Lead - FCC
A13: IC | B13: Cloud Practice USA | C13: Asha | D13: Angalla | E13: Engineer | F13: Contractor USA - Billable | H13: =SUBSTITUTE(SUBSTITUTE(B13,"Organizational Effectiveness","EPM"),"CPM","EPM") -> Cloud Practice USA | J13: =SUBSTITUTE(TRIM(H13)," ","_") -> Cloud_Practice_USA | K13: =_xlfn.CONCAT(J13,E13) -> Cloud_Practice_USAEngineer | M13: =J13 -> Cloud_Practice_USA | N13: =E13 -> Engineer | O13: =_xlfn.CONCAT(C13," ",D13) -> Asha Angalla | P13: {=INDEX(_xlfn.TEXTSPLIT(B13," "),3)} -> USA | S13: EPM_Practice_India_-_ConsolidationSoftware Engineer | U13: EPM_Practice_USA_-_Managed_Services | W13: Architect
A14: IC | B14: Cloud Practice USA | C14: Gowtham | D14: Nelavelli | E14: Engineer | F14: Contractor USA - Billable | H14: =SUBSTITUTE(SUBSTITUTE(B14,"Organizational Effectiveness","EPM"),"CPM","EPM") -> Cloud Practice USA | J14: =SUBSTITUTE(TRIM(H14)," ","_") -> Cloud_Practice_USA | K14: =_xlfn.CONCAT(J14,E14) -> Cloud_Practice_USAEngineer | M14: =J14 -> Cloud_Practice_USA | N14: =E14 -> Engineer | O14: =_xlfn.CONCAT(C14," ",D14) -> Gowtham Nelavelli | P14: {=INDEX(_xlfn.TEXTSPLIT(B14," "),3)} -> USA | S14: EPM_Practice_India_-_ConsolidationSr. Software Engineer | U14: EPM_Practice_USA_-_Planning | W14: Business/Data Analyst
A15: IC | B15: Cloud Practice USA | C15: Yoshi | D15: Budiyanto | E15: Architect | F15: Contractor USA - Billable | H15: =SUBSTITUTE(SUBSTITUTE(B15,"Organizational Effectiveness","EPM"),"CPM","EPM") -> Cloud Practice USA | J15: =SUBSTITUTE(TRIM(H15)," ","_") -> Cloud_Practice_USA | K15: =_xlfn.CONCAT(J15,E15) -> Cloud_Practice_USAArchitect | M15: =J15 -> Cloud_Practice_USA | N15: =E15 -> Architect | O15: =_xlfn.CONCAT(C15," ",D15) -> Yoshi Budiyanto | P15: {=INDEX(_xlfn.TEXTSPLIT(B15," "),3)} -> USA | S15: EPM_Practice_India_-_ConsolidationApplication Developer - FCC | U15: ERP_Practice_Argentina | W15: Developer
... A25: Donyati | B25: EPM Practice India - Consolidation | C25: Sabaritha | D25: Rajendran | E25: Sr. Software Engineer | F25: Full Time India - Billable | H25: =SUBSTITUTE(SUBSTITUTE(B25,"Organizational Effectiveness","EPM"),"CPM","EPM") -> EPM Practice India - Consolidation | J25: =SUBSTITUTE(TRIM(H25)," ","_") -> EPM_Practice_India_-_Consolidation | K25: =_xlfn.CONCAT(J25,E25) -> EPM_Practice_India_-_ConsolidationSr. Software Engineer | M25: =J25 -> EPM_Practice_India_-_Consolidation | N25: =E25 -> Sr. Software Engineer | O25: =_xlfn.CONCAT(C25," ",D25) -> Sabaritha Rajendran | P25: {=INDEX(_xlfn.TEXTSPLIT(B25," "),3)} -> India | S25: EPM_Practice_India_-_IntegrationSr. Integration Lead | U25: TS_Practice_USA | W25: Project Manager
A26: Donyati | B26: EPM Practice India - Consolidation | C26: Rithik | D26: Prem | E26: Sr. Software Engineer | F26: Full Time India - Billable | H26: =SUBSTITUTE(SUBSTITUTE(B26,"Organizational Effectiveness","EPM"),"CPM","EPM") -> EPM Practice India - Consolidation | J26: =SUBSTITUTE(TRIM(H26)," ","_") -> EPM_Practice_India_-_Consolidation | K26: =_xlfn.CONCAT(J26,E26) -> EPM_Practice_India_-_ConsolidationSr. Software Engineer | M26: =J26 -> EPM_Practice_India_-_Consolidation | N26: =E26 -> Sr. Software Engineer | O26: =_xlfn.CONCAT(C26," ",D26) -> Rithik Prem | P26: {=INDEX(_xlfn.TEXTSPLIT(B26," "),3)} -> India | S26: EPM_Practice_India_-_PlanningSr. Application Lead - PLN | W26: QA Tester - Automation
A27: Donyati | B27: EPM Practice India - Consolidation | C27: Manjunath | D27: M P | E27: Sr. Software Engineer | F27: Full Time India - Billable | H27: =SUBSTITUTE(SUBSTITUTE(B27,"Organizational Effectiveness","EPM"),"CPM","EPM") -> EPM Practice India - Consolidation | J27: =SUBSTITUTE(TRIM(H27)," ","_") -> EPM_Practice_India_-_Consolidation | K27: =_xlfn.CONCAT(J27,E27) -> EPM_Practice_India_-_ConsolidationSr. Software Engineer | M27: =J27 -> EPM_Practice_India_-_Consolidation | N27: =E27 -> Sr. Software Engineer | O27: =_xlfn.CONCAT(C27," ",D27) -> Manjunath M P | P27: {=INDEX(_xlfn.TEXTSPLIT(B27," "),3)} -> India | S27: EPM_Practice_India_-_PlanningSr. Application Developer | W27: QA Tester - Manual
A28: Donyati | B28: EPM Practice India - Consolidation | C28: Kartikey | D28: Panday | E28: Application Developer - FCC | F28: Full Time India - Billable | H28: =SUBSTITUTE(SUBSTITUTE(B28,"Organizational Effectiveness","EPM"),"CPM","EPM") -> EPM Practice India - Consolidation | J28: =SUBSTITUTE(TRIM(H28)," ","_") -> EPM_Practice_India_-_Consolidation | K28: =_xlfn.CONCAT(J28,E28) -> EPM_Practice_India_-_ConsolidationApplication Developer - FCC | M28: =J28 -> EPM_Practice_India_-_Consolidation | N28: =E28 -> Application Developer - FCC | O28: =_xlfn.CONCAT(C28," ",D28) -> Kartikey Panday | P28: {=INDEX(_xlfn.TEXTSPLIT(B28," "),3)} -> India | S28: EPM_Practice_India_-_PlanningSolution Architect - PLN | W28: Security Engineer
A29: Donyati | B29: EPM Practice India - Consolidation | C29: Kamalashree | D29: Appavu | E29: Application Developer - FCC | F29: Full Time India - Billable | H29: =SUBSTITUTE(SUBSTITUTE(B29,"Organizational Effectiveness","EPM"),"CPM","EPM") -> EPM Practice India - Consolidation | J29: =SUBSTITUTE(TRIM(H29)," ","_") -> EPM_Practice_India_-_Consolidation | K29: =_xlfn.CONCAT(J29,E29) -> EPM_Practice_India_-_ConsolidationApplication Developer - FCC | M29: =J29 -> EPM_Practice_India_-_Consolidation | N29: =E29 -> Application Developer - FCC | O29: =_xlfn.CONCAT(C29," ",D29) -> Kamalashree Appavu | P29: {=INDEX(_xlfn.TEXTSPLIT(B29," "),3)} -> India | S29: EPM_Practice_India_-_PlanningApplication Developer - PLN | W29: Service Delivery Manager
A30: Donyati | B30: EPM Practice India - Consolidation | C30: Aparna Ottapurakkal | D30: Kallada | E30: Sr. Solution Architect - FCC | F30: Full Time India - Billable | H30: =SUBSTITUTE(SUBSTITUTE(B30,"Organizational Effectiveness","EPM"),"CPM","EPM") -> EPM Practice India - Consolidation | J30: =SUBSTITUTE(TRIM(H30)," ","_") -> EPM_Practice_India_-_Consolidation | K30: =_xlfn.CONCAT(J30,E30) -> EPM_Practice_India_-_ConsolidationSr. Solution Architect - FCC | M30: =J30 -> EPM_Practice_India_-_Consolidation | N30: =E30 -> Sr. Solution Architect - FCC | O30: =_xlfn.CONCAT(C30," ",D30) -> Aparna Ottapurakkal Kallada | P30: {=INDEX(_xlfn.TEXTSPLIT(B30," "),3)} -> India | S30: EPM_Practice_India_-_PlanningSr. Application Developer - PLN | W30: Software Engineer
A31: Donyati | B31: EPM Practice India - Consolidation | C31: Anand | D31: Thota | E31: Application Lead - FCC | F31: Full Time India - Billable | H31: =SUBSTITUTE(SUBSTITUTE(B31,"Organizational Effectiveness","EPM"),"CPM","EPM") -> EPM Practice India - Consolidation | J31: =SUBSTITUTE(TRIM(H31)," ","_") -> EPM_Practice_India_-_Consolidation | K31: =_xlfn.CONCAT(J31,E31) -> EPM_Practice_India_-_ConsolidationApplication Lead - FCC | M31: =J31 -> EPM_Practice_India_-_Consolidation | N31: =E31 -> Application Lead - FCC | O31: =_xlfn.CONCAT(C31," ",D31) -> Anand Thota | P31: {=INDEX(_xlfn.TEXTSPLIT(B31," "),3)} -> India | S31: EPM_Practice_India_-_PlanningSr. Solution Architect | W31: Solution Architect
A32: Donyati | B32: EPM Practice India - Integration | C32: Disha Chhabria | D32: Kukreja | E32: Sr. Solution Architect | F32: Full Time India - Billable | H32: =SUBSTITUTE(SUBSTITUTE(B32,"Organizational Effectiveness","EPM"),"CPM","EPM") -> EPM Practice India - Integration | J32: =SUBSTITUTE(TRIM(H32)," ","_") -> EPM_Practice_India_-_Integration | K32: =_xlfn.CONCAT(J32,E32) -> EPM_Practice_India_-_IntegrationSr. Solution Architect | M32: =J32 -> EPM_Practice_India_-_Integration | N32: =E32 -> Sr. Solution Architect | O32: =_xlfn.CONCAT(C32," ",D32) -> Disha Chhabria Kukreja | P32: {=INDEX(_xlfn.TEXTSPLIT(B32," "),3)} -> India | S32: EPM_Practice_India_-_PlanningSoftware Engineer | W32: Solution Architect - DI
A33: Donyati | B33: EPM Practice India - Integration | C33: Lohith | D33: Reddy Pidimarla | E33: Sr. Software Engineer | F33: Full Time India - Billable | H33: =SUBSTITUTE(SUBSTITUTE(B33,"Organizational Effectiveness","EPM"),"CPM","EPM") -> EPM Practice India - Integration | J33: =SUBSTITUTE(TRIM(H33)," ","_") -> EPM_Practice_India_-_Integration | K33: =_xlfn.CONCAT(J33,E33) -> EPM_Practice_India_-_IntegrationSr. Software Engineer | M33: =J33 -> EPM_Practice_India_-_Integration | N33: =E33 -> Sr. Software Engineer | O33: =_xlfn.CONCAT(C33," ",D33) -> Lohith Reddy Pidimarla | P33: {=INDEX(_xlfn.TEXTSPLIT(B33," "),3)} -> India | S33: EPM_Practice_India_-_PlanningApplication Lead - PLN | W33: Solution Architect - FCC
A34: Donyati | B34: EPM Practice India - Integration | C34: Shyam | D34: Natarajan | E34: Software Engineer | F34: Full Time India - Billable | H34: =SUBSTITUTE(SUBSTITUTE(B34,"Organizational Effectiveness","EPM"),"CPM","EPM") -> EPM Practice India - Integration | J34: =SUBSTITUTE(TRIM(H34)," ","_") -> EPM_Practice_India_-_Integration | K34: =_xlfn.CONCAT(J34,E34) -> EPM_Practice_India_-_IntegrationSoftware Engineer | M34: =J34 -> EPM_Practice_India_-_Integration | N34: =E34 -> Software Engineer | O34: =_xlfn.CONCAT(C34," ",D34) -> Shyam Natarajan | P34: {=INDEX(_xlfn.TEXTSPLIT(B34," "),3)} -> India | S34: EPM_Practice_India_-_PlanningSr. Solution Architect - PLN | W34: Solution Architect - PLN
A35: Donyati | B35: EPM Practice India - Integration | C35: Ashok Reddy | D35: Komineni | E35: Sr. Software Engineer | F35: Full Time India - Billable | H35: =SUBSTITUTE(SUBSTITUTE(B35,"Organizational Effectiveness","EPM"),"CPM","EPM") -> EPM Practice India - Integration | J35: =SUBSTITUTE(TRIM(H35)," ","_") -> EPM_Practice_India_-_Integration | K35: =_xlfn.CONCAT(J35,E35) -> EPM_Practice_India_-_IntegrationSr. Software Engineer | M35: =J35 -> EPM_Practice_India_-_Integration | N35: =E35 -> Sr. Software Engineer | O35: =_xlfn.CONCAT(C35," ",D35) -> Ashok Reddy Komineni | P35: {=INDEX(_xlfn.TEXTSPLIT(B35," "),3)} -> India | S35: EPM_Practice_India_-_PlanningSr. Software Engineer | W35: Sr. Application Developer
A36: Donyati | B36: EPM Practice India - Integration | C36: Prakash | D36: Ramchandran | E36: Solution Architect - DI | F36: Full Time India - Billable | H36: =SUBSTITUTE(SUBSTITUTE(B36,"Organizational Effectiveness","EPM"),"CPM","EPM") -> EPM Practice India - Integration | J36: =SUBSTITUTE(TRIM(H36)," ","_") -> EPM_Practice_India_-_Integration | K36: =_xlfn.CONCAT(J36,E36) -> EPM_Practice_India_-_IntegrationSolution Architect - DI | M36: =J36 -> EPM_Practice_India_-_Integration | N36: =E36 -> Solution Architect - DI | O36: =_xlfn.CONCAT(C36," ",D36) -> Prakash Ramchandran | P36: {=INDEX(_xlfn.TEXTSPLIT(B36," "),3)} -> India | S36: EPM_Practice_USAApplication Developer | W36: Sr. Application Developer - DI
A37: Donyati | B37: EPM Practice India - Integration | C37: Sanjai | D37: Ponnuvel | E37: Software Engineer | F37: Full Time India - Billable | H37: =SUBSTITUTE(SUBSTITUTE(B37,"Organizational Effectiveness","EPM"),"CPM","EPM") -> EPM Practice India - Integration | J37: =SUBSTITUTE(TRIM(H37)," ","_") -> EPM_Practice_India_-_Integration | K37: =_xlfn.CONCAT(J37,E37) -> EPM_Practice_India_-_IntegrationSoftware Engineer | M37: =J37 -> EPM_Practice_India_-_Integration | N37: =E37 -> Software Engineer | O37: =_xlfn.CONCAT(C37," ",D37) -> Sanjai Ponnuvel | P37: {=INDEX(_xlfn.TEXTSPLIT(B37," "),3)} -> India | S37: EPM_Practice_USAPrincipal Architect | W37: Sr. Application Developer - PLN
... A63: Donyati | B63: EPM Practice India - Planning | C63: Vadisela | D63: Pavan Kumar Reddy | E63: Software Engineer | F63: Full Time India - Billable | H63: =SUBSTITUTE(SUBSTITUTE(B63,"Organizational Effectiveness","EPM"),"CPM","EPM") -> EPM Practice India - Planning | J63: =SUBSTITUTE(TRIM(H63)," ","_") -> EPM_Practice_India_-_Planning | K63: =_xlfn.CONCAT(J63,E63) -> EPM_Practice_India_-_PlanningSoftware Engineer | M63: =J63 -> EPM_Practice_India_-_Planning | N63: =E63 -> Software Engineer | O63: =_xlfn.CONCAT(C63," ",D63) -> Vadisela Pavan Kumar Reddy | P63: {=INDEX(_xlfn.TEXTSPLIT(B63," "),3)} -> India | S63: EPM_Practice_USA_-_PlanningApplication Developer - PLN | W63: Techno-Functional Finance Lead
A64: Donyati | B64: EPM Practice India - Planning | C64: Girinath | D64: B | E64: Software Engineer | F64: Full Time India - Billable | H64: =SUBSTITUTE(SUBSTITUTE(B64,"Organizational Effectiveness","EPM"),"CPM","EPM") -> EPM Practice India - Planning | J64: =SUBSTITUTE(TRIM(H64)," ","_") -> EPM_Practice_India_-_Planning | K64: =_xlfn.CONCAT(J64,E64) -> EPM_Practice_India_-_PlanningSoftware Engineer | M64: =J64 -> EPM_Practice_India_-_Planning | N64: =E64 -> Software Engineer | O64: =_xlfn.CONCAT(C64," ",D64) -> Girinath B | P64: {=INDEX(_xlfn.TEXTSPLIT(B64," "),3)} -> India | S64: EPM_Practice_USA_-_PlanningSolution Architect | W64: 0
A65: Donyati | B65: EPM Practice India - Planning | C65: Karaneeshwaran | D65: K | E65: Software Engineer | F65: Full Time India - Billable | H65: =SUBSTITUTE(SUBSTITUTE(B65,"Organizational Effectiveness","EPM"),"CPM","EPM") -> EPM Practice India - Planning | J65: =SUBSTITUTE(TRIM(H65)," ","_") -> EPM_Practice_India_-_Planning | K65: =_xlfn.CONCAT(J65,E65) -> EPM_Practice_India_-_PlanningSoftware Engineer | M65: =J65 -> EPM_Practice_India_-_Planning | N65: =E65 -> Software Engineer | O65: =_xlfn.CONCAT(C65," ",D65) -> Karaneeshwaran K | P65: {=INDEX(_xlfn.TEXTSPLIT(B65," "),3)} -> India | S65: EPM_Practice_USA_-_PlanningApplication Developer
A66: Donyati | B66: EPM Practice India - Planning | C66: Shreepriya | D66: V | E66: Software Engineer | F66: Full Time India - Billable | H66: =SUBSTITUTE(SUBSTITUTE(B66,"Organizational Effectiveness","EPM"),"CPM","EPM") -> EPM Practice India - Planning | J66: =SUBSTITUTE(TRIM(H66)," ","_") -> EPM_Practice_India_-_Planning | K66: =_xlfn.CONCAT(J66,E66) -> EPM_Practice_India_-_PlanningSoftware Engineer | M66: =J66 -> EPM_Practice_India_-_Planning | N66: =E66 -> Software Engineer | O66: =_xlfn.CONCAT(C66," ",D66) -> Shreepriya V | P66: {=INDEX(_xlfn.TEXTSPLIT(B66," "),3)} -> India | S66: EPM_Practice_USA_-_PlanningSr. Application Lead
A67: Donyati | B67: EPM Practice India - Planning | C67: Saran | D67: Jayaprakash | E67: Software Engineer | F67: Full Time India - Billable | H67: =SUBSTITUTE(SUBSTITUTE(B67,"Organizational Effectiveness","EPM"),"CPM","EPM") -> EPM Practice India - Planning | J67: =SUBSTITUTE(TRIM(H67)," ","_") -> EPM_Practice_India_-_Planning | K67: =_xlfn.CONCAT(J67,E67) -> EPM_Practice_India_-_PlanningSoftware Engineer | M67: =J67 -> EPM_Practice_India_-_Planning | N67: =E67 -> Software Engineer | O67: =_xlfn.CONCAT(C67," ",D67) -> Saran Jayaprakash | P67: {=INDEX(_xlfn.TEXTSPLIT(B67," "),3)} -> India | S67: ERP_Practice_ArgentinaApplication Developer
A68: Donyati | B68: EPM Practice India - Planning | C68: Sharmila | D68: S | E68: Software Engineer | F68: Full Time India - Billable | H68: =SUBSTITUTE(SUBSTITUTE(B68,"Organizational Effectiveness","EPM"),"CPM","EPM") -> EPM Practice India - Planning | J68: =SUBSTITUTE(TRIM(H68)," ","_") -> EPM_Practice_India_-_Planning | K68: =_xlfn.CONCAT(J68,E68) -> EPM_Practice_India_-_PlanningSoftware Engineer | M68: =J68 -> EPM_Practice_India_-_Planning | N68: =E68 -> Software Engineer | O68: =_xlfn.CONCAT(C68," ",D68) -> Sharmila S | P68: {=INDEX(_xlfn.TEXTSPLIT(B68," "),3)} -> India | S68: ERP_Practice_ArgentinaSr. Application Lead
A69: Donyati | B69: EPM Practice India - Planning | C69: Deep Narayan | D69: Sharma | E69: Software Engineer | F69: Full Time India - Billable | H69: =SUBSTITUTE(SUBSTITUTE(B69,"Organizational Effectiveness","EPM"),"CPM","EPM") -> EPM Practice India - Planning | J69: =SUBSTITUTE(TRIM(H69)," ","_") -> EPM_Practice_India_-_Planning | K69: =_xlfn.CONCAT(J69,E69) -> EPM_Practice_India_-_PlanningSoftware Engineer | M69: =J69 -> EPM_Practice_India_-_Planning | N69: =E69 -> Software Engineer | O69: =_xlfn.CONCAT(C69," ",D69) -> Deep Narayan Sharma | P69: {=INDEX(_xlfn.TEXTSPLIT(B69," "),3)} -> India | S69: ERP_Practice_ArgentinaSr. Functional Lead
A70: Donyati | B70: EPM Practice India - Planning | C70: Visweswari | D70: Somaiahgari | E70: Application Lead - PLN | F70: Full Time India - Billable | H70: =SUBSTITUTE(SUBSTITUTE(B70,"Organizational Effectiveness","EPM"),"CPM","EPM") -> EPM Practice India - Planning | J70: =SUBSTITUTE(TRIM(H70)," ","_") -> EPM_Practice_India_-_Planning | K70: =_xlfn.CONCAT(J70,E70) -> EPM_Practice_India_-_PlanningApplication Lead - PLN | M70: =J70 -> EPM_Practice_India_-_Planning | N70: =E70 -> Application Lead - PLN | O70: =_xlfn.CONCAT(C70," ",D70) -> Visweswari Somaiahgari | P70: {=INDEX(_xlfn.TEXTSPLIT(B70," "),3)} -> India | S70: ERP_Practice_ArgentinaSr. Application Developer
A71: Donyati | B71: EPM Practice India - Planning | C71: Shabnam | D71: Fairoz | E71: Application Lead - PLN | F71: Full Time India - Billable | H71: =SUBSTITUTE(SUBSTITUTE(B71,"Organizational Effectiveness","EPM"),"CPM","EPM") -> EPM Practice India - Planning | J71: =SUBSTITUTE(TRIM(H71)," ","_") -> EPM_Practice_India_-_Planning | K71: =_xlfn.CONCAT(J71,E71) -> EPM_Practice_India_-_PlanningApplication Lead - PLN | M71: =J71 -> EPM_Practice_India_-_Planning | N71: =E71 -> Application Lead - PLN | O71: =_xlfn.CONCAT(C71," ",D71) -> Shabnam Fairoz | P71: {=INDEX(_xlfn.TEXTSPLIT(B71," "),3)} -> India | S71: ERP_Practice_ArgentinaSr. Project Manager
A72: Donyati | B72: EPM Practice India - Planning | C72: Rinku | D72: Agrawal | E72: Sr. Solution Architect - PLN | F72: Full Time India - Billable | H72: =SUBSTITUTE(SUBSTITUTE(B72,"Organizational Effectiveness","EPM"),"CPM","EPM") -> EPM Practice India - Planning | J72: =SUBSTITUTE(TRIM(H72)," ","_") -> EPM_Practice_India_-_Planning | K72: =_xlfn.CONCAT(J72,E72) -> EPM_Practice_India_-_PlanningSr. Solution Architect - PLN | M72: =J72 -> EPM_Practice_India_-_Planning | N72: =E72 -> Sr. Solution Architect - PLN | O72: =_xlfn.CONCAT(C72," ",D72) -> Rinku Agrawal | P72: {=INDEX(_xlfn.TEXTSPLIT(B72," "),3)} -> India | S72: ERP_Practice_BrazilApplication Lead
A73: Donyati | B73: EPM Practice India - Planning | C73: Kruthika | D73: Sidnal | E73: Application Developer - PLN | F73: Full Time India - Billable | H73: =SUBSTITUTE(SUBSTITUTE(B73,"Organizational Effectiveness","EPM"),"CPM","EPM") -> EPM Practice India - Planning | J73: =SUBSTITUTE(TRIM(H73)," ","_") -> EPM_Practice_India_-_Planning | K73: =_xlfn.CONCAT(J73,E73) -> EPM_Practice_India_-_PlanningApplication Developer - PLN | M73: =J73 -> EPM_Practice_India_-_Planning | N73: =E73 -> Application Developer - PLN | O73: =_xlfn.CONCAT(C73," ",D73) -> Kruthika Sidnal | P73: {=INDEX(_xlfn.TEXTSPLIT(B73," "),3)} -> India | S73: ERP_Practice_CzechRepublicSr. Project Manager
A74: Donyati | B74: EPM Practice India - Planning | C74: Kashinath | D74: Manoharan | E74: Sr. Software Engineer | F74: Full Time India - Billable | H74: =SUBSTITUTE(SUBSTITUTE(B74,"Organizational Effectiveness","EPM"),"CPM","EPM") -> EPM Practice India - Planning | J74: =SUBSTITUTE(TRIM(H74)," ","_") -> EPM_Practice_India_-_Planning | K74: =_xlfn.CONCAT(J74,E74) -> EPM_Practice_India_-_PlanningSr. Software Engineer | M74: =J74 -> EPM_Practice_India_-_Planning | N74: =E74 -> Sr. Software Engineer | O74: =_xlfn.CONCAT(C74," ",D74) -> Kashinath Manoharan | P74: {=INDEX(_xlfn.TEXTSPLIT(B74," "),3)} -> India | S74: ERP_Practice_GermanyPrincipal
A75: Donyati | B75: EPM Practice India - Planning | C75: Indumathi | D75: Peraiyur Chandrasekar | E75: Sr. Application Developer - PLN | F75: Full Time India - Billable | H75: =SUBSTITUTE(SUBSTITUTE(B75,"Organizational Effectiveness","EPM"),"CPM","EPM") -> EPM Practice India - Planning | J75: =SUBSTITUTE(TRIM(H75)," ","_") -> EPM_Practice_India_-_Planning | K75: =_xlfn.CONCAT(J75,E75) -> EPM_Practice_India_-_PlanningSr. Application Developer - PLN | M75: =J75 -> EPM_Practice_India_-_Planning | N75: =E75 -> Sr. Application Developer - PLN | O75: =_xlfn.CONCAT(C75," ",D75) -> Indumathi Peraiyur Chandrasekar | P75: {=INDEX(_xlfn.TEXTSPLIT(B75," "),3)} -> India | S75: ERP_Practice_IndiaSolution Architect
A76: Donyati | B76: EPM Practice India - Planning | C76: Balaji | D76: Venkatachalam | E76: Solution Architect - PLN | F76: Full Time India - Billable | H76: =SUBSTITUTE(SUBSTITUTE(B76,"Organizational Effectiveness","EPM"),"CPM","EPM") -> EPM Practice India - Planning | J76: =SUBSTITUTE(TRIM(H76)," ","_") -> EPM_Practice_India_-_Planning | K76: =_xlfn.CONCAT(J76,E76) -> EPM_Practice_India_-_PlanningSolution Architect - PLN | M76: =J76 -> EPM_Practice_India_-_Planning | N76: =E76 -> Solution Architect - PLN | O76: =_xlfn.CONCAT(C76," ",D76) -> Balaji Venkatachalam | P76: {=INDEX(_xlfn.TEXTSPLIT(B76," "),3)} -> India | S76: ERP_Practice_IndiaSr. Application Developer
... A132: IC | B132: ERP Practice Mexico | C132: Melvin | D132: Benitez | E132: Application Developer | F132: Contractor Mexico - Billable | H132: =SUBSTITUTE(SUBSTITUTE(B132,"Organizational Effectiveness","EPM"),"CPM","EPM") -> ERP Practice Mexico | J132: =SUBSTITUTE(TRIM(H132)," ","_") -> ERP_Practice_Mexico | K132: =_xlfn.CONCAT(J132,E132) -> ERP_Practice_MexicoApplication Developer | M132: =J132 -> ERP_Practice_Mexico | N132: =E132 -> Application Developer | O132: =_xlfn.CONCAT(C132," ",D132) -> Melvin Benitez | P132: {=INDEX(_xlfn.TEXTSPLIT(B132," "),3)} -> Mexico | S132: TS_Practice_USABusiness/Data Analyst
A133: IC | B133: ERP Practice Spain | C133: Bruce | D133: Murray | E133: Techno-Functional Finance Lead | F133: Contractor Spain - Billable | H133: =SUBSTITUTE(SUBSTITUTE(B133,"Organizational Effectiveness","EPM"),"CPM","EPM") -> ERP Practice Spain | J133: =SUBSTITUTE(TRIM(H133)," ","_") -> ERP_Practice_Spain | K133: =_xlfn.CONCAT(J133,E133) -> ERP_Practice_SpainTechno-Functional Finance Lead | M133: =J133 -> ERP_Practice_Spain | N133: =E133 -> Techno-Functional Finance Lead | O133: =_xlfn.CONCAT(C133," ",D133) -> Bruce Murray | P133: {=INDEX(_xlfn.TEXTSPLIT(B133," "),3)} -> Spain
A134: SC&H | B134: ERP Practice USA | C134: Cristina | D134: Purice | E134: Application Lead | F134: Contractor USA - Billable | H134: =SUBSTITUTE(SUBSTITUTE(B134,"Organizational Effectiveness","EPM"),"CPM","EPM") -> ERP Practice USA | J134: =SUBSTITUTE(TRIM(H134)," ","_") -> ERP_Practice_USA | K134: =_xlfn.CONCAT(J134,E134) -> ERP_Practice_USAApplication Lead | M134: =J134 -> ERP_Practice_USA | N134: =E134 -> Application Lead | O134: =_xlfn.CONCAT(C134," ",D134) -> Cristina Purice | P134: {=INDEX(_xlfn.TEXTSPLIT(B134," "),3)} -> USA
A135: SC&H | B135: ERP Practice USA | C135: Brian | D135: Kotch | E135: Sr. Application Lead | F135: Contractor USA - Billable | H135: =SUBSTITUTE(SUBSTITUTE(B135,"Organizational Effectiveness","EPM"),"CPM","EPM") -> ERP Practice USA | J135: =SUBSTITUTE(TRIM(H135)," ","_") -> ERP_Practice_USA | K135: =_xlfn.CONCAT(J135,E135) -> ERP_Practice_USASr. Application Lead | M135: =J135 -> ERP_Practice_USA | N135: =E135 -> Sr. Application Lead | O135: =_xlfn.CONCAT(C135," ",D135) -> Brian Kotch | P135: {=INDEX(_xlfn.TEXTSPLIT(B135," "),3)} -> USA
A136: Donyati | B136: ERP Practice USA | C136: Rick D | D136: Humphress | E136: Application Support Lead | F136: Full Time USA - Billable | H136: =SUBSTITUTE(SUBSTITUTE(B136,"Organizational Effectiveness","EPM"),"CPM","EPM") -> ERP Practice USA | J136: =SUBSTITUTE(TRIM(H136)," ","_") -> ERP_Practice_USA | K136: =_xlfn.CONCAT(J136,E136) -> ERP_Practice_USAApplication Support Lead | M136: =J136 -> ERP_Practice_USA | N136: =E136 -> Application Support Lead | O136: =_xlfn.CONCAT(C136," ",D136) -> Rick D Humphress | P136: {=INDEX(_xlfn.TEXTSPLIT(B136," "),3)} -> USA
A137: Donyati | B137: ERP Practice USA | C137: Elizabeth | D137: Stallings | E137: Application Lead | F137: Full Time USA - Billable | H137: =SUBSTITUTE(SUBSTITUTE(B137,"Organizational Effectiveness","EPM"),"CPM","EPM") -> ERP Practice USA | J137: =SUBSTITUTE(TRIM(H137)," ","_") -> ERP_Practice_USA | K137: =_xlfn.CONCAT(J137,E137) -> ERP_Practice_USAApplication Lead | M137: =J137 -> ERP_Practice_USA | N137: =E137 -> Application Lead | O137: =_xlfn.CONCAT(C137," ",D137) -> Elizabeth Stallings | P137: {=INDEX(_xlfn.TEXTSPLIT(B137," "),3)} -> USA
A138: Donyati | B138: ERP Practice USA | C138: Veera | D138: Gandreti | E138: Sr. Application Lead | F138: Full Time USA - Billable | H138: =SUBSTITUTE(SUBSTITUTE(B138,"Organizational Effectiveness","EPM"),"CPM","EPM") -> ERP Practice USA | J138: =SUBSTITUTE(TRIM(H138)," ","_") -> ERP_Practice_USA | K138: =_xlfn.CONCAT(J138,E138) -> ERP_Practice_USASr. Application Lead | M138: =J138 -> ERP_Practice_USA | N138: =E138 -> Sr. Application Lead | O138: =_xlfn.CONCAT(C138," ",D138) -> Veera Gandreti | P138: {=INDEX(_xlfn.TEXTSPLIT(B138," "),3)} -> USA
A139: Donyati | B139: ERP Practice USA | C139: Sean | D139: Stillwell | E139: Sr. Solution Architect | F139: Full Time USA - Billable | H139: =SUBSTITUTE(SUBSTITUTE(B139,"Organizational Effectiveness","EPM"),"CPM","EPM") -> ERP Practice USA | J139: =SUBSTITUTE(TRIM(H139)," ","_") -> ERP_Practice_USA | K139: =_xlfn.CONCAT(J139,E139) -> ERP_Practice_USASr. Solution Architect | M139: =J139 -> ERP_Practice_USA | N139: =E139 -> Sr. Solution Architect | O139: =_xlfn.CONCAT(C139," ",D139) -> Sean Stillwell | P139: {=INDEX(_xlfn.TEXTSPLIT(B139," "),3)} -> USA
A140: Donyati | B140: ERP Practice USA | C140: Benjamin | D140: Lyskawa | E140: Project Manager | F140: Full Time USA - Billable | H140: =SUBSTITUTE(SUBSTITUTE(B140,"Organizational Effectiveness","EPM"),"CPM","EPM") -> ERP Practice USA | J140: =SUBSTITUTE(TRIM(H140)," ","_") -> ERP_Practice_USA | K140: =_xlfn.CONCAT(J140,E140) -> ERP_Practice_USAProject Manager | M140: =J140 -> ERP_Practice_USA | N140: =E140 -> Project Manager | O140: =_xlfn.CONCAT(C140," ",D140) -> Benjamin Lyskawa | P140: {=INDEX(_xlfn.TEXTSPLIT(B140," "),3)} -> USA
A141: Sygna Solutions | B141: ERP Practice USA | C141: Venkateshwar | D141: Reddy | E141: Sr. Application Support Lead | F141: Contractor USA - Billable | H141: =SUBSTITUTE(SUBSTITUTE(B141,"Organizational Effectiveness","EPM"),"CPM","EPM") -> ERP Practice USA | J141: =SUBSTITUTE(TRIM(H141)," ","_") -> ERP_Practice_USA | K141: =_xlfn.CONCAT(J141,E141) -> ERP_Practice_USASr. Application Support Lead | M141: =J141 -> ERP_Practice_USA | N141: =E141 -> Sr. Application Support Lead | O141: =_xlfn.CONCAT(C141," ",D141) -> Venkateshwar Reddy | P141: {=INDEX(_xlfn.TEXTSPLIT(B141," "),3)} -> USA
A142: Sygna Solutions | B142: ERP Practice USA | C142: Suresh | D142: Lingutla | E142: Application Lead | F142: Contractor USA - Billable | H142: =SUBSTITUTE(SUBSTITUTE(B142,"Organizational Effectiveness","EPM"),"CPM","EPM") -> ERP Practice USA | J142: =SUBSTITUTE(TRIM(H142)," ","_") -> ERP_Practice_USA | K142: =_xlfn.CONCAT(J142,E142) -> ERP_Practice_USAApplication Lead | M142: =J142 -> ERP_Practice_USA | N142: =E142 -> Application Lead | O142: =_xlfn.CONCAT(C142," ",D142) -> Suresh Lingutla | P142: {=INDEX(_xlfn.TEXTSPLIT(B142," "),3)} -> USA
A143: Smartsoft International Inc. | B143: ERP Practice USA | C143: Vasanth | D143: Krishnamoorthy | E143: Sr. Application Developer | F143: Contractor USA - Billable | H143: =SUBSTITUTE(SUBSTITUTE(B143,"Organizational Effectiveness","EPM"),"CPM","EPM") -> ERP Practice USA | J143: =SUBSTITUTE(TRIM(H143)," ","_") -> ERP_Practice_USA | K143: =_xlfn.CONCAT(J143,E143) -> ERP_Practice_USASr. Application Developer | M143: =J143 -> ERP_Practice_USA | N143: =E143 -> Sr. Application Developer | O143: =_xlfn.CONCAT(C143," ",D143) -> Vasanth Krishnamoorthy | P143: {=INDEX(_xlfn.TEXTSPLIT(B143," "),3)} -> USA
A144: Smartsoft International Inc. | B144: ERP Practice USA | C144: Muthukumar | D144: Kumar | E144: Sr. Application Support Lead | F144: Contractor USA - Billable | H144: =SUBSTITUTE(SUBSTITUTE(B144,"Organizational Effectiveness","EPM"),"CPM","EPM") -> ERP Practice USA | J144: =SUBSTITUTE(TRIM(H144)," ","_") -> ERP_Practice_USA | K144: =_xlfn.CONCAT(J144,E144) -> ERP_Practice_USASr. Application Support Lead | M144: =J144 -> ERP_Practice_USA | N144: =E144 -> Sr. Application Support Lead | O144: =_xlfn.CONCAT(C144," ",D144) -> Muthukumar Kumar | P144: {=INDEX(_xlfn.TEXTSPLIT(B144," "),3)} -> USA
... A278: ReqRoute Inc | B278: TS Practice USA | C278: Jinali | D278: Kamdar | E278: Business/Data Analyst | F278: Contractor USA - Billable | H278: =SUBSTITUTE(SUBSTITUTE(B278,"Organizational Effectiveness","EPM"),"CPM","EPM") -> TS Practice USA | J278: =SUBSTITUTE(TRIM(H278)," ","_") -> TS_Practice_USA | K278: =_xlfn.CONCAT(J278,E278) -> TS_Practice_USABusiness/Data Analyst | M278: =J278 -> TS_Practice_USA | N278: =E278 -> Business/Data Analyst | O278: =_xlfn.CONCAT(C278," ",D278) -> Jinali Kamdar | P278: {=INDEX(_xlfn.TEXTSPLIT(B278," "),3)} -> USA
J279: =SUBSTITUTE(TRIM(H279)," ","_") | K279: =_xlfn.CONCAT(J279,E279) | M279: =J279

Sheet Customer Capability Service
A1: Customers | B1: Updated 9/23/25 | D1: Capability | E1: Updated 11/7/25 | G1: Service | H1: Updated 11/7/25
A2: 1800HANSONS | D2: ARCS | G2: Advisory
A3: Acadia Healthcare | D3: AWS | G3: Application Rationalization
A4: Adecco | D4: Azure | G4: Application Support
A5: Adecco(Oracle) | D5: Backend Technologies | G5: Assessment
A6: ADVICS | D6: BCP/DR | G6: Business Analyst Support
A7: Aisin World Corp of America | D7: BI | G7: Change Management
A8: AIT Worldwide Logistics | D8: Cloud Engineering | G8: Deployment Support
A9: Amentum(SC&H) | D9: Cloud IP | G9: Development
A10: AmTrust Financial Services | D10: Cloud PM | G10: Divestiture/Spinoff Support
A11: AmTrust Financial(Oracle) | D11: Consolidation Cloud | G11: Enhancements
A12: Anthem(TNP Systems) | D12: CPM IP | G12: Finance Transformation
A13: Apex Tool Group | D13: Cybersecurity | G13: Functional Support
... A30: Body Control Systems | D30: Google Cloud | G30: Upgrade
A31: BorgWarner | D31: HFM
A32: BRAVVOX | D32: Hyperion Suite
A33: Builders FirstSource | D33: IT
A34: Bunge(Microland) | D34: Middleware
A35: CarTech(SC&H) | D35: MuleSoft
A36: Catholic Relief Services | D36: OCI
A37: CDM Smith | D37: OneStream
A38: Central Insurance | D38: Oracle Data Integrator
A39: Centric3 | D39: Oracle EBS
A40: Century Aluminum | D40: Oracle ERP Cloud
A41: Charter Communications(Trace3) | D41: Oracle HCM
A42: Cintas(Trace3) | D42: Oracle JD Edwards
... A64: Equinox Gold | D64: Workday
A65: Experian(Xoogify)
A66: Express Flooring
A67: FDC
A68: Fiserv
A69: Fiserv India
A70: Ford
A71: Ford(Insight)
A72: Gardner Denver(PARC)
A73: Gentex
A74: Gilead Sciences(ZS Associates)
A75: Global Partners
A76: Global Partners(Oracle)
... A193: ZF
